Workbook

Sheet Eingaben
A1: 🏠 Immobilien Portfolio – Eingaben
A2: Alle Werte hier erfassen. Dashboard, Cashflow, Steuer & AfA sowie Verkauf berechnen sich automatisch.
A4: Globale Einstellungen (Steuer)
B5: Haushaltseinkommen p.a. (€) | D5: 0 | F5: Basis-ZvE (Haushalt, nach Kinderfreibetrag)
B6: Verheiratet? | D6: Nein | F6: =MAX(0,D5-D7*D8) -> 0
B7: Anzahl Kinder | D7: 0
B8: Kinderfreibetrag je Kind (€) | D8: 9756
B9: Pauschaler Steuersatz (ohne Haushaltseinkommen) | D9: 0.4
B10: Hinweis: gilt für alle Immobilien; jede Immobilie wird isoliert gegen dieses Haushaltseinkommen gerechnet (vereinfachte Modellrechnung).
A12: Immobilien
A13: Nr. | B13: Name | C13: Kaufjahr | D13: Aktueller Marktwert (€) | E13: Aktuelle Restschuld (€) | F13: Kaufpreis (€) | G13: Wohnfläche (m²) | H13: Mieteingabe | I13: Miete pro m² (€) | J13: Miete absolut (€/Monat) | K13: Mietsteigerung p.a. (%) | L13: Kaufnebenkosten (%) | M13: Nicht umlagef. Kosten p.a. (€) | N13: Eigenkapital gesamt (€) | O13: Sollzins p.a. (%) | P13: Tilgung p.a. (%) | Q13: Lineare AfA (%) | R13: Neubau | S13: Degressive AfA aktiv | T13: Degressive AfA (%) | U13: Sonder-AfA aktiv | V13: Sonder-AfA (%) | W13: Sonder-AfA Jahre | X13: Notizen | Z13: Kaufneben- kosten (€) | AA13: Gesamt- kosten (€) | AB13: Darlehen (€) | AC13: Mtl. Kalt- miete (€) | AD13: Gebäudewert / AfA-Basis (€) | AE13: Mtl. Annu- ität (€) | AF13: Zinssatz mtl. | AG13: Aktuelles Modelljahr
A14: 1 | B14: Musterwohnung Berlin | C14: 2024 | D14: 250000 | E14: 248000 | F14: 248000 | G14: 62 | H14: pro m² | I14: 12.42 | J14: 770 | K14: 0.02 | L14: 0.07 | M14: 1200 | N14: 17360 | O14: 0.042 | P14: 0.01 | Q14: 0.02 | R14: Nein | S14: Nein | T14: 0.05 | U14: Nein | V14: 0.05 | W14: 4 | X14: Beispielobjekt – bitte anpassen oder löschen | Z14: =IF($B14="","",F14*L14) -> 17360 | AA14: =IF($B14="","",F14+Z14) -> 265360 | AB14: =IF($B14="","",MAX(0,AA14-N14)) -> 248000 | AC14: =IF($B14="","",IF(H14="absolut",J14,G14*I14)) -> 770.04 | AD14: =IF($B14="","",F14*0.8) -> 198400 | AE14: =IF($B14="","",IF(AB14=0,0,AB14*(O14+P14)/12)) -> 1074.6667 | AF14: =IF($B14="","",O14/12) -> 0.0035 | AG14: =IF($B14="","",MIN(10,MAX(1,YEAR(TODAY())-C14+1))) -> 3
A15: 2 | Z15: =IF($B15="","",F15*L15) | AA15: =IF($B15="","",F15+Z15) | AB15: =IF($B15="","",MAX(0,AA15-N15)) | AC15: =IF($B15="","",IF(H15="absolut",J15,G15*I15)) | AD15: =IF($B15="","",F15*0.8) | AE15: =IF($B15="","",IF(AB15=0,0,AB15*(O15+P15)/12)) | AF15: =IF($B15="","",O15/12) | AG15: =IF($B15="","",MIN(10,MAX(1,YEAR(TODAY())-C15+1)))
A16: 3 | Z16: =IF($B16="","",F16*L16) | AA16: =IF($B16="","",F16+Z16) | AB16: =IF($B16="","",MAX(0,AA16-N16)) | AC16: =IF($B16="","",IF(H16="absolut",J16,G16*I16)) | AD16: =IF($B16="","",F16*0.8) | AE16: =IF($B16="","",IF(AB16=0,0,AB16*(O16+P16)/12)) | AF16: =IF($B16="","",O16/12) | AG16: =IF($B16="","",MIN(10,MAX(1,YEAR(TODAY())-C16+1)))
A17: 4 | Z17: =IF($B17="","",F17*L17) | AA17: =IF($B17="","",F17+Z17) | AB17: =IF($B17="","",MAX(0,AA17-N17)) | AC17: =IF($B17="","",IF(H17="absolut",J17,G17*I17)) | AD17: =IF($B17="","",F17*0.8) | AE17: =IF($B17="","",IF(AB17=0,0,AB17*(O17+P17)/12)) | AF17: =IF($B17="","",O17/12) | AG17: =IF($B17="","",MIN(10,MAX(1,YEAR(TODAY())-C17+1)))
A18: 5 | Z18: =IF($B18="","",F18*L18) | AA18: =IF($B18="","",F18+Z18) | AB18: =IF($B18="","",MAX(0,AA18-N18)) | AC18: =IF($B18="","",IF(H18="absolut",J18,G18*I18)) | AD18: =IF($B18="","",F18*0.8) | AE18: =IF($B18="","",IF(AB18=0,0,AB18*(O18+P18)/12)) | AF18: =IF($B18="","",O18/12) | AG18: =IF($B18="","",MIN(10,MAX(1,YEAR(TODAY())-C18+1)))
A19: 6 | Z19: =IF($B19="","",F19*L19) | AA19: =IF($B19="","",F19+Z19) | AB19: =IF($B19="","",MAX(0,AA19-N19)) | AC19: =IF($B19="","",IF(H19="absolut",J19,G19*I19)) | AD19: =IF($B19="","",F19*0.8) | AE19: =IF($B19="","",IF(AB19=0,0,AB19*(O19+P19)/12)) | AF19: =IF($B19="","",O19/12) | AG19: =IF($B19="","",MIN(10,MAX(1,YEAR(TODAY())-C19+1)))
A20: 7 | Z20: =IF($B20="","",F20*L20) | AA20: =IF($B20="","",F20+Z20) | AB20: =IF($B20="","",MAX(0,AA20-N20)) | AC20: =IF($B20="","",IF(H20="absolut",J20,G20*I20)) | AD20: =IF($B20="","",F20*0.8) | AE20: =IF($B20="","",IF(AB20=0,0,AB20*(O20+P20)/12)) | AF20: =IF($B20="","",O20/12) | AG20: =IF($B20="","",MIN(10,MAX(1,YEAR(TODAY())-C20+1)))
A21: 8 | Z21: =IF($B21="","",F21*L21) | AA21: =IF($B21="","",F21+Z21) | AB21: =IF($B21="","",MAX(0,AA21-N21)) | AC21: =IF($B21="","",IF(H21="absolut",J21,G21*I21)) | AD21: =IF($B21="","",F21*0.8) | AE21: =IF($B21="","",IF(AB21=0,0,AB21*(O21+P21)/12)) | AF21: =IF($B21="","",O21/12) | AG21: =IF($B21="","",MIN(10,MAX(1,YEAR(TODAY())-C21+1)))
A22: 9 | Z22: =IF($B22="","",F22*L22) | AA22: =IF($B22="","",F22+Z22) | AB22: =IF($B22="","",MAX(0,AA22-N22)) | AC22: =IF($B22="","",IF(H22="absolut",J22,G22*I22)) | AD22: =IF($B22="","",F22*0.8) | AE22: =IF($B22="","",IF(AB22=0,0,AB22*(O22+P22)/12)) | AF22: =IF($B22="","",O22/12) | AG22: =IF($B22="","",MIN(10,MAX(1,YEAR(TODAY())-C22+1)))
A23: 10 | Z23: =IF($B23="","",F23*L23) | AA23: =IF($B23="","",F23+Z23) | AB23: =IF($B23="","",MAX(0,AA23-N23)) | AC23: =IF($B23="","",IF(H23="absolut",J23,G23*I23)) | AD23: =IF($B23="","",F23*0.8) | AE23: =IF($B23="","",IF(AB23=0,0,AB23*(O23+P23)/12)) | AF23: =IF($B23="","",O23/12) | AG23: =IF($B23="","",MIN(10,MAX(1,YEAR(TODAY())-C23+1)))

Sheet Dashboard
A1: 📊 Dashboard – Portfolio-Übersicht
A2: Aggregierte Kennzahlen und Diagramme über alle Immobilien. Aktualisiert sich automatisch aus 'Eingaben'.
B4: Gesamtwert | E4: Gesamtrestschuld | H4: Nettovermögen | K4: Anzahl Immobilien
B5: =SUM($C$46:$C$55) -> 250000 | E5: =SUM($D$46:$D$55) -> 248000 | H5: =SUM($C$46:$C$55)-SUM($D$46:$D$55) -> 2000 | K5: =COUNTIF($B$46:$B$55,"?*") -> 1
B7: Mieteinnahmen p.a. | E7: Ausgaben p.a. | H7: Cashflow p.a. | K7: Ø Bruttorendite
B8: =SUM($G$46:$G$55) -> 9613.7954 | E8: =SUM($H$46:$H$55) -> 14096 | H8: =SUM($I$46:$I$55) -> -2681.9029 | K8: =IFERROR(SUM($G$46:$G$55)/SUM($C$46:$C$55),0) -> 0.038455182
A11: Diagramme
A12: Diagramme aktualisieren sich automatisch, sobald weitere Immobilien in 'Eingaben' erfasst werden.
A44: Berechnungstabelle (Basis für KPIs & Diagramme)
A45: Nr. | B45: Immobilie | C45: Wert (€) | D45: Restschuld (€) | E45: Eigenkapital (€) | F45: Modelljahr | G45: Miete p.a. (€) | H45: Ausgaben p.a. (€) | I45: Cashflow p.a. (€) | J45: Bruttorendite | K45: Beste IRR | L45: CF positiv (€) | M45: CF negativ (€)
A46: 1 | B46: =IF(Eingaben!$B$14="","",Eingaben!$B$14) -> Musterwohnung Berlin | C46: =IF(Eingaben!$B$14="",0,Eingaben!$D$14) -> 250000 | D46: =IF(Eingaben!$B$14="",0,Eingaben!$E$14) -> 248000 | E46: =C46-D46 -> 2000 | F46: =IF(Eingaben!$B$14="","",Eingaben!$AG$14) -> 3 | G46: =IF(Eingaben!$B$14="",0,INDEX(Cashflow!$E$5:$E$104,(A46-1)*10+F46)) -> 9613.7954 | H46: =IF(Eingaben!$B$14="",0,INDEX(Cashflow!$I$5:$I$104,(A46-1)*10+F46)+INDEX(Cashflow!$K$5:$K$104,(A46-1)*10+F46)) -> 14096 | I46: =IF(Eingaben!$B$14="",0,INDEX(Cashflow!$M$5:$M$104,(A46-1)*10+F46)) -> -2681.9029 | J46: =IF(OR(Eingaben!$B$14="",C46=0),0,G46/C46) -> 0.038455182 | K46: =IF(Eingaben!$B$14="",0,_xlfn.MAXIFS(Verkauf!$J$5:$J$34,Verkauf!$A$5:$A$34,A46)) -> 0.098674431 | L46: =IF(I46>=0,I46,0) -> 0 | M46: =IF(I46<0,I46,0) -> -2681.9029
A47: 2 | B47: =IF(Eingaben!$B$15="","",Eingaben!$B$15) | C47: =IF(Eingaben!$B$15="",0,Eingaben!$D$15) -> 0 | D47: =IF(Eingaben!$B$15="",0,Eingaben!$E$15) -> 0 | E47: =C47-D47 -> 0 | F47: =IF(Eingaben!$B$15="","",Eingaben!$AG$15) | G47: =IF(Eingaben!$B$15="",0,INDEX(Cashflow!$E$5:$E$104,(A47-1)*10+F47)) -> 0 | H47: =IF(Eingaben!$B$15="",0,INDEX(Cashflow!$I$5:$I$104,(A47-1)*10+F47)+INDEX(Cashflow!$K$5:$K$104,(A47-1)*10+F47)) -> 0 | I47: =IF(Eingaben!$B$15="",0,INDEX(Cashflow!$M$5:$M$104,(A47-1)*10+F47)) -> 0 | J47: =IF(OR(Eingaben!$B$15="",C47=0),0,G47/C47) -> 0 | K47: =IF(Eingaben!$B$15="",0,_xlfn.MAXIFS(Verkauf!$J$5:$J$34,Verkauf!$A$5:$A$34,A47)) -> 0 | L47: =IF(I47>=0,I47,0) -> 0 | M47: =IF(I47<0,I47,0) -> 0
A48: 3 | B48: =IF(Eingaben!$B$16="","",Eingaben!$B$16) | C48: =IF(Eingaben!$B$16="",0,Eingaben!$D$16) -> 0 | D48: =IF(Eingaben!$B$16="",0,Eingaben!$E$16) -> 0 | E48: =C48-D48 -> 0 | F48: =IF(Eingaben!$B$16="","",Eingaben!$AG$16) | G48: =IF(Eingaben!$B$16="",0,INDEX(Cashflow!$E$5:$E$104,(A48-1)*10+F48)) -> 0 | H48: =IF(Eingaben!$B$16="",0,INDEX(Cashflow!$I$5:$I$104,(A48-1)*10+F48)+INDEX(Cashflow!$K$5:$K$104,(A48-1)*10+F48)) -> 0 | I48: =IF(Eingaben!$B$16="",0,INDEX(Cashflow!$M$5:$M$104,(A48-1)*10+F48)) -> 0 | J48: =IF(OR(Eingaben!$B$16="",C48=0),0,G48/C48) -> 0 | K48: =IF(Eingaben!$B$16="",0,_xlfn.MAXIFS(Verkauf!$J$5:$J$34,Verkauf!$A$5:$A$34,A48)) -> 0 | L48: =IF(I48>=0,I48,0) -> 0 | M48: =IF(I48<0,I48,0) -> 0
A49: 4 | B49: =IF(Eingaben!$B$17="","",Eingaben!$B$17) | C49: =IF(Eingaben!$B$17="",0,Eingaben!$D$17) -> 0 | D49: =IF(Eingaben!$B$17="",0,Eingaben!$E$17) -> 0 | E49: =C49-D49 -> 0 | F49: =IF(Eingaben!$B$17="","",Eingaben!$AG$17) | G49: =IF(Eingaben!$B$17="",0,INDEX(Cashflow!$E$5:$E$104,(A49-1)*10+F49)) -> 0 | H49: =IF(Eingaben!$B$17="",0,INDEX(Cashflow!$I$5:$I$104,(A49-1)*10+F49)+INDEX(Cashflow!$K$5:$K$104,(A49-1)*10+F49)) -> 0 | I49: =IF(Eingaben!$B$17="",0,INDEX(Cashflow!$M$5:$M$104,(A49-1)*10+F49)) -> 0 | J49: =IF(OR(Eingaben!$B$17="",C49=0),0,G49/C49) -> 0 | K49: =IF(Eingaben!$B$17="",0,_xlfn.MAXIFS(Verkauf!$J$5:$J$34,Verkauf!$A$5:$A$34,A49)) -> 0 | L49: =IF(I49>=0,I49,0) -> 0 | M49: =IF(I49<0,I49,0) -> 0
A50: 5 | B50: =IF(Eingaben!$B$18="","",Eingaben!$B$18) | C50: =IF(Eingaben!$B$18="",0,Eingaben!$D$18) -> 0 | D50: =IF(Eingaben!$B$18="",0,Eingaben!$E$18) -> 0 | E50: =C50-D50 -> 0 | F50: =IF(Eingaben!$B$18="","",Eingaben!$AG$18) | G50: =IF(Eingaben!$B$18="",0,INDEX(Cashflow!$E$5:$E$104,(A50-1)*10+F50)) -> 0 | H50: =IF(Eingaben!$B$18="",0,INDEX(Cashflow!$I$5:$I$104,(A50-1)*10+F50)+INDEX(Cashflow!$K$5:$K$104,(A50-1)*10+F50)) -> 0 | I50: =IF(Eingaben!$B$18="",0,INDEX(Cashflow!$M$5:$M$104,(A50-1)*10+F50)) -> 0 | J50: =IF(OR(Eingaben!$B$18="",C50=0),0,G50/C50) -> 0 | K50: =IF(Eingaben!$B$18="",0,_xlfn.MAXIFS(Verkauf!$J$5:$J$34,Verkauf!$A$5:$A$34,A50)) -> 0 | L50: =IF(I50>=0,I50,0) -> 0 | M50: =IF(I50<0,I50,0) -> 0
A51: Modellgrenzen: vereinfachte Modellrechnung, keine Steuer-, Rechts- oder Anlageberatung. 'Wert' und 'Restschuld' sind manuell in 'Eingaben' zu pflegen (tatsächliche aktuelle Werte); alle übrigen Kennzahlen basieren auf den Modellannahmen (Kaufpreis, Zins, Miete, AfA etc.).
A53: 8 | B53: =IF(Eingaben!$B$21="","",Eingaben!$B$21) | C53: =IF(Eingaben!$B$21="",0,Eingaben!$D$21) -> 0 | D53: =IF(Eingaben!$B$21="",0,Eingaben!$E$21) -> 0 | E53: =C53-D53 -> 0 | F53: =IF(Eingaben!$B$21="","",Eingaben!$AG$21) | G53: =IF(Eingaben!$B$21="",0,INDEX(Cashflow!$E$5:$E$104,(A53-1)*10+F53)) -> 0 | H53: =IF(Eingaben!$B$21="",0,INDEX(Cashflow!$I$5:$I$104,(A53-1)*10+F53)+INDEX(Cashflow!$K$5:$K$104,(A53-1)*10+F53)) -> 0 | I53: =IF(Eingaben!$B$21="",0,INDEX(Cashflow!$M$5:$M$104,(A53-1)*10+F53)) -> 0 | J53: =IF(OR(Eingaben!$B$21="",C53=0),0,G53/C53) -> 0 | K53: =IF(Eingaben!$B$21="",0,_xlfn.MAXIFS(Verkauf!$J$5:$J$34,Verkauf!$A$5:$A$34,A53)) -> 0 | L53: =IF(I53>=0,I53,0) -> 0 | M53: =IF(I53<0,I53,0) -> 0
A54: 9 | B54: =IF(Eingaben!$B$22="","",Eingaben!$B$22) | C54: =IF(Eingaben!$B$22="",0,Eingaben!$D$22) -> 0 | D54: =IF(Eingaben!$B$22="",0,Eingaben!$E$22) -> 0 | E54: =C54-D54 -> 0 | F54: =IF(Eingaben!$B$22="","",Eingaben!$AG$22) | G54: =IF(Eingaben!$B$22="",0,INDEX(Cashflow!$E$5:$E$104,(A54-1)*10+F54)) -> 0 | H54: =IF(Eingaben!$B$22="",0,INDEX(Cashflow!$I$5:$I$104,(A54-1)*10+F54)+INDEX(Cashflow!$K$5:$K$104,(A54-1)*10+F54)) -> 0 | I54: =IF(Eingaben!$B$22="",0,INDEX(Cashflow!$M$5:$M$104,(A54-1)*10+F54)) -> 0 | J54: =IF(OR(Eingaben!$B$22="",C54=0),0,G54/C54) -> 0 | K54: =IF(Eingaben!$B$22="",0,_xlfn.MAXIFS(Verkauf!$J$5:$J$34,Verkauf!$A$5:$A$34,A54)) -> 0 | L54: =IF(I54>=0,I54,0) -> 0 | M54: =IF(I54<0,I54,0) -> 0
A55: 10 | B55: =IF(Eingaben!$B$23="","",Eingaben!$B$23) | C55: =IF(Eingaben!$B$23="",0,Eingaben!$D$23) -> 0 | D55: =IF(Eingaben!$B$23="",0,Eingaben!$E$23) -> 0 | E55: =C55-D55 -> 0 | F55: =IF(Eingaben!$B$23="","",Eingaben!$AG$23) | G55: =IF(Eingaben!$B$23="",0,INDEX(Cashflow!$E$5:$E$104,(A55-1)*10+F55)) -> 0 | H55: =IF(Eingaben!$B$23="",0,INDEX(Cashflow!$I$5:$I$104,(A55-1)*10+F55)+INDEX(Cashflow!$K$5:$K$104,(A55-1)*10+F55)) -> 0 | I55: =IF(Eingaben!$B$23="",0,INDEX(Cashflow!$M$5:$M$104,(A55-1)*10+F55)) -> 0 | J55: =IF(OR(Eingaben!$B$23="",C55=0),0,G55/C55) -> 0 | K55: =IF(Eingaben!$B$23="",0,_xlfn.MAXIFS(Verkauf!$J$5:$J$34,Verkauf!$A$5:$A$34,A55)) -> 0 | L55: =IF(I55>=0,I55,0) -> 0 | M55: =IF(I55<0,I55,0) -> 0

Sheet Cashflow
A1: 📈 Cashflow – 10-Jahres-Verlauf je Immobilie
A2: Ein Block pro Immobilie (Jahr 1–10). Werte werden automatisch aus 'Eingaben' und 'Steuer & AfA' berechnet.
A4: Nr. | B4: Immobilie | C4: Jahr | D4: Restschuld Jahresanfang (€) | E4: Miete p.a. (€) | F4: Miete mtl. (€) | G4: Zinsen p.a. (€) | H4: Tilgung p.a. (€) | I4: Bankrate p.a. (€) | J4: Restschuld Jahresende (€) | K4: Nicht umlagef. Kosten (€) | L4: Steuerwirkung (€) | M4: Cashflow p.a. (€) | N4: Cashflow mtl. (€) | O4: Zinssatz mtl. (Lookup) | P4: Annuität mtl. (Lookup)
A5: 1 | B5: =IF(Eingaben!$B$14="","",Eingaben!$B$14) -> Musterwohnung Berlin | C5: 1 | D5: =IF(Eingaben!$B$14="","",Eingaben!$AB$14) -> 248000 | E5: =IF(Eingaben!$B$14="","",Eingaben!$AC$14*12*(1+Eingaben!$K$14)^(1-1)) -> 9240.48 | F5: =IF(Eingaben!$B$14="","",E5/12) -> 770.04 | G5: =IF(Eingaben!$B$14="","",I5-H5) -> 10367.699 | H5: =IF(Eingaben!$B$14="","",D5-J5) -> 2528.3014 | I5: =IF(Eingaben!$B$14="","",P5*12) -> 12896 | J5: =IF(Eingaben!$B$14="","",IF(O5=0,MAX(0,D5-P5*12),MAX(0,D5*(1+O5)^12-P5*((1+O5)^12-1)/O5))) -> 245471.7 | K5: =IF(Eingaben!$B$14="","",Eingaben!$M$14) -> 1200 | L5: =IF(Eingaben!$B$14="","",'Steuer & AfA'!L5) -> 2038.0874 | M5: =IF(Eingaben!$B$14="","",E5+L5-I5-K5) -> -2817.4326 | N5: =IF(Eingaben!$B$14="","",M5/12) -> -234.78605 | O5: =IF(Eingaben!$B$14="","",Eingaben!$AF$14) -> 0.0035 | P5: =IF(Eingaben!$B$14="","",Eingaben!$AE$14) -> 1074.6667
A6: 1 | B6: =IF(Eingaben!$B$14="","",Eingaben!$B$14) -> Musterwohnung Berlin | C6: 2 | D6: =IF(Eingaben!$B$14="","",J5) -> 245471.7 | E6: =IF(Eingaben!$B$14="","",Eingaben!$AC$14*12*(1+Eingaben!$K$14)^(2-1)) -> 9425.2896 | F6: =IF(Eingaben!$B$14="","",E6/12) -> 785.4408 | G6: =IF(Eingaben!$B$14="","",I6-H6) -> 10259.442 | H6: =IF(Eingaben!$B$14="","",D6-J6) -> 2636.5582 | I6: =IF(Eingaben!$B$14="","",P6*12) -> 12896 | J6: =IF(Eingaben!$B$14="","",IF(O6=0,MAX(0,D6-P6*12),MAX(0,D6*(1+O6)^12-P6*((1+O6)^12-1)/O6))) -> 242835.14 | K6: =IF(Eingaben!$B$14="","",Eingaben!$M$14) -> 1200 | L6: =IF(Eingaben!$B$14="","",'Steuer & AfA'!L6) -> 1920.8609 | M6: =IF(Eingaben!$B$14="","",E6+L6-I6-K6) -> -2749.8495 | N6: =IF(Eingaben!$B$14="","",M6/12) -> -229.15413 | O6: =IF(Eingaben!$B$14="","",Eingaben!$AF$14) -> 0.0035 | P6: =IF(Eingaben!$B$14="","",Eingaben!$AE$14) -> 1074.6667
A7: 1 | B7: =IF(Eingaben!$B$14="","",Eingaben!$B$14) -> Musterwohnung Berlin | C7: 3 | D7: =IF(Eingaben!$B$14="","",J6) -> 242835.14 | E7: =IF(Eingaben!$B$14="","",Eingaben!$AC$14*12*(1+Eingaben!$K$14)^(3-1)) -> 9613.7954 | F7: =IF(Eingaben!$B$14="","",E7/12) -> 801.14962 | G7: =IF(Eingaben!$B$14="","",I7-H7) -> 10146.55 | H7: =IF(Eingaben!$B$14="","",D7-J7) -> 2749.4504 | I7: =IF(Eingaben!$B$14="","",P7*12) -> 12896 | J7: =IF(Eingaben!$B$14="","",IF(O7=0,MAX(0,D7-P7*12),MAX(0,D7*(1+O7)^12-P7*((1+O7)^12-1)/O7))) -> 240085.69 | K7: =IF(Eingaben!$B$14="","",Eingaben!$M$14) -> 1200 | L7: =IF(Eingaben!$B$14="","",'Steuer & AfA'!L7) -> 1800.3017 | M7: =IF(Eingaben!$B$14="","",E7+L7-I7-K7) -> -2681.9029 | N7: =IF(Eingaben!$B$14="","",M7/12) -> -223.49191 | O7: =IF(Eingaben!$B$14="","",Eingaben!$AF$14) -> 0.0035 | P7: =IF(Eingaben!$B$14="","",Eingaben!$AE$14) -> 1074.6667
A8: 1 | B8: =IF(Eingaben!$B$14="","",Eingaben!$B$14) -> Musterwohnung Berlin | C8: 4 | D8: =IF(Eingaben!$B$14="","",J7) -> 240085.69 | E8: =IF(Eingaben!$B$14="","",Eingaben!$AC$14*12*(1+Eingaben!$K$14)^(4-1)) -> 9806.0713 | F8: =IF(Eingaben!$B$14="","",E8/12) -> 817.17261 | G8: =IF(Eingaben!$B$14="","",I8-H8) -> 10028.824 | H8: =IF(Eingaben!$B$14="","",D8-J8) -> 2867.1764 | I8: =IF(Eingaben!$B$14="","",P8*12) -> 12896 | J8: =IF(Eingaben!$B$14="","",IF(O8=0,MAX(0,D8-P8*12),MAX(0,D8*(1+O8)^12-P8*((1+O8)^12-1)/O8))) -> 237218.51 | K8: =IF(Eingaben!$B$14="","",Eingaben!$M$14) -> 1200 | L8: =IF(Eingaben!$B$14="","",'Steuer & AfA'!L8) -> 1676.3009 | M8: =IF(Eingaben!$B$14="","",E8+L8-I8-K8) -> -2613.6278 | N8: =IF(Eingaben!$B$14="","",M8/12) -> -217.80231 | O8: =IF(Eingaben!$B$14="","",Eingaben!$AF$14) -> 0.0035 | P8: =IF(Eingaben!$B$14="","",Eingaben!$AE$14) -> 1074.6667
A9: 1 | B9: =IF(Eingaben!$B$14="","",Eingaben!$B$14) -> Musterwohnung Berlin | C9: 5 | D9: =IF(Eingaben!$B$14="","",J8) -> 237218.51 | E9: =IF(Eingaben!$B$14="","",Eingaben!$AC$14*12*(1+Eingaben!$K$14)^(5-1)) -> 10002.193 | F9: =IF(Eingaben!$B$14="","",E9/12) -> 833.51606 | G9: =IF(Eingaben!$B$14="","",I9-H9) -> 9906.0569 | H9: =IF(Eingaben!$B$14="","",D9-J9) -> 2989.9431 | I9: =IF(Eingaben!$B$14="","",P9*12) -> 12896 | J9: =IF(Eingaben!$B$14="","",IF(O9=0,MAX(0,D9-P9*12),MAX(0,D9*(1+O9)^12-P9*((1+O9)^12-1)/O9))) -> 234228.57 | K9: =IF(Eingaben!$B$14="","",Eingaben!$M$14) -> 1200 | L9: =IF(Eingaben!$B$14="","",'Steuer & AfA'!L9) -> 1548.7457 | M9: =IF(Eingaben!$B$14="","",E9+L9-I9-K9) -> -2545.0616 | N9: =IF(Eingaben!$B$14="","",M9/12) -> -212.08847 | O9: =IF(Eingaben!$B$14="","",Eingaben!$AF$14) -> 0.0035 | P9: =IF(Eingaben!$B$14="","",Eingaben!$AE$14) -> 1074.6667
A10: 1 | B10: =IF(Eingaben!$B$14="","",Eingaben!$B$14) -> Musterwohnung Berlin | C10: 6 | D10: =IF(Eingaben!$B$14="","",J9) -> 234228.57 | E10: =IF(Eingaben!$B$14="","",Eingaben!$AC$14*12*(1+Eingaben!$K$14)^(6-1)) -> 10202.237 | F10: =IF(Eingaben!$B$14="","",E10/12) -> 850.18638 | G10: =IF(Eingaben!$B$14="","",I10-H10) -> 9778.0335 | H10: =IF(Eingaben!$B$14="","",D10-J10) -> 3117.9665 | I10: =IF(Eingaben!$B$14="","",P10*12) -> 12896 | J10: =IF(Eingaben!$B$14="","",IF(O10=0,MAX(0,D10-P10*12),MAX(0,D10*(1+O10)^12-P10*((1+O10)^12-1)/O10))) -> 231110.6 | K10: =IF(Eingaben!$B$14="","",Eingaben!$M$14) -> 1200 | L10: =IF(Eingaben!$B$14="","",'Steuer & AfA'!L10) -> 1417.5188 | M10: =IF(Eingaben!$B$14="","",E10+L10-I10-K10) -> -2476.2447 | N10: =IF(Eingaben!$B$14="","",M10/12) -> -206.35372 | O10: =IF(Eingaben!$B$14="","",Eingaben!$AF$14) -> 0.0035 | P10: =IF(Eingaben!$B$14="","",Eingaben!$AE$14) -> 1074.6667
A11: 1 | B11: =IF(Eingaben!$B$14="","",Eingaben!$B$14) -> Musterwohnung Berlin | C11: 7 | D11: =IF(Eingaben!$B$14="","",J10) -> 231110.6 | E11: =IF(Eingaben!$B$14="","",Eingaben!$AC$14*12*(1+Eingaben!$K$14)^(7-1)) -> 10406.281 | F11: =IF(Eingaben!$B$14="","",E11/12) -> 867.19011 | G11: =IF(Eingaben!$B$14="","",I11-H11) -> 9644.5283 | H11: =IF(Eingaben!$B$14="","",D11-J11) -> 3251.4717 | I11: =IF(Eingaben!$B$14="","",P11*12) -> 12896 | J11: =IF(Eingaben!$B$14="","",IF(O11=0,MAX(0,D11-P11*12),MAX(0,D11*(1+O11)^12-P11*((1+O11)^12-1)/O11))) -> 227859.13 | K11: =IF(Eingaben!$B$14="","",Eingaben!$M$14) -> 1200 | L11: =IF(Eingaben!$B$14="","",'Steuer & AfA'!L11) -> 1282.4988 | M11: =IF(Eingaben!$B$14="","",E11+L11-I11-K11) -> -2407.2199 | N11: =IF(Eingaben!$B$14="","",M11/12) -> -200.60166 | O11: =IF(Eingaben!$B$14="","",Eingaben!$AF$14) -> 0.0035 | P11: =IF(Eingaben!$B$14="","",Eingaben!$AE$14) -> 1074.6667
A12: 1 | B12: =IF(Eingaben!$B$14="","",Eingaben!$B$14) -> Musterwohnung Berlin | C12: 8 | D12: =IF(Eingaben!$B$14="","",J11) -> 227859.13 | E12: =IF(Eingaben!$B$14="","",Eingaben!$AC$14*12*(1+Eingaben!$K$14)^(8-1)) -> 10614.407 | F12: =IF(Eingaben!$B$14="","",E12/12) -> 884.53391 | G12: =IF(Eingaben!$B$14="","",I12-H12) -> 9505.3068 | H12: =IF(Eingaben!$B$14="","",D12-J12) -> 3390.6932 | I12: =IF(Eingaben!$B$14="","",P12*12) -> 12896 | J12: =IF(Eingaben!$B$14="","",IF(O12=0,MAX(0,D12-P12*12),MAX(0,D12*(1+O12)^12-P12*((1+O12)^12-1)/O12))) -> 224468.44 | K12: =IF(Eingaben!$B$14="","",Eingaben!$M$14) -> 1200 | L12: =IF(Eingaben!$B$14="","",'Steuer & AfA'!L12) -> 1143.5599 | M12: =IF(Eingaben!$B$14="","",E12+L12-I12-K12) -> -2338.0331 | N12: =IF(Eingaben!$B$14="","",M12/12) -> -194.83609 | O12: =IF(Eingaben!$B$14="","",Eingaben!$AF$14) -> 0.0035 | P12: =IF(Eingaben!$B$14="","",Eingaben!$AE$14) -> 1074.6667
A13: 1 | B13: =IF(Eingaben!$B$14="","",Eingaben!$B$14) -> Musterwohnung Berlin | C13: 9 | D13: =IF(Eingaben!$B$14="","",J12) -> 224468.44 | E13: =IF(Eingaben!$B$14="","",Eingaben!$AC$14*12*(1+Eingaben!$K$14)^(9-1)) -> 10826.695 | F13: =IF(Eingaben!$B$14="","",E13/12) -> 902.22459 | G13: =IF(Eingaben!$B$14="","",I13-H13) -> 9360.1241 | H13: =IF(Eingaben!$B$14="","",D13-J13) -> 3535.8759 | I13: =IF(Eingaben!$B$14="","",P13*12) -> 12896 | J13: =IF(Eingaben!$B$14="","",IF(O13=0,MAX(0,D13-P13*12),MAX(0,D13*(1+O13)^12-P13*((1+O13)^12-1)/O13))) -> 220932.56 | K13: =IF(Eingaben!$B$14="","",Eingaben!$M$14) -> 1200 | L13: =IF(Eingaben!$B$14="","",'Steuer & AfA'!L13) -> 1000.5716 | M13: =IF(Eingaben!$B$14="","",E13+L13-I13-K13) -> -2268.7333 | N13: =IF(Eingaben!$B$14="","",M13/12) -> -189.06111 | O13: =IF(Eingaben!$B$14="","",Eingaben!$AF$14) -> 0.0035 | P13: =IF(Eingaben!$B$14="","",Eingaben!$AE$14) -> 1074.6667
A14: 1 | B14: =IF(Eingaben!$B$14="","",Eingaben!$B$14) -> Musterwohnung Berlin | C14: 10 | D14: =IF(Eingaben!$B$14="","",J13) -> 220932.56 | E14: =IF(Eingaben!$B$14="","",Eingaben!$AC$14*12*(1+Eingaben!$K$14)^(10-1)) -> 11043.229 | F14: =IF(Eingaben!$B$14="","",E14/12) -> 920.26908 | G14: =IF(Eingaben!$B$14="","",I14-H14) -> 9208.7249 | H14: =IF(Eingaben!$B$14="","",D14-J14) -> 3687.2751 | I14: =IF(Eingaben!$B$14="","",P14*12) -> 12896 | J14: =IF(Eingaben!$B$14="","",IF(O14=0,MAX(0,D14-P14*12),MAX(0,D14*(1+O14)^12-P14*((1+O14)^12-1)/O14))) -> 217245.29 | K14: =IF(Eingaben!$B$14="","",Eingaben!$M$14) -> 1200 | L14: =IF(Eingaben!$B$14="","",'Steuer & AfA'!L14) -> 853.39838 | M14: =IF(Eingaben!$B$14="","",E14+L14-I14-K14) -> -2199.3726 | N14: =IF(Eingaben!$B$14="","",M14/12) -> -183.28105 | O14: =IF(Eingaben!$B$14="","",Eingaben!$AF$14) -> 0.0035 | P14: =IF(Eingaben!$B$14="","",Eingaben!$AE$14) -> 1074.6667
A15: 2 | B15: =IF(Eingaben!$B$15="","",Eingaben!$B$15) | C15: 1 | D15: =IF(Eingaben!$B$15="","",Eingaben!$AB$15) | E15: =IF(Eingaben!$B$15="","",Eingaben!$AC$15*12*(1+Eingaben!$K$15)^(1-1)) | F15: =IF(Eingaben!$B$15="","",E15/12) | G15: =IF(Eingaben!$B$15="","",I15-H15) | H15: =IF(Eingaben!$B$15="","",D15-J15) | I15: =IF(Eingaben!$B$15="","",P15*12) | J15: =IF(Eingaben!$B$15="","",IF(O15=0,MAX(0,D15-P15*12),MAX(0,D15*(1+O15)^12-P15*((1+O15)^12-1)/O15))) | K15: =IF(Eingaben!$B$15="","",Eingaben!$M$15) | L15: =IF(Eingaben!$B$15="","",'Steuer & AfA'!L15) | M15: =IF(Eingaben!$B$15="","",E15+L15-I15-K15) | N15: =IF(Eingaben!$B$15="","",M15/12) | O15: =IF(Eingaben!$B$15="","",Eingaben!$AF$15) | P15: =IF(Eingaben!$B$15="","",Eingaben!$AE$15)
A16: 2 | B16: =IF(Eingaben!$B$15="","",Eingaben!$B$15) | C16: 2 | D16: =IF(Eingaben!$B$15="","",J15) | E16: =IF(Eingaben!$B$15="","",Eingaben!$AC$15*12*(1+Eingaben!$K$15)^(2-1)) | F16: =IF(Eingaben!$B$15="","",E16/12) | G16: =IF(Eingaben!$B$15="","",I16-H16) | H16: =IF(Eingaben!$B$15="","",D16-J16) | I16: =IF(Eingaben!$B$15="","",P16*12) | J16: =IF(Eingaben!$B$15="","",IF(O16=0,MAX(0,D16-P16*12),MAX(0,D16*(1+O16)^12-P16*((1+O16)^12-1)/O16))) | K16: =IF(Eingaben!$B$15="","",Eingaben!$M$15) | L16: =IF(Eingaben!$B$15="","",'Steuer & AfA'!L16) | M16: =IF(Eingaben!$B$15="","",E16+L16-I16-K16) | N16: =IF(Eingaben!$B$15="","",M16/12) | O16: =IF(Eingaben!$B$15="","",Eingaben!$AF$15) | P16: =IF(Eingaben!$B$15="","",Eingaben!$AE$15)
A17: 2 | B17: =IF(Eingaben!$B$15="","",Eingaben!$B$15) | C17: 3 | D17: =IF(Eingaben!$B$15="","",J16) | E17: =IF(Eingaben!$B$15="","",Eingaben!$AC$15*12*(1+Eingaben!$K$15)^(3-1)) | F17: =IF(Eingaben!$B$15="","",E17/12) | G17: =IF(Eingaben!$B$15="","",I17-H17) | H17: =IF(Eingaben!$B$15="","",D17-J17) | I17: =IF(Eingaben!$B$15="","",P17*12) | J17: =IF(Eingaben!$B$15="","",IF(O17=0,MAX(0,D17-P17*12),MAX(0,D17*(1+O17)^12-P17*((1+O17)^12-1)/O17))) | K17: =IF(Eingaben!$B$15="","",Eingaben!$M$15) | L17: =IF(Eingaben!$B$15="","",'Steuer & AfA'!L17) | M17: =IF(Eingaben!$B$15="","",E17+L17-I17-K17) | N17: =IF(Eingaben!$B$15="","",M17/12) | O17: =IF(Eingaben!$B$15="","",Eingaben!$AF$15) | P17: =IF(Eingaben!$B$15="","",Eingaben!$AE$15)
A18: 2 | B18: =IF(Eingaben!$B$15="","",Eingaben!$B$15) | C18: 4 | D18: =IF(Eingaben!$B$15="","",J17) | E18: =IF(Eingaben!$B$15="","",Eingaben!$AC$15*12*(1+Eingaben!$K$15)^(4-1)) | F18: =IF(Eingaben!$B$15="","",E18/12) | G18: =IF(Eingaben!$B$15="","",I18-H18) | H18: =IF(Eingaben!$B$15="","",D18-J18) | I18: =IF(Eingaben!$B$15="","",P18*12) | J18: =IF(Eingaben!$B$15="","",IF(O18=0,MAX(0,D18-P18*12),MAX(0,D18*(1+O18)^12-P18*((1+O18)^12-1)/O18))) | K18: =IF(Eingaben!$B$15="","",Eingaben!$M$15) | L18: =IF(Eingaben!$B$15="","",'Steuer & AfA'!L18) | M18: =IF(Eingaben!$B$15="","",E18+L18-I18-K18) | N18: =IF(Eingaben!$B$15="","",M18/12) | O18: =IF(Eingaben!$B$15="","",Eingaben!$AF$15) | P18: =IF(Eingaben!$B$15="","",Eingaben!$AE$15)
A19: 2 | B19: =IF(Eingaben!$B$15="","",Eingaben!$B$15) | C19: 5 | D19: =IF(Eingaben!$B$15="","",J18) | E19: =IF(Eingaben!$B$15="","",Eingaben!$AC$15*12*(1+Eingaben!$K$15)^(5-1)) | F19: =IF(Eingaben!$B$15="","",E19/12) | G19: =IF(Eingaben!$B$15="","",I19-H19) | H19: =IF(Eingaben!$B$15="","",D19-J19) | I19: =IF(Eingaben!$B$15="","",P19*12) | J19: =IF(Eingaben!$B$15="","",IF(O19=0,MAX(0,D19-P19*12),MAX(0,D19*(1+O19)^12-P19*((1+O19)^12-1)/O19))) | K19: =IF(Eingaben!$B$15="","",Eingaben!$M$15) | L19: =IF(Eingaben!$B$15="","",'Steuer & AfA'!L19) | M19: =IF(Eingaben!$B$15="","",E19+L19-I19-K19) | N19: =IF(Eingaben!$B$15="","",M19/12) | O19: =IF(Eingaben!$B$15="","",Eingaben!$AF$15) | P19: =IF(Eingaben!$B$15="","",Eingaben!$AE$15)
A20: 2 | B20: =IF(Eingaben!$B$15="","",Eingaben!$B$15) | C20: 6 | D20: =IF(Eingaben!$B$15="","",J19) | E20: =IF(Eingaben!$B$15="","",Eingaben!$AC$15*12*(1+Eingaben!$K$15)^(6-1)) | F20: =IF(Eingaben!$B$15="","",E20/12) | G20: =IF(Eingaben!$B$15="","",I20-H20) | H20: =IF(Eingaben!$B$15="","",D20-J20) | I20: =IF(Eingaben!$B$15="","",P20*12) | J20: =IF(Eingaben!$B$15="","",IF(O20=0,MAX(0,D20-P20*12),MAX(0,D20*(1+O20)^12-P20*((1+O20)^12-1)/O20))) | K20: =IF(Eingaben!$B$15="","",Eingaben!$M$15) | L20: =IF(Eingaben!$B$15="","",'Steuer & AfA'!L20) | M20: =IF(Eingaben!$B$15="","",E20+L20-I20-K20) | N20: =IF(Eingaben!$B$15="","",M20/12) | O20: =IF(Eingaben!$B$15="","",Eingaben!$AF$15) | P20: =IF(Eingaben!$B$15="","",Eingaben!$AE$15)
A21: 2 | B21: =IF(Eingaben!$B$15="","",Eingaben!$B$15) | C21: 7 | D21: =IF(Eingaben!$B$15="","",J20) | E21: =IF(Eingaben!$B$15="","",Eingaben!$AC$15*12*(1+Eingaben!$K$15)^(7-1)) | F21: =IF(Eingaben!$B$15="","",E21/12) | G21: =IF(Eingaben!$B$15="","",I21-H21) | H21: =IF(Eingaben!$B$15="","",D21-J21) | I21: =IF(Eingaben!$B$15="","",P21*12) | J21: =IF(Eingaben!$B$15="","",IF(O21=0,MAX(0,D21-P21*12),MAX(0,D21*(1+O21)^12-P21*((1+O21)^12-1)/O21))) | K21: =IF(Eingaben!$B$15="","",Eingaben!$M$15) | L21: =IF(Eingaben!$B$15="","",'Steuer & AfA'!L21) | M21: =IF(Eingaben!$B$15="","",E21+L21-I21-K21) | N21: =IF(Eingaben!$B$15="","",M21/12) | O21: =IF(Eingaben!$B$15="","",Eingaben!$AF$15) | P21: =IF(Eingaben!$B$15="","",Eingaben!$AE$15)
A22: 2 | B22: =IF(Eingaben!$B$15="","",Eingaben!$B$15) | C22: 8 | D22: =IF(Eingaben!$B$15="","",J21) | E22: =IF(Eingaben!$B$15="","",Eingaben!$AC$15*12*(1+Eingaben!$K$15)^(8-1)) | F22: =IF(Eingaben!$B$15="","",E22/12) | G22: =IF(Eingaben!$B$15="","",I22-H22) | H22: =IF(Eingaben!$B$15="","",D22-J22) | I22: =IF(Eingaben!$B$15="","",P22*12) | J22: =IF(Eingaben!$B$15="","",IF(O22=0,MAX(0,D22-P22*12),MAX(0,D22*(1+O22)^12-P22*((1+O22)^12-1)/O22))) | K22: =IF(Eingaben!$B$15="","",Eingaben!$M$15) | L22: =IF(Eingaben!$B$15="","",'Steuer & AfA'!L22) | M22: =IF(Eingaben!$B$15="","",E22+L22-I22-K22) | N22: =IF(Eingaben!$B$15="","",M22/12) | O22: =IF(Eingaben!$B$15="","",Eingaben!$AF$15) | P22: =IF(Eingaben!$B$15="","",Eingaben!$AE$15)
A23: 2 | B23: =IF(Eingaben!$B$15="","",Eingaben!$B$15) | C23: 9 | D23: =IF(Eingaben!$B$15="","",J22) | E23: =IF(Eingaben!$B$15="","",Eingaben!$AC$15*12*(1+Eingaben!$K$15)^(9-1)) | F23: =IF(Eingaben!$B$15="","",E23/12) | G23: =IF(Eingaben!$B$15="","",I23-H23) | H23: =IF(Eingaben!$B$15="","",D23-J23) | I23: =IF(Eingaben!$B$15="","",P23*12) | J23: =IF(Eingaben!$B$15="","",IF(O23=0,MAX(0,D23-P23*12),MAX(0,D23*(1+O23)^12-P23*((1+O23)^12-1)/O23))) | K23: =IF(Eingaben!$B$15="","",Eingaben!$M$15) | L23: =IF(Eingaben!$B$15="","",'Steuer & AfA'!L23) | M23: =IF(Eingaben!$B$15="","",E23+L23-I23-K23) | N23: =IF(Eingaben!$B$15="","",M23/12) | O23: =IF(Eingaben!$B$15="","",Eingaben!$AF$15) | P23: =IF(Eingaben!$B$15="","",Eingaben!$AE$15)
A24: 2 | B24: =IF(Eingaben!$B$15="","",Eingaben!$B$15) | C24: 10 | D24: =IF(Eingaben!$B$15="","",J23) | E24: =IF(Eingaben!$B$15="","",Eingaben!$AC$15*12*(1+Eingaben!$K$15)^(10-1)) | F24: =IF(Eingaben!$B$15="","",E24/12) | G24: =IF(Eingaben!$B$15="","",I24-H24) | H24: =IF(Eingaben!$B$15="","",D24-J24) | I24: =IF(Eingaben!$B$15="","",P24*12) | J24: =IF(Eingaben!$B$15="","",IF(O24=0,MAX(0,D24-P24*12),MAX(0,D24*(1+O24)^12-P24*((1+O24)^12-1)/O24))) | K24: =IF(Eingaben!$B$15="","",Eingaben!$M$15) | L24: =IF(Eingaben!$B$15="","",'Steuer & AfA'!L24) | M24: =IF(Eingaben!$B$15="","",E24+L24-I24-K24) | N24: =IF(Eingaben!$B$15="","",M24/12) | O24: =IF(Eingaben!$B$15="","",Eingaben!$AF$15) | P24: =IF(Eingaben!$B$15="","",Eingaben!$AE$15)
A25: 3 | B25: =IF(Eingaben!$B$16="","",Eingaben!$B$16) | C25: 1 | D25: =IF(Eingaben!$B$16="","",Eingaben!$AB$16) | E25: =IF(Eingaben!$B$16="","",Eingaben!$AC$16*12*(1+Eingaben!$K$16)^(1-1)) | F25: =IF(Eingaben!$B$16="","",E25/12) | G25: =IF(Eingaben!$B$16="","",I25-H25) | H25: =IF(Eingaben!$B$16="","",D25-J25) | I25: =IF(Eingaben!$B$16="","",P25*12) | J25: =IF(Eingaben!$B$16="","",IF(O25=0,MAX(0,D25-P25*12),MAX(0,D25*(1+O25)^12-P25*((1+O25)^12-1)/O25))) | K25: =IF(Eingaben!$B$16="","",Eingaben!$M$16) | L25: =IF(Eingaben!$B$16="","",'Steuer & AfA'!L25) | M25: =IF(Eingaben!$B$16="","",E25+L25-I25-K25) | N25: =IF(Eingaben!$B$16="","",M25/12) | O25: =IF(Eingaben!$B$16="","",Eingaben!$AF$16) | P25: =IF(Eingaben!$B$16="","",Eingaben!$AE$16)
A26: 3 | B26: =IF(Eingaben!$B$16="","",Eingaben!$B$16) | C26: 2 | D26: =IF(Eingaben!$B$16="","",J25) | E26: =IF(Eingaben!$B$16="","",Eingaben!$AC$16*12*(1+Eingaben!$K$16)^(2-1)) | F26: =IF(Eingaben!$B$16="","",E26/12) | G26: =IF(Eingaben!$B$16="","",I26-H26) | H26: =IF(Eingaben!$B$16="","",D26-J26) | I26: =IF(Eingaben!$B$16="","",P26*12) | J26: =IF(Eingaben!$B$16="","",IF(O26=0,MAX(0,D26-P26*12),MAX(0,D26*(1+O26)^12-P26*((1+O26)^12-1)/O26))) | K26: =IF(Eingaben!$B$16="","",Eingaben!$M$16) | L26: =IF(Eingaben!$B$16="","",'Steuer & AfA'!L26) | M26: =IF(Eingaben!$B$16="","",E26+L26-I26-K26) | N26: =IF(Eingaben!$B$16="","",M26/12) | O26: =IF(Eingaben!$B$16="","",Eingaben!$AF$16) | P26: =IF(Eingaben!$B$16="","",Eingaben!$AE$16)
A27: 3 | B27: =IF(Eingaben!$B$16="","",Eingaben!$B$16) | C27: 3 | D27: =IF(Eingaben!$B$16="","",J26) | E27: =IF(Eingaben!$B$16="","",Eingaben!$AC$16*12*(1+Eingaben!$K$16)^(3-1)) | F27: =IF(Eingaben!$B$16="","",E27/12) | G27: =IF(Eingaben!$B$16="","",I27-H27) | H27: =IF(Eingaben!$B$16="","",D27-J27) | I27: =IF(Eingaben!$B$16="","",P27*12) | J27: =IF(Eingaben!$B$16="","",IF(O27=0,MAX(0,D27-P27*12),MAX(0,D27*(1+O27)^12-P27*((1+O27)^12-1)/O27))) | K27: =IF(Eingaben!$B$16="","",Eingaben!$M$16) | L27: =IF(Eingaben!$B$16="","",'Steuer & AfA'!L27) | M27: =IF(Eingaben!$B$16="","",E27+L27-I27-K27) | N27: =IF(Eingaben!$B$16="","",M27/12) | O27: =IF(Eingaben!$B$16="","",Eingaben!$AF$16) | P27: =IF(Eingaben!$B$16="","",Eingaben!$AE$16)
A28: 3 | B28: =IF(Eingaben!$B$16="","",Eingaben!$B$16) | C28: 4 | D28: =IF(Eingaben!$B$16="","",J27) | E28: =IF(Eingaben!$B$16="","",Eingaben!$AC$16*12*(1+Eingaben!$K$16)^(4-1)) | F28: =IF(Eingaben!$B$16="","",E28/12) | G28: =IF(Eingaben!$B$16="","",I28-H28) | H28: =IF(Eingaben!$B$16="","",D28-J28) | I28: =IF(Eingaben!$B$16="","",P28*12) | J28: =IF(Eingaben!$B$16="","",IF(O28=0,MAX(0,D28-P28*12),MAX(0,D28*(1+O28)^12-P28*((1+O28)^12-1)/O28))) | K28: =IF(Eingaben!$B$16="","",Eingaben!$M$16) | L28: =IF(Eingaben!$B$16="","",'Steuer & AfA'!L28) | M28: =IF(Eingaben!$B$16="","",E28+L28-I28-K28) | N28: =IF(Eingaben!$B$16="","",M28/12) | O28: =IF(Eingaben!$B$16="","",Eingaben!$AF$16) | P28: =IF(Eingaben!$B$16="","",Eingaben!$AE$16)
A29: 3 | B29: =IF(Eingaben!$B$16="","",Eingaben!$B$16) | C29: 5 | D29: =IF(Eingaben!$B$16="","",J28) | E29: =IF(Eingaben!$B$16="","",Eingaben!$AC$16*12*(1+Eingaben!$K$16)^(5-1)) | F29: =IF(Eingaben!$B$16="","",E29/12) | G29: =IF(Eingaben!$B$16="","",I29-H29) | H29: =IF(Eingaben!$B$16="","",D29-J29) | I29: =IF(Eingaben!$B$16="","",P29*12) | J29: =IF(Eingaben!$B$16="","",IF(O29=0,MAX(0,D29-P29*12),MAX(0,D29*(1+O29)^12-P29*((1+O29)^12-1)/O29))) | K29: =IF(Eingaben!$B$16="","",Eingaben!$M$16) | L29: =IF(Eingaben!$B$16="","",'Steuer & AfA'!L29) | M29: =IF(Eingaben!$B$16="","",E29+L29-I29-K29) | N29: =IF(Eingaben!$B$16="","",M29/12) | O29: =IF(Eingaben!$B$16="","",Eingaben!$AF$16) | P29: =IF(Eingaben!$B$16="","",Eingaben!$AE$16)
A30: 3 | B30: =IF(Eingaben!$B$16="","",Eingaben!$B$16) | C30: 6 | D30: =IF(Eingaben!$B$16="","",J29) | E30: =IF(Eingaben!$B$16="","",Eingaben!$AC$16*12*(1+Eingaben!$K$16)^(6-1)) | F30: =IF(Eingaben!$B$16="","",E30/12) | G30: =IF(Eingaben!$B$16="","",I30-H30) | H30: =IF(Eingaben!$B$16="","",D30-J30) | I30: =IF(Eingaben!$B$16="","",P30*12) | J30: =IF(Eingaben!$B$16="","",IF(O30=0,MAX(0,D30-P30*12),MAX(0,D30*(1+O30)^12-P30*((1+O30)^12-1)/O30))) | K30: =IF(Eingaben!$B$16="","",Eingaben!$M$16) | L30: =IF(Eingaben!$B$16="","",'Steuer & AfA'!L30) | M30: =IF(Eingaben!$B$16="","",E30+L30-I30-K30) | N30: =IF(Eingaben!$B$16="","",M30/12) | O30: =IF(Eingaben!$B$16="","",Eingaben!$AF$16) | P30: =IF(Eingaben!$B$16="","",Eingaben!$AE$16)
A31: 3 | B31: =IF(Eingaben!$B$16="","",Eingaben!$B$16) | C31: 7 | D31: =IF(Eingaben!$B$16="","",J30) | E31: =IF(Eingaben!$B$16="","",Eingaben!$AC$16*12*(1+Eingaben!$K$16)^(7-1)) | F31: =IF(Eingaben!$B$16="","",E31/12) | G31: =IF(Eingaben!$B$16="","",I31-H31) | H31: =IF(Eingaben!$B$16="","",D31-J31) | I31: =IF(Eingaben!$B$16="","",P31*12) | J31: =IF(Eingaben!$B$16="","",IF(O31=0,MAX(0,D31-P31*12),MAX(0,D31*(1+O31)^12-P31*((1+O31)^12-1)/O31))) | K31: =IF(Eingaben!$B$16="","",Eingaben!$M$16) | L31: =IF(Eingaben!$B$16="","",'Steuer & AfA'!L31) | M31: =IF(Eingaben!$B$16="","",E31+L31-I31-K31) | N31: =IF(Eingaben!$B$16="","",M31/12) | O31: =IF(Eingaben!$B$16="","",Eingaben!$AF$16) | P31: =IF(Eingaben!$B$16="","",Eingaben!$AE$16)
A32: 3 | B32: =IF(Eingaben!$B$16="","",Eingaben!$B$16) | C32: 8 | D32: =IF(Eingaben!$B$16="","",J31) | E32: =IF(Eingaben!$B$16="","",Eingaben!$AC$16*12*(1+Eingaben!$K$16)^(8-1)) | F32: =IF(Eingaben!$B$16="","",E32/12) | G32: =IF(Eingaben!$B$16="","",I32-H32) | H32: =IF(Eingaben!$B$16="","",D32-J32) | I32: =IF(Eingaben!$B$16="","",P32*12) | J32: =IF(Eingaben!$B$16="","",IF(O32=0,MAX(0,D32-P32*12),MAX(0,D32*(1+O32)^12-P32*((1+O32)^12-1)/O32))) | K32: =IF(Eingaben!$B$16="","",Eingaben!$M$16) | L32: =IF(Eingaben!$B$16="","",'Steuer & AfA'!L32) | M32: =IF(Eingaben!$B$16="","",E32+L32-I32-K32) | N32: =IF(Eingaben!$B$16="","",M32/12) | O32: =IF(Eingaben!$B$16="","",Eingaben!$AF$16) | P32: =IF(Eingaben!$B$16="","",Eingaben!$AE$16)
A33: 3 | B33: =IF(Eingaben!$B$16="","",Eingaben!$B$16) | C33: 9 | D33: =IF(Eingaben!$B$16="","",J32) | E33: =IF(Eingaben!$B$16="","",Eingaben!$AC$16*12*(1+Eingaben!$K$16)^(9-1)) | F33: =IF(Eingaben!$B$16="","",E33/12) | G33: =IF(Eingaben!$B$16="","",I33-H33) | H33: =IF(Eingaben!$B$16="","",D33-J33) | I33: =IF(Eingaben!$B$16="","",P33*12) | J33: =IF(Eingaben!$B$16="","",IF(O33=0,MAX(0,D33-P33*12),MAX(0,D33*(1+O33)^12-P33*((1+O33)^12-1)/O33))) | K33: =IF(Eingaben!$B$16="","",Eingaben!$M$16) | L33: =IF(Eingaben!$B$16="","",'Steuer & AfA'!L33) | M33: =IF(Eingaben!$B$16="","",E33+L33-I33-K33) | N33: =IF(Eingaben!$B$16="","",M33/12) | O33: =IF(Eingaben!$B$16="","",Eingaben!$AF$16) | P33: =IF(Eingaben!$B$16="","",Eingaben!$AE$16)
A34: 3 | B34: =IF(Eingaben!$B$16="","",Eingaben!$B$16) | C34: 10 | D34: =IF(Eingaben!$B$16="","",J33) | E34: =IF(Eingaben!$B$16="","",Eingaben!$AC$16*12*(1+Eingaben!$K$16)^(10-1)) | F34: =IF(Eingaben!$B$16="","",E34/12) | G34: =IF(Eingaben!$B$16="","",I34-H34) | H34: =IF(Eingaben!$B$16="","",D34-J34) | I34: =IF(Eingaben!$B$16="","",P34*12) | J34: =IF(Eingaben!$B$16="","",IF(O34=0,MAX(0,D34-P34*12),MAX(0,D34*(1+O34)^12-P34*((1+O34)^12-1)/O34))) | K34: =IF(Eingaben!$B$16="","",Eingaben!$M$16) | L34: =IF(Eingaben!$B$16="","",'Steuer & AfA'!L34) | M34: =IF(Eingaben!$B$16="","",E34+L34-I34-K34) | N34: =IF(Eingaben!$B$16="","",M34/12) | O34: =IF(Eingaben!$B$16="","",Eingaben!$AF$16) | P34: =IF(Eingaben!$B$16="","",Eingaben!$AE$16)
A35: 4 | B35: =IF(Eingaben!$B$17="","",Eingaben!$B$17) | C35: 1 | D35: =IF(Eingaben!$B$17="","",Eingaben!$AB$17) | E35: =IF(Eingaben!$B$17="","",Eingaben!$AC$17*12*(1+Eingaben!$K$17)^(1-1)) | F35: =IF(Eingaben!$B$17="","",E35/12) | G35: =IF(Eingaben!$B$17="","",I35-H35) | H35: =IF(Eingaben!$B$17="","",D35-J35) | I35: =IF(Eingaben!$B$17="","",P35*12) | J35: =IF(Eingaben!$B$17="","",IF(O35=0,MAX(0,D35-P35*12),MAX(0,D35*(1+O35)^12-P35*((1+O35)^12-1)/O35))) | K35: =IF(Eingaben!$B$17="","",Eingaben!$M$17) | L35: =IF(Eingaben!$B$17="","",'Steuer & AfA'!L35) | M35: =IF(Eingaben!$B$17="","",E35+L35-I35-K35) | N35: =IF(Eingaben!$B$17="","",M35/12) | O35: =IF(Eingaben!$B$17="","",Eingaben!$AF$17) | P35: =IF(Eingaben!$B$17="","",Eingaben!$AE$17)
A36: 4 | B36: =IF(Eingaben!$B$17="","",Eingaben!$B$17) | C36: 2 | D36: =IF(Eingaben!$B$17="","",J35) | E36: =IF(Eingaben!$B$17="","",Eingaben!$AC$17*12*(1+Eingaben!$K$17)^(2-1)) | F36: =IF(Eingaben!$B$17="","",E36/12) | G36: =IF(Eingaben!$B$17="","",I36-H36) | H36: =IF(Eingaben!$B$17="","",D36-J36) | I36: =IF(Eingaben!$B$17="","",P36*12) | J36: =IF(Eingaben!$B$17="","",IF(O36=0,MAX(0,D36-P36*12),MAX(0,D36*(1+O36)^12-P36*((1+O36)^12-1)/O36))) | K36: =IF(Eingaben!$B$17="","",Eingaben!$M$17) | L36: =IF(Eingaben!$B$17="","",'Steuer & AfA'!L36) | M36: =IF(Eingaben!$B$17="","",E36+L36-I36-K36) | N36: =IF(Eingaben!$B$17="","",M36/12) | O36: =IF(Eingaben!$B$17="","",Eingaben!$AF$17) | P36: =IF(Eingaben!$B$17="","",Eingaben!$AE$17)
A37: 4 | B37: =IF(Eingaben!$B$17="","",Eingaben!$B$17) | C37: 3 | D37: =IF(Eingaben!$B$17="","",J36) | E37: =IF(Eingaben!$B$17="","",Eingaben!$AC$17*12*(1+Eingaben!$K$17)^(3-1)) | F37: =IF(Eingaben!$B$17="","",E37/12) | G37: =IF(Eingaben!$B$17="","",I37-H37) | H37: =IF(Eingaben!$B$17="","",D37-J37) | I37: =IF(Eingaben!$B$17="","",P37*12) | J37: =IF(Eingaben!$B$17="","",IF(O37=0,MAX(0,D37-P37*12),MAX(0,D37*(1+O37)^12-P37*((1+O37)^12-1)/O37))) | K37: =IF(Eingaben!$B$17="","",Eingaben!$M$17) | L37: =IF(Eingaben!$B$17="","",'Steuer & AfA'!L37) | M37: =IF(Eingaben!$B$17="","",E37+L37-I37-K37) | N37: =IF(Eingaben!$B$17="","",M37/12) | O37: =IF(Eingaben!$B$17="","",Eingaben!$AF$17) | P37: =IF(Eingaben!$B$17="","",Eingaben!$AE$17)
A38: 4 | B38: =IF(Eingaben!$B$17="","",Eingaben!$B$17) | C38: 4 | D38: =IF(Eingaben!$B$17="","",J37) | E38: =IF(Eingaben!$B$17="","",Eingaben!$AC$17*12*(1+Eingaben!$K$17)^(4-1)) | F38: =IF(Eingaben!$B$17="","",E38/12) | G38: =IF(Eingaben!$B$17="","",I38-H38) | H38: =IF(Eingaben!$B$17="","",D38-J38) | I38: =IF(Eingaben!$B$17="","",P38*12) | J38: =IF(Eingaben!$B$17="","",IF(O38=0,MAX(0,D38-P38*12),MAX(0,D38*(1+O38)^12-P38*((1+O38)^12-1)/O38))) | K38: =IF(Eingaben!$B$17="","",Eingaben!$M$17) | L38: =IF(Eingaben!$B$17="","",'Steuer & AfA'!L38) | M38: =IF(Eingaben!$B$17="","",E38+L38-I38-K38) | N38: =IF(Eingaben!$B$17="","",M38/12) | O38: =IF(Eingaben!$B$17="","",Eingaben!$AF$17) | P38: =IF(Eingaben!$B$17="","",Eingaben!$AE$17)
A39: 4 | B39: =IF(Eingaben!$B$17="","",Eingaben!$B$17) | C39: 5 | D39: =IF(Eingaben!$B$17="","",J38) | E39: =IF(Eingaben!$B$17="","",Eingaben!$AC$17*12*(1+Eingaben!$K$17)^(5-1)) | F39: =IF(Eingaben!$B$17="","",E39/12) | G39: =IF(Eingaben!$B$17="","",I39-H39) | H39: =IF(Eingaben!$B$17="","",D39-J39) | I39: =IF(Eingaben!$B$17="","",P39*12) | J39: =IF(Eingaben!$B$17="","",IF(O39=0,MAX(0,D39-P39*12),MAX(0,D39*(1+O39)^12-P39*((1+O39)^12-1)/O39))) | K39: =IF(Eingaben!$B$17="","",Eingaben!$M$17) | L39: =IF(Eingaben!$B$17="","",'Steuer & AfA'!L39) | M39: =IF(Eingaben!$B$17="","",E39+L39-I39-K39) | N39: =IF(Eingaben!$B$17="","",M39/12) | O39: =IF(Eingaben!$B$17="","",Eingaben!$AF$17) | P39: =IF(Eingaben!$B$17="","",Eingaben!$AE$17)
A40: 4 | B40: =IF(Eingaben!$B$17="","",Eingaben!$B$17) | C40: 6 | D40: =IF(Eingaben!$B$17="","",J39) | E40: =IF(Eingaben!$B$17="","",Eingaben!$AC$17*12*(1+Eingaben!$K$17)^(6-1)) | F40: =IF(Eingaben!$B$17="","",E40/12) | G40: =IF(Eingaben!$B$17="","",I40-H40) | H40: =IF(Eingaben!$B$17="","",D40-J40) | I40: =IF(Eingaben!$B$17="","",P40*12) | J40: =IF(Eingaben!$B$17="","",IF(O40=0,MAX(0,D40-P40*12),MAX(0,D40*(1+O40)^12-P40*((1+O40)^12-1)/O40))) | K40: =IF(Eingaben!$B$17="","",Eingaben!$M$17) | L40: =IF(Eingaben!$B$17="","",'Steuer & AfA'!L40) | M40: =IF(Eingaben!$B$17="","",E40+L40-I40-K40) | N40: =IF(Eingaben!$B$17="","",M40/12) | O40: =IF(Eingaben!$B$17="","",Eingaben!$AF$17) | P40: =IF(Eingaben!$B$17="","",Eingaben!$AE$17)
A41: 4 | B41: =IF(Eingaben!$B$17="","",Eingaben!$B$17) | C41: 7 | D41: =IF(Eingaben!$B$17="","",J40) | E41: =IF(Eingaben!$B$17="","",Eingaben!$AC$17*12*(1+Eingaben!$K$17)^(7-1)) | F41: =IF(Eingaben!$B$17="","",E41/12) | G41: =IF(Eingaben!$B$17="","",I41-H41) | H41: =IF(Eingaben!$B$17="","",D41-J41) | I41: =IF(Eingaben!$B$17="","",P41*12) | J41: =IF(Eingaben!$B$17="","",IF(O41=0,MAX(0,D41-P41*12),MAX(0,D41*(1+O41)^12-P41*((1+O41)^12-1)/O41))) | K41: =IF(Eingaben!$B$17="","",Eingaben!$M$17) | L41: =IF(Eingaben!$B$17="","",'Steuer & AfA'!L41) | M41: =IF(Eingaben!$B$17="","",E41+L41-I41-K41) | N41: =IF(Eingaben!$B$17="","",M41/12) | O41: =IF(Eingaben!$B$17="","",Eingaben!$AF$17) | P41: =IF(Eingaben!$B$17="","",Eingaben!$AE$17)
A42: 4 | B42: =IF(Eingaben!$B$17="","",Eingaben!$B$17) | C42: 8 | D42: =IF(Eingaben!$B$17="","",J41) | E42: =IF(Eingaben!$B$17="","",Eingaben!$AC$17*12*(1+Eingaben!$K$17)^(8-1)) | F42: =IF(Eingaben!$B$17="","",E42/12) | G42: =IF(Eingaben!$B$17="","",I42-H42) | H42: =IF(Eingaben!$B$17="","",D42-J42) | I42: =IF(Eingaben!$B$17="","",P42*12) | J42: =IF(Eingaben!$B$17="","",IF(O42=0,MAX(0,D42-P42*12),MAX(0,D42*(1+O42)^12-P42*((1+O42)^12-1)/O42))) | K42: =IF(Eingaben!$B$17="","",Eingaben!$M$17) | L42: =IF(Eingaben!$B$17="","",'Steuer & AfA'!L42) | M42: =IF(Eingaben!$B$17="","",E42+L42-I42-K42) | N42: =IF(Eingaben!$B$17="","",M42/12) | O42: =IF(Eingaben!$B$17="","",Eingaben!$AF$17) | P42: =IF(Eingaben!$B$17="","",Eingaben!$AE$17)
A43: 4 | B43: =IF(Eingaben!$B$17="","",Eingaben!$B$17) | C43: 9 | D43: =IF(Eingaben!$B$17="","",J42) | E43: =IF(Eingaben!$B$17="","",Eingaben!$AC$17*12*(1+Eingaben!$K$17)^(9-1)) | F43: =IF(Eingaben!$B$17="","",E43/12) | G43: =IF(Eingaben!$B$17="","",I43-H43) | H43: =IF(Eingaben!$B$17="","",D43-J43) | I43: =IF(Eingaben!$B$17="","",P43*12) | J43: =IF(Eingaben!$B$17="","",IF(O43=0,MAX(0,D43-P43*12),MAX(0,D43*(1+O43)^12-P43*((1+O43)^12-1)/O43))) | K43: =IF(Eingaben!$B$17="","",Eingaben!$M$17) | L43: =IF(Eingaben!$B$17="","",'Steuer & AfA'!L43) | M43: =IF(Eingaben!$B$17="","",E43+L43-I43-K43) | N43: =IF(Eingaben!$B$17="","",M43/12) | O43: =IF(Eingaben!$B$17="","",Eingaben!$AF$17) | P43: =IF(Eingaben!$B$17="","",Eingaben!$AE$17)
A44: 4 | B44: =IF(Eingaben!$B$17="","",Eingaben!$B$17) | C44: 10 | D44: =IF(Eingaben!$B$17="","",J43) | E44: =IF(Eingaben!$B$17="","",Eingaben!$AC$17*12*(1+Eingaben!$K$17)^(10-1)) | F44: =IF(Eingaben!$B$17="","",E44/12) | G44: =IF(Eingaben!$B$17="","",I44-H44) | H44: =IF(Eingaben!$B$17="","",D44-J44) | I44: =IF(Eingaben!$B$17="","",P44*12) | J44: =IF(Eingaben!$B$17="","",IF(O44=0,MAX(0,D44-P44*12),MAX(0,D44*(1+O44)^12-P44*((1+O44)^12-1)/O44))) | K44: =IF(Eingaben!$B$17="","",Eingaben!$M$17) | L44: =IF(Eingaben!$B$17="","",'Steuer & AfA'!L44) | M44: =IF(Eingaben!$B$17="","",E44+L44-I44-K44) | N44: =IF(Eingaben!$B$17="","",M44/12) | O44: =IF(Eingaben!$B$17="","",Eingaben!$AF$17) | P44: =IF(Eingaben!$B$17="","",Eingaben!$AE$17)
A45: 5 | B45: =IF(Eingaben!$B$18="","",Eingaben!$B$18) | C45: 1 | D45: =IF(Eingaben!$B$18="","",Eingaben!$AB$18) | E45: =IF(Eingaben!$B$18="","",Eingaben!$AC$18*12*(1+Eingaben!$K$18)^(1-1)) | F45: =IF(Eingaben!$B$18="","",E45/12) | G45: =IF(Eingaben!$B$18="","",I45-H45) | H45: =IF(Eingaben!$B$18="","",D45-J45) | I45: =IF(Eingaben!$B$18="","",P45*12) | J45: =IF(Eingaben!$B$18="","",IF(O45=0,MAX(0,D45-P45*12),MAX(0,D45*(1+O45)^12-P45*((1+O45)^12-1)/O45))) | K45: =IF(Eingaben!$B$18="","",Eingaben!$M$18) | L45: =IF(Eingaben!$B$18="","",'Steuer & AfA'!L45) | M45: =IF(Eingaben!$B$18="","",E45+L45-I45-K45) | N45: =IF(Eingaben!$B$18="","",M45/12) | O45: =IF(Eingaben!$B$18="","",Eingaben!$AF$18) | P45: =IF(Eingaben!$B$18="","",Eingaben!$AE$18)
A46: 5 | B46: =IF(Eingaben!$B$18="","",Eingaben!$B$18) | C46: 2 | D46: =IF(Eingaben!$B$18="","",J45) | E46: =IF(Eingaben!$B$18="","",Eingaben!$AC$18*12*(1+Eingaben!$K$18)^(2-1)) | F46: =IF(Eingaben!$B$18="","",E46/12) | G46: =IF(Eingaben!$B$18="","",I46-H46) | H46: =IF(Eingaben!$B$18="","",D46-J46) | I46: =IF(Eingaben!$B$18="","",P46*12) | J46: =IF(Eingaben!$B$18="","",IF(O46=0,MAX(0,D46-P46*12),MAX(0,D46*(1+O46)^12-P46*((1+O46)^12-1)/O46))) | K46: =IF(Eingaben!$B$18="","",Eingaben!$M$18) | L46: =IF(Eingaben!$B$18="","",'Steuer & AfA'!L46) | M46: =IF(Eingaben!$B$18="","",E46+L46-I46-K46) | N46: =IF(Eingaben!$B$18="","",M46/12) | O46: =IF(Eingaben!$B$18="","",Eingaben!$AF$18) | P46: =IF(Eingaben!$B$18="","",Eingaben!$AE$18)
A47: 5 | B47: =IF(Eingaben!$B$18="","",Eingaben!$B$18) | C47: 3 | D47: =IF(Eingaben!$B$18="","",J46) | E47: =IF(Eingaben!$B$18="","",Eingaben!$AC$18*12*(1+Eingaben!$K$18)^(3-1)) | F47: =IF(Eingaben!$B$18="","",E47/12) | G47: =IF(Eingaben!$B$18="","",I47-H47) | H47: =IF(Eingaben!$B$18="","",D47-J47) | I47: =IF(Eingaben!$B$18="","",P47*12) | J47: =IF(Eingaben!$B$18="","",IF(O47=0,MAX(0,D47-P47*12),MAX(0,D47*(1+O47)^12-P47*((1+O47)^12-1)/O47))) | K47: =IF(Eingaben!$B$18="","",Eingaben!$M$18) | L47: =IF(Eingaben!$B$18="","",'Steuer & AfA'!L47) | M47: =IF(Eingaben!$B$18="","",E47+L47-I47-K47) | N47: =IF(Eingaben!$B$18="","",M47/12) | O47: =IF(Eingaben!$B$18="","",Eingaben!$AF$18) | P47: =IF(Eingaben!$B$18="","",Eingaben!$AE$18)
A48: 5 | B48: =IF(Eingaben!$B$18="","",Eingaben!$B$18) | C48: 4 | D48: =IF(Eingaben!$B$18="","",J47) | E48: =IF(Eingaben!$B$18="","",Eingaben!$AC$18*12*(1+Eingaben!$K$18)^(4-1)) | F48: =IF(Eingaben!$B$18="","",E48/12) | G48: =IF(Eingaben!$B$18="","",I48-H48) | H48: =IF(Eingaben!$B$18="","",D48-J48) | I48: =IF(Eingaben!$B$18="","",P48*12) | J48: =IF(Eingaben!$B$18="","",IF(O48=0,MAX(0,D48-P48*12),MAX(0,D48*(1+O48)^12-P48*((1+O48)^12-1)/O48))) | K48: =IF(Eingaben!$B$18="","",Eingaben!$M$18) | L48: =IF(Eingaben!$B$18="","",'Steuer & AfA'!L48) | M48: =IF(Eingaben!$B$18="","",E48+L48-I48-K48) | N48: =IF(Eingaben!$B$18="","",M48/12) | O48: =IF(Eingaben!$B$18="","",Eingaben!$AF$18) | P48: =IF(Eingaben!$B$18="","",Eingaben!$AE$18)
A49: 5 | B49: =IF(Eingaben!$B$18="","",Eingaben!$B$18) | C49: 5 | D49: =IF(Eingaben!$B$18="","",J48) | E49: =IF(Eingaben!$B$18="","",Eingaben!$AC$18*12*(1+Eingaben!$K$18)^(5-1)) | F49: =IF(Eingaben!$B$18="","",E49/12) | G49: =IF(Eingaben!$B$18="","",I49-H49) | H49: =IF(Eingaben!$B$18="","",D49-J49) | I49: =IF(Eingaben!$B$18="","",P49*12) | J49: =IF(Eingaben!$B$18="","",IF(O49=0,MAX(0,D49-P49*12),MAX(0,D49*(1+O49)^12-P49*((1+O49)^12-1)/O49))) | K49: =IF(Eingaben!$B$18="","",Eingaben!$M$18) | L49: =IF(Eingaben!$B$18="","",'Steuer & AfA'!L49) | M49: =IF(Eingaben!$B$18="","",E49+L49-I49-K49) | N49: =IF(Eingaben!$B$18="","",M49/12) | O49: =IF(Eingaben!$B$18="","",Eingaben!$AF$18) | P49: =IF(Eingaben!$B$18="","",Eingaben!$AE$18)
A50: 5 | B50: =IF(Eingaben!$B$18="","",Eingaben!$B$18) | C50: 6 | D50: =IF(Eingaben!$B$18="","",J49) | E50: =IF(Eingaben!$B$18="","",Eingaben!$AC$18*12*(1+Eingaben!$K$18)^(6-1)) | F50: =IF(Eingaben!$B$18="","",E50/12) | G50: =IF(Eingaben!$B$18="","",I50-H50) | H50: =IF(Eingaben!$B$18="","",D50-J50) | I50: =IF(Eingaben!$B$18="","",P50*12) | J50: =IF(Eingaben!$B$18="","",IF(O50=0,MAX(0,D50-P50*12),MAX(0,D50*(1+O50)^12-P50*((1+O50)^12-1)/O50))) | K50: =IF(Eingaben!$B$18="","",Eingaben!$M$18) | L50: =IF(Eingaben!$B$18="","",'Steuer & AfA'!L50) | M50: =IF(Eingaben!$B$18="","",E50+L50-I50-K50) | N50: =IF(Eingaben!$B$18="","",M50/12) | O50: =IF(Eingaben!$B$18="","",Eingaben!$AF$18) | P50: =IF(Eingaben!$B$18="","",Eingaben!$AE$18)
A51: 5 | B51: =IF(Eingaben!$B$18="","",Eingaben!$B$18) | C51: 7 | D51: =IF(Eingaben!$B$18="","",J50) | E51: =IF(Eingaben!$B$18="","",Eingaben!$AC$18*12*(1+Eingaben!$K$18)^(7-1)) | F51: =IF(Eingaben!$B$18="","",E51/12) | G51: =IF(Eingaben!$B$18="","",I51-H51) | H51: =IF(Eingaben!$B$18="","",D51-J51) | I51: =IF(Eingaben!$B$18="","",P51*12) | J51: =IF(Eingaben!$B$18="","",IF(O51=0,MAX(0,D51-P51*12),MAX(0,D51*(1+O51)^12-P51*((1+O51)^12-1)/O51))) | K51: =IF(Eingaben!$B$18="","",Eingaben!$M$18) | L51: =IF(Eingaben!$B$18="","",'Steuer & AfA'!L51) | M51: =IF(Eingaben!$B$18="","",E51+L51-I51-K51) | N51: =IF(Eingaben!$B$18="","",M51/12) | O51: =IF(Eingaben!$B$18="","",Eingaben!$AF$18) | P51: =IF(Eingaben!$B$18="","",Eingaben!$AE$18)
A52: 5 | B52: =IF(Eingaben!$B$18="","",Eingaben!$B$18) | C52: 8 | D52: =IF(Eingaben!$B$18="","",J51) | E52: =IF(Eingaben!$B$18="","",Eingaben!$AC$18*12*(1+Eingaben!$K$18)^(8-1)) | F52: =IF(Eingaben!$B$18="","",E52/12) | G52: =IF(Eingaben!$B$18="","",I52-H52) | H52: =IF(Eingaben!$B$18="","",D52-J52) | I52: =IF(Eingaben!$B$18="","",P52*12) | J52: =IF(Eingaben!$B$18="","",IF(O52=0,MAX(0,D52-P52*12),MAX(0,D52*(1+O52)^12-P52*((1+O52)^12-1)/O52))) | K52: =IF(Eingaben!$B$18="","",Eingaben!$M$18) | L52: =IF(Eingaben!$B$18="","",'Steuer & AfA'!L52) | M52: =IF(Eingaben!$B$18="","",E52+L52-I52-K52) | N52: =IF(Eingaben!$B$18="","",M52/12) | O52: =IF(Eingaben!$B$18="","",Eingaben!$AF$18) | P52: =IF(Eingaben!$B$18="","",Eingaben!$AE$18)
A53: 5 | B53: =IF(Eingaben!$B$18="","",Eingaben!$B$18) | C53: 9 | D53: =IF(Eingaben!$B$18="","",J52) | E53: =IF(Eingaben!$B$18="","",Eingaben!$AC$18*12*(1+Eingaben!$K$18)^(9-1)) | F53: =IF(Eingaben!$B$18="","",E53/12) | G53: =IF(Eingaben!$B$18="","",I53-H53) | H53: =IF(Eingaben!$B$18="","",D53-J53) | I53: =IF(Eingaben!$B$18="","",P53*12) | J53: =IF(Eingaben!$B$18="","",IF(O53=0,MAX(0,D53-P53*12),MAX(0,D53*(1+O53)^12-P53*((1+O53)^12-1)/O53))) | K53: =IF(Eingaben!$B$18="","",Eingaben!$M$18) | L53: =IF(Eingaben!$B$18="","",'Steuer & AfA'!L53) | M53: =IF(Eingaben!$B$18="","",E53+L53-I53-K53) | N53: =IF(Eingaben!$B$18="","",M53/12) | O53: =IF(Eingaben!$B$18="","",Eingaben!$AF$18) | P53: =IF(Eingaben!$B$18="","",Eingaben!$AE$18)
A54: 5 | B54: =IF(Eingaben!$B$18="","",Eingaben!$B$18) | C54: 10 | D54: =IF(Eingaben!$B$18="","",J53) | E54: =IF(Eingaben!$B$18="","",Eingaben!$AC$18*12*(1+Eingaben!$K$18)^(10-1)) | F54: =IF(Eingaben!$B$18="","",E54/12) | G54: =IF(Eingaben!$B$18="","",I54-H54) | H54: =IF(Eingaben!$B$18="","",D54-J54) | I54: =IF(Eingaben!$B$18="","",P54*12) | J54: =IF(Eingaben!$B$18="","",IF(O54=0,MAX(0,D54-P54*12),MAX(0,D54*(1+O54)^12-P54*((1+O54)^12-1)/O54))) | K54: =IF(Eingaben!$B$18="","",Eingaben!$M$18) | L54: =IF(Eingaben!$B$18="","",'Steuer & AfA'!L54) | M54: =IF(Eingaben!$B$18="","",E54+L54-I54-K54) | N54: =IF(Eingaben!$B$18="","",M54/12) | O54: =IF(Eingaben!$B$18="","",Eingaben!$AF$18) | P54: =IF(Eingaben!$B$18="","",Eingaben!$AE$18)
A55: 6 | B55: =IF(Eingaben!$B$19="","",Eingaben!$B$19) | C55: 1 | D55: =IF(Eingaben!$B$19="","",Eingaben!$AB$19) | E55: =IF(Eingaben!$B$19="","",Eingaben!$AC$19*12*(1+Eingaben!$K$19)^(1-1)) | F55: =IF(Eingaben!$B$19="","",E55/12) | G55: =IF(Eingaben!$B$19="","",I55-H55) | H55: =IF(Eingaben!$B$19="","",D55-J55) | I55: =IF(Eingaben!$B$19="","",P55*12) | J55: =IF(Eingaben!$B$19="","",IF(O55=0,MAX(0,D55-P55*12),MAX(0,D55*(1+O55)^12-P55*((1+O55)^12-1)/O55))) | K55: =IF(Eingaben!$B$19="","",Eingaben!$M$19) | L55: =IF(Eingaben!$B$19="","",'Steuer & AfA'!L55) | M55: =IF(Eingaben!$B$19="","",E55+L55-I55-K55) | N55: =IF(Eingaben!$B$19="","",M55/12) | O55: =IF(Eingaben!$B$19="","",Eingaben!$AF$19) | P55: =IF(Eingaben!$B$19="","",Eingaben!$AE$19)
A56: 6 | B56: =IF(Eingaben!$B$19="","",Eingaben!$B$19) | C56: 2 | D56: =IF(Eingaben!$B$19="","",J55) | E56: =IF(Eingaben!$B$19="","",Eingaben!$AC$19*12*(1+Eingaben!$K$19)^(2-1)) | F56: =IF(Eingaben!$B$19="","",E56/12) | G56: =IF(Eingaben!$B$19="","",I56-H56) | H56: =IF(Eingaben!$B$19="","",D56-J56) | I56: =IF(Eingaben!$B$19="","",P56*12) | J56: =IF(Eingaben!$B$19="","",IF(O56=0,MAX(0,D56-P56*12),MAX(0,D56*(1+O56)^12-P56*((1+O56)^12-1)/O56))) | K56: =IF(Eingaben!$B$19="","",Eingaben!$M$19) | L56: =IF(Eingaben!$B$19="","",'Steuer & AfA'!L56) | M56: =IF(Eingaben!$B$19="","",E56+L56-I56-K56) | N56: =IF(Eingaben!$B$19="","",M56/12) | O56: =IF(Eingaben!$B$19="","",Eingaben!$AF$19) | P56: =IF(Eingaben!$B$19="","",Eingaben!$AE$19)
A57: 6 | B57: =IF(Eingaben!$B$19="","",Eingaben!$B$19) | C57: 3 | D57: =IF(Eingaben!$B$19="","",J56) | E57: =IF(Eingaben!$B$19="","",Eingaben!$AC$19*12*(1+Eingaben!$K$19)^(3-1)) | F57: =IF(Eingaben!$B$19="","",E57/12) | G57: =IF(Eingaben!$B$19="","",I57-H57) | H57: =IF(Eingaben!$B$19="","",D57-J57) | I57: =IF(Eingaben!$B$19="","",P57*12) | J57: =IF(Eingaben!$B$19="","",IF(O57=0,MAX(0,D57-P57*12),MAX(0,D57*(1+O57)^12-P57*((1+O57)^12-1)/O57))) | K57: =IF(Eingaben!$B$19="","",Eingaben!$M$19) | L57: =IF(Eingaben!$B$19="","",'Steuer & AfA'!L57) | M57: =IF(Eingaben!$B$19="","",E57+L57-I57-K57) | N57: =IF(Eingaben!$B$19="","",M57/12) | O57: =IF(Eingaben!$B$19="","",Eingaben!$AF$19) | P57: =IF(Eingaben!$B$19="","",Eingaben!$AE$19)
A58: 6 | B58: =IF(Eingaben!$B$19="","",Eingaben!$B$19) | C58: 4 | D58: =IF(Eingaben!$B$19="","",J57) | E58: =IF(Eingaben!$B$19="","",Eingaben!$AC$19*12*(1+Eingaben!$K$19)^(4-1)) | F58: =IF(Eingaben!$B$19="","",E58/12) | G58: =IF(Eingaben!$B$19="","",I58-H58) | H58: =IF(Eingaben!$B$19="","",D58-J58) | I58: =IF(Eingaben!$B$19="","",P58*12) | J58: =IF(Eingaben!$B$19="","",IF(O58=0,MAX(0,D58-P58*12),MAX(0,D58*(1+O58)^12-P58*((1+O58)^12-1)/O58))) | K58: =IF(Eingaben!$B$19="","",Eingaben!$M$19) | L58: =IF(Eingaben!$B$19="","",'Steuer & AfA'!L58) | M58: =IF(Eingaben!$B$19="","",E58+L58-I58-K58) | N58: =IF(Eingaben!$B$19="","",M58/12) | O58: =IF(Eingaben!$B$19="","",Eingaben!$AF$19) | P58: =IF(Eingaben!$B$19="","",Eingaben!$AE$19)
A59: 6 | B59: =IF(Eingaben!$B$19="","",Eingaben!$B$19) | C59: 5 | D59: =IF(Eingaben!$B$19="","",J58) | E59: =IF(Eingaben!$B$19="","",Eingaben!$AC$19*12*(1+Eingaben!$K$19)^(5-1)) | F59: =IF(Eingaben!$B$19="","",E59/12) | G59: =IF(Eingaben!$B$19="","",I59-H59) | H59: =IF(Eingaben!$B$19="","",D59-J59) | I59: =IF(Eingaben!$B$19="","",P59*12) | J59: =IF(Eingaben!$B$19="","",IF(O59=0,MAX(0,D59-P59*12),MAX(0,D59*(1+O59)^12-P59*((1+O59)^12-1)/O59))) | K59: =IF(Eingaben!$B$19="","",Eingaben!$M$19) | L59: =IF(Eingaben!$B$19="","",'Steuer & AfA'!L59) | M59: =IF(Eingaben!$B$19="","",E59+L59-I59-K59) | N59: =IF(Eingaben!$B$19="","",M59/12) | O59: =IF(Eingaben!$B$19="","",Eingaben!$AF$19) | P59: =IF(Eingaben!$B$19="","",Eingaben!$AE$19)
A60: 6 | B60: =IF(Eingaben!$B$19="","",Eingaben!$B$19) | C60: 6 | D60: =IF(Eingaben!$B$19="","",J59) | E60: =IF(Eingaben!$B$19="","",Eingaben!$AC$19*12*(1+Eingaben!$K$19)^(6-1)) | F60: =IF(Eingaben!$B$19="","",E60/12) | G60: =IF(Eingaben!$B$19="","",I60-H60) | H60: =IF(Eingaben!$B$19="","",D60-J60) | I60: =IF(Eingaben!$B$19="","",P60*12) | J60: =IF(Eingaben!$B$19="","",IF(O60=0,MAX(0,D60-P60*12),MAX(0,D60*(1+O60)^12-P60*((1+O60)^12-1)/O60))) | K60: =IF(Eingaben!$B$19="","",Eingaben!$M$19) | L60: =IF(Eingaben!$B$19="","",'Steuer & AfA'!L60) | M60: =IF(Eingaben!$B$19="","",E60+L60-I60-K60) | N60: =IF(Eingaben!$B$19="","",M60/12) | O60: =IF(Eingaben!$B$19="","",Eingaben!$AF$19) | P60: =IF(Eingaben!$B$19="","",Eingaben!$AE$19)
A61: 6 | B61: =IF(Eingaben!$B$19="","",Eingaben!$B$19) | C61: 7 | D61: =IF(Eingaben!$B$19="","",J60) | E61: =IF(Eingaben!$B$19="","",Eingaben!$AC$19*12*(1+Eingaben!$K$19)^(7-1)) | F61: =IF(Eingaben!$B$19="","",E61/12) | G61: =IF(Eingaben!$B$19="","",I61-H61) | H61: =IF(Eingaben!$B$19="","",D61-J61) | I61: =IF(Eingaben!$B$19="","",P61*12) | J61: =IF(Eingaben!$B$19="","",IF(O61=0,MAX(0,D61-P61*12),MAX(0,D61*(1+O61)^12-P61*((1+O61)^12-1)/O61))) | K61: =IF(Eingaben!$B$19="","",Eingaben!$M$19) | L61: =IF(Eingaben!$B$19="","",'Steuer & AfA'!L61) | M61: =IF(Eingaben!$B$19="","",E61+L61-I61-K61) | N61: =IF(Eingaben!$B$19="","",M61/12) | O61: =IF(Eingaben!$B$19="","",Eingaben!$AF$19) | P61: =IF(Eingaben!$B$19="","",Eingaben!$AE$19)
A62: 6 | B62: =IF(Eingaben!$B$19="","",Eingaben!$B$19) | C62: 8 | D62: =IF(Eingaben!$B$19="","",J61) | E62: =IF(Eingaben!$B$19="","",Eingaben!$AC$19*12*(1+Eingaben!$K$19)^(8-1)) | F62: =IF(Eingaben!$B$19="","",E62/12) | G62: =IF(Eingaben!$B$19="","",I62-H62) | H62: =IF(Eingaben!$B$19="","",D62-J62) | I62: =IF(Eingaben!$B$19="","",P62*12) | J62: =IF(Eingaben!$B$19="","",IF(O62=0,MAX(0,D62-P62*12),MAX(0,D62*(1+O62)^12-P62*((1+O62)^12-1)/O62))) | K62: =IF(Eingaben!$B$19="","",Eingaben!$M$19) | L62: =IF(Eingaben!$B$19="","",'Steuer & AfA'!L62) | M62: =IF(Eingaben!$B$19="","",E62+L62-I62-K62) | N62: =IF(Eingaben!$B$19="","",M62/12) | O62: =IF(Eingaben!$B$19="","",Eingaben!$AF$19) | P62: =IF(Eingaben!$B$19="","",Eingaben!$AE$19)
A63: 6 | B63: =IF(Eingaben!$B$19="","",Eingaben!$B$19) | C63: 9 | D63: =IF(Eingaben!$B$19="","",J62) | E63: =IF(Eingaben!$B$19="","",Eingaben!$AC$19*12*(1+Eingaben!$K$19)^(9-1)) | F63: =IF(Eingaben!$B$19="","",E63/12) | G63: =IF(Eingaben!$B$19="","",I63-H63) | H63: =IF(Eingaben!$B$19="","",D63-J63) | I63: =IF(Eingaben!$B$19="","",P63*12) | J63: =IF(Eingaben!$B$19="","",IF(O63=0,MAX(0,D63-P63*12),MAX(0,D63*(1+O63)^12-P63*((1+O63)^12-1)/O63))) | K63: =IF(Eingaben!$B$19="","",Eingaben!$M$19) | L63: =IF(Eingaben!$B$19="","",'Steuer & AfA'!L63) | M63: =IF(Eingaben!$B$19="","",E63+L63-I63-K63) | N63: =IF(Eingaben!$B$19="","",M63/12) | O63: =IF(Eingaben!$B$19="","",Eingaben!$AF$19) | P63: =IF(Eingaben!$B$19="","",Eingaben!$AE$19)
A64: 6 | B64: =IF(Eingaben!$B$19="","",Eingaben!$B$19) | C64: 10 | D64: =IF(Eingaben!$B$19="","",J63) | E64: =IF(Eingaben!$B$19="","",Eingaben!$AC$19*12*(1+Eingaben!$K$19)^(10-1)) | F64: =IF(Eingaben!$B$19="","",E64/12) | G64: =IF(Eingaben!$B$19="","",I64-H64) | H64: =IF(Eingaben!$B$19="","",D64-J64) | I64: =IF(Eingaben!$B$19="","",P64*12) | J64: =IF(Eingaben!$B$19="","",IF(O64=0,MAX(0,D64-P64*12),MAX(0,D64*(1+O64)^12-P64*((1+O64)^12-1)/O64))) | K64: =IF(Eingaben!$B$19="","",Eingaben!$M$19) | L64: =IF(Eingaben!$B$19="","",'Steuer & AfA'!L64) | M64: =IF(Eingaben!$B$19="","",E64+L64-I64-K64) | N64: =IF(Eingaben!$B$19="","",M64/12) | O64: =IF(Eingaben!$B$19="","",Eingaben!$AF$19) | P64: =IF(Eingaben!$B$19="","",Eingaben!$AE$19)
A65: 7 | B65: =IF(Eingaben!$B$20="","",Eingaben!$B$20) | C65: 1 | D65: =IF(Eingaben!$B$20="","",Eingaben!$AB$20) | E65: =IF(Eingaben!$B$20="","",Eingaben!$AC$20*12*(1+Eingaben!$K$20)^(1-1)) | F65: =IF(Eingaben!$B$20="","",E65/12) | G65: =IF(Eingaben!$B$20="","",I65-H65) | H65: =IF(Eingaben!$B$20="","",D65-J65) | I65: =IF(Eingaben!$B$20="","",P65*12) | J65: =IF(Eingaben!$B$20="","",IF(O65=0,MAX(0,D65-P65*12),MAX(0,D65*(1+O65)^12-P65*((1+O65)^12-1)/O65))) | K65: =IF(Eingaben!$B$20="","",Eingaben!$M$20) | L65: =IF(Eingaben!$B$20="","",'Steuer & AfA'!L65) | M65: =IF(Eingaben!$B$20="","",E65+L65-I65-K65) | N65: =IF(Eingaben!$B$20="","",M65/12) | O65: =IF(Eingaben!$B$20="","",Eingaben!$AF$20) | P65: =IF(Eingaben!$B$20="","",Eingaben!$AE$20)
A66: 7 | B66: =IF(Eingaben!$B$20="","",Eingaben!$B$20) | C66: 2 | D66: =IF(Eingaben!$B$20="","",J65) | E66: =IF(Eingaben!$B$20="","",Eingaben!$AC$20*12*(1+Eingaben!$K$20)^(2-1)) | F66: =IF(Eingaben!$B$20="","",E66/12) | G66: =IF(Eingaben!$B$20="","",I66-H66) | H66: =IF(Eingaben!$B$20="","",D66-J66) | I66: =IF(Eingaben!$B$20="","",P66*12) | J66: =IF(Eingaben!$B$20="","",IF(O66=0,MAX(0,D66-P66*12),MAX(0,D66*(1+O66)^12-P66*((1+O66)^12-1)/O66))) | K66: =IF(Eingaben!$B$20="","",Eingaben!$M$20) | L66: =IF(Eingaben!$B$20="","",'Steuer & AfA'!L66) | M66: =IF(Eingaben!$B$20="","",E66+L66-I66-K66) | N66: =IF(Eingaben!$B$20="","",M66/12) | O66: =IF(Eingaben!$B$20="","",Eingaben!$AF$20) | P66: =IF(Eingaben!$B$20="","",Eingaben!$AE$20)
A67: 7 | B67: =IF(Eingaben!$B$20="","",Eingaben!$B$20) | C67: 3 | D67: =IF(Eingaben!$B$20="","",J66) | E67: =IF(Eingaben!$B$20="","",Eingaben!$AC$20*12*(1+Eingaben!$K$20)^(3-1)) | F67: =IF(Eingaben!$B$20="","",E67/12) | G67: =IF(Eingaben!$B$20="","",I67-H67) | H67: =IF(Eingaben!$B$20="","",D67-J67) | I67: =IF(Eingaben!$B$20="","",P67*12) | J67: =IF(Eingaben!$B$20="","",IF(O67=0,MAX(0,D67-P67*12),MAX(0,D67*(1+O67)^12-P67*((1+O67)^12-1)/O67))) | K67: =IF(Eingaben!$B$20="","",Eingaben!$M$20) | L67: =IF(Eingaben!$B$20="","",'Steuer & AfA'!L67) | M67: =IF(Eingaben!$B$20="","",E67+L67-I67-K67) | N67: =IF(Eingaben!$B$20="","",M67/12) | O67: =IF(Eingaben!$B$20="","",Eingaben!$AF$20) | P67: =IF(Eingaben!$B$20="","",Eingaben!$AE$20)
A68: 7 | B68: =IF(Eingaben!$B$20="","",Eingaben!$B$20) | C68: 4 | D68: =IF(Eingaben!$B$20="","",J67) | E68: =IF(Eingaben!$B$20="","",Eingaben!$AC$20*12*(1+Eingaben!$K$20)^(4-1)) | F68: =IF(Eingaben!$B$20="","",E68/12) | G68: =IF(Eingaben!$B$20="","",I68-H68) | H68: =IF(Eingaben!$B$20="","",D68-J68) | I68: =IF(Eingaben!$B$20="","",P68*12) | J68: =IF(Eingaben!$B$20="","",IF(O68=0,MAX(0,D68-P68*12),MAX(0,D68*(1+O68)^12-P68*((1+O68)^12-1)/O68))) | K68: =IF(Eingaben!$B$20="","",Eingaben!$M$20) | L68: =IF(Eingaben!$B$20="","",'Steuer & AfA'!L68) | M68: =IF(Eingaben!$B$20="","",E68+L68-I68-K68) | N68: =IF(Eingaben!$B$20="","",M68/12) | O68: =IF(Eingaben!$B$20="","",Eingaben!$AF$20) | P68: =IF(Eingaben!$B$20="","",Eingaben!$AE$20)
A69: 7 | B69: =IF(Eingaben!$B$20="","",Eingaben!$B$20) | C69: 5 | D69: =IF(Eingaben!$B$20="","",J68) | E69: =IF(Eingaben!$B$20="","",Eingaben!$AC$20*12*(1+Eingaben!$K$20)^(5-1)) | F69: =IF(Eingaben!$B$20="","",E69/12) | G69: =IF(Eingaben!$B$20="","",I69-H69) | H69: =IF(Eingaben!$B$20="","",D69-J69) | I69: =IF(Eingaben!$B$20="","",P69*12) | J69: =IF(Eingaben!$B$20="","",IF(O69=0,MAX(0,D69-P69*12),MAX(0,D69*(1+O69)^12-P69*((1+O69)^12-1)/O69))) | K69: =IF(Eingaben!$B$20="","",Eingaben!$M$20) | L69: =IF(Eingaben!$B$20="","",'Steuer & AfA'!L69) | M69: =IF(Eingaben!$B$20="","",E69+L69-I69-K69) | N69: =IF(Eingaben!$B$20="","",M69/12) | O69: =IF(Eingaben!$B$20="","",Eingaben!$AF$20) | P69: =IF(Eingaben!$B$20="","",Eingaben!$AE$20)
A70: 7 | B70: =IF(Eingaben!$B$20="","",Eingaben!$B$20) | C70: 6 | D70: =IF(Eingaben!$B$20="","",J69) | E70: =IF(Eingaben!$B$20="","",Eingaben!$AC$20*12*(1+Eingaben!$K$20)^(6-1)) | F70: =IF(Eingaben!$B$20="","",E70/12) | G70: =IF(Eingaben!$B$20="","",I70-H70) | H70: =IF(Eingaben!$B$20="","",D70-J70) | I70: =IF(Eingaben!$B$20="","",P70*12) | J70: =IF(Eingaben!$B$20="","",IF(O70=0,MAX(0,D70-P70*12),MAX(0,D70*(1+O70)^12-P70*((1+O70)^12-1)/O70))) | K70: =IF(Eingaben!$B$20="","",Eingaben!$M$20) | L70: =IF(Eingaben!$B$20="","",'Steuer & AfA'!L70) | M70: =IF(Eingaben!$B$20="","",E70+L70-I70-K70) | N70: =IF(Eingaben!$B$20="","",M70/12) | O70: =IF(Eingaben!$B$20="","",Eingaben!$AF$20) | P70: =IF(Eingaben!$B$20="","",Eingaben!$AE$20)
A71: 7 | B71: =IF(Eingaben!$B$20="","",Eingaben!$B$20) | C71: 7 | D71: =IF(Eingaben!$B$20="","",J70) | E71: =IF(Eingaben!$B$20="","",Eingaben!$AC$20*12*(1+Eingaben!$K$20)^(7-1)) | F71: =IF(Eingaben!$B$20="","",E71/12) | G71: =IF(Eingaben!$B$20="","",I71-H71) | H71: =IF(Eingaben!$B$20="","",D71-J71) | I71: =IF(Eingaben!$B$20="","",P71*12) | J71: =IF(Eingaben!$B$20="","",IF(O71=0,MAX(0,D71-P71*12),MAX(0,D71*(1+O71)^12-P71*((1+O71)^12-1)/O71))) | K71: =IF(Eingaben!$B$20="","",Eingaben!$M$20) | L71: =IF(Eingaben!$B$20="","",'Steuer & AfA'!L71) | M71: =IF(Eingaben!$B$20="","",E71+L71-I71-K71) | N71: =IF(Eingaben!$B$20="","",M71/12) | O71: =IF(Eingaben!$B$20="","",Eingaben!$AF$20) | P71: =IF(Eingaben!$B$20="","",Eingaben!$AE$20)
A72: 7 | B72: =IF(Eingaben!$B$20="","",Eingaben!$B$20) | C72: 8 | D72: =IF(Eingaben!$B$20="","",J71) | E72: =IF(Eingaben!$B$20="","",Eingaben!$AC$20*12*(1+Eingaben!$K$20)^(8-1)) | F72: =IF(Eingaben!$B$20="","",E72/12) | G72: =IF(Eingaben!$B$20="","",I72-H72) | H72: =IF(Eingaben!$B$20="","",D72-J72) | I72: =IF(Eingaben!$B$20="","",P72*12) | J72: =IF(Eingaben!$B$20="","",IF(O72=0,MAX(0,D72-P72*12),MAX(0,D72*(1+O72)^12-P72*((1+O72)^12-1)/O72))) | K72: =IF(Eingaben!$B$20="","",Eingaben!$M$20) | L72: =IF(Eingaben!$B$20="","",'Steuer & AfA'!L72) | M72: =IF(Eingaben!$B$20="","",E72+L72-I72-K72) | N72: =IF(Eingaben!$B$20="","",M72/12) | O72: =IF(Eingaben!$B$20="","",Eingaben!$AF$20) | P72: =IF(Eingaben!$B$20="","",Eingaben!$AE$20)
A73: 7 | B73: =IF(Eingaben!$B$20="","",Eingaben!$B$20) | C73: 9 | D73: =IF(Eingaben!$B$20="","",J72) | E73: =IF(Eingaben!$B$20="","",Eingaben!$AC$20*12*(1+Eingaben!$K$20)^(9-1)) | F73: =IF(Eingaben!$B$20="","",E73/12) | G73: =IF(Eingaben!$B$20="","",I73-H73) | H73: =IF(Eingaben!$B$20="","",D73-J73) | I73: =IF(Eingaben!$B$20="","",P73*12) | J73: =IF(Eingaben!$B$20="","",IF(O73=0,MAX(0,D73-P73*12),MAX(0,D73*(1+O73)^12-P73*((1+O73)^12-1)/O73))) | K73: =IF(Eingaben!$B$20="","",Eingaben!$M$20) | L73: =IF(Eingaben!$B$20="","",'Steuer & AfA'!L73) | M73: =IF(Eingaben!$B$20="","",E73+L73-I73-K73) | N73: =IF(Eingaben!$B$20="","",M73/12) | O73: =IF(Eingaben!$B$20="","",Eingaben!$AF$20) | P73: =IF(Eingaben!$B$20="","",Eingaben!$AE$20)
A74: 7 | B74: =IF(Eingaben!$B$20="","",Eingaben!$B$20) | C74: 10 | D74: =IF(Eingaben!$B$20="","",J73) | E74: =IF(Eingaben!$B$20="","",Eingaben!$AC$20*12*(1+Eingaben!$K$20)^(10-1)) | F74: =IF(Eingaben!$B$20="","",E74/12) | G74: =IF(Eingaben!$B$20="","",I74-H74) | H74: =IF(Eingaben!$B$20="","",D74-J74) | I74: =IF(Eingaben!$B$20="","",P74*12) | J74: =IF(Eingaben!$B$20="","",IF(O74=0,MAX(0,D74-P74*12),MAX(0,D74*(1+O74)^12-P74*((1+O74)^12-1)/O74))) | K74: =IF(Eingaben!$B$20="","",Eingaben!$M$20) | L74: =IF(Eingaben!$B$20="","",'Steuer & AfA'!L74) | M74: =IF(Eingaben!$B$20="","",E74+L74-I74-K74) | N74: =IF(Eingaben!$B$20="","",M74/12) | O74: =IF(Eingaben!$B$20="","",Eingaben!$AF$20) | P74: =IF(Eingaben!$B$20="","",Eingaben!$AE$20)
A75: 8 | B75: =IF(Eingaben!$B$21="","",Eingaben!$B$21) | C75: 1 | D75: =IF(Eingaben!$B$21="","",Eingaben!$AB$21) | E75: =IF(Eingaben!$B$21="","",Eingaben!$AC$21*12*(1+Eingaben!$K$21)^(1-1)) | F75: =IF(Eingaben!$B$21="","",E75/12) | G75: =IF(Eingaben!$B$21="","",I75-H75) | H75: =IF(Eingaben!$B$21="","",D75-J75) | I75: =IF(Eingaben!$B$21="","",P75*12) | J75: =IF(Eingaben!$B$21="","",IF(O75=0,MAX(0,D75-P75*12),MAX(0,D75*(1+O75)^12-P75*((1+O75)^12-1)/O75))) | K75: =IF(Eingaben!$B$21="","",Eingaben!$M$21) | L75: =IF(Eingaben!$B$21="","",'Steuer & AfA'!L75) | M75: =IF(Eingaben!$B$21="","",E75+L75-I75-K75) | N75: =IF(Eingaben!$B$21="","",M75/12) | O75: =IF(Eingaben!$B$21="","",Eingaben!$AF$21) | P75: =IF(Eingaben!$B$21="","",Eingaben!$AE$21)
A76: 8 | B76: =IF(Eingaben!$B$21="","",Eingaben!$B$21) | C76: 2 | D76: =IF(Eingaben!$B$21="","",J75) | E76: =IF(Eingaben!$B$21="","",Eingaben!$AC$21*12*(1+Eingaben!$K$21)^(2-1)) | F76: =IF(Eingaben!$B$21="","",E76/12) | G76: =IF(Eingaben!$B$21="","",I76-H76) | H76: =IF(Eingaben!$B$21="","",D76-J76) | I76: =IF(Eingaben!$B$21="","",P76*12) | J76: =IF(Eingaben!$B$21="","",IF(O76=0,MAX(0,D76-P76*12),MAX(0,D76*(1+O76)^12-P76*((1+O76)^12-1)/O76))) | K76: =IF(Eingaben!$B$21="","",Eingaben!$M$21) | L76: =IF(Eingaben!$B$21="","",'Steuer & AfA'!L76) | M76: =IF(Eingaben!$B$21="","",E76+L76-I76-K76) | N76: =IF(Eingaben!$B$21="","",M76/12) | O76: =IF(Eingaben!$B$21="","",Eingaben!$AF$21) | P76: =IF(Eingaben!$B$21="","",Eingaben!$AE$21)
A77: 8 | B77: =IF(Eingaben!$B$21="","",Eingaben!$B$21) | C77: 3 | D77: =IF(Eingaben!$B$21="","",J76) | E77: =IF(Eingaben!$B$21="","",Eingaben!$AC$21*12*(1+Eingaben!$K$21)^(3-1)) | F77: =IF(Eingaben!$B$21="","",E77/12) | G77: =IF(Eingaben!$B$21="","",I77-H77) | H77: =IF(Eingaben!$B$21="","",D77-J77) | I77: =IF(Eingaben!$B$21="","",P77*12) | J77: =IF(Eingaben!$B$21="","",IF(O77=0,MAX(0,D77-P77*12),MAX(0,D77*(1+O77)^12-P77*((1+O77)^12-1)/O77))) | K77: =IF(Eingaben!$B$21="","",Eingaben!$M$21) | L77: =IF(Eingaben!$B$21="","",'Steuer & AfA'!L77) | M77: =IF(Eingaben!$B$21="","",E77+L77-I77-K77) | N77: =IF(Eingaben!$B$21="","",M77/12) | O77: =IF(Eingaben!$B$21="","",Eingaben!$AF$21) | P77: =IF(Eingaben!$B$21="","",Eingaben!$AE$21)
A78: 8 | B78: =IF(Eingaben!$B$21="","",Eingaben!$B$21) | C78: 4 | D78: =IF(Eingaben!$B$21="","",J77) | E78: =IF(Eingaben!$B$21="","",Eingaben!$AC$21*12*(1+Eingaben!$K$21)^(4-1)) | F78: =IF(Eingaben!$B$21="","",E78/12) | G78: =IF(Eingaben!$B$21="","",I78-H78) | H78: =IF(Eingaben!$B$21="","",D78-J78) | I78: =IF(Eingaben!$B$21="","",P78*12) | J78: =IF(Eingaben!$B$21="","",IF(O78=0,MAX(0,D78-P78*12),MAX(0,D78*(1+O78)^12-P78*((1+O78)^12-1)/O78))) | K78: =IF(Eingaben!$B$21="","",Eingaben!$M$21) | L78: =IF(Eingaben!$B$21="","",'Steuer & AfA'!L78) | M78: =IF(Eingaben!$B$21="","",E78+L78-I78-K78) | N78: =IF(Eingaben!$B$21="","",M78/12) | O78: =IF(Eingaben!$B$21="","",Eingaben!$AF$21) | P78: =IF(Eingaben!$B$21="","",Eingaben!$AE$21)
A79: 8 | B79: =IF(Eingaben!$B$21="","",Eingaben!$B$21) | C79: 5 | D79: =IF(Eingaben!$B$21="","",J78) | E79: =IF(Eingaben!$B$21="","",Eingaben!$AC$21*12*(1+Eingaben!$K$21)^(5-1)) | F79: =IF(Eingaben!$B$21="","",E79/12) | G79: =IF(Eingaben!$B$21="","",I79-H79) | H79: =IF(Eingaben!$B$21="","",D79-J79) | I79: =IF(Eingaben!$B$21="","",P79*12) | J79: =IF(Eingaben!$B$21="","",IF(O79=0,MAX(0,D79-P79*12),MAX(0,D79*(1+O79)^12-P79*((1+O79)^12-1)/O79))) | K79: =IF(Eingaben!$B$21="","",Eingaben!$M$21) | L79: =IF(Eingaben!$B$21="","",'Steuer & AfA'!L79) | M79: =IF(Eingaben!$B$21="","",E79+L79-I79-K79) | N79: =IF(Eingaben!$B$21="","",M79/12) | O79: =IF(Eingaben!$B$21="","",Eingaben!$AF$21) | P79: =IF(Eingaben!$B$21="","",Eingaben!$AE$21)
A80: 8 | B80: =IF(Eingaben!$B$21="","",Eingaben!$B$21) | C80: 6 | D80: =IF(Eingaben!$B$21="","",J79) | E80: =IF(Eingaben!$B$21="","",Eingaben!$AC$21*12*(1+Eingaben!$K$21)^(6-1)) | F80: =IF(Eingaben!$B$21="","",E80/12) | G80: =IF(Eingaben!$B$21="","",I80-H80) | H80: =IF(Eingaben!$B$21="","",D80-J80) | I80: =IF(Eingaben!$B$21="","",P80*12) | J80: =IF(Eingaben!$B$21="","",IF(O80=0,MAX(0,D80-P80*12),MAX(0,D80*(1+O80)^12-P80*((1+O80)^12-1)/O80))) | K80: =IF(Eingaben!$B$21="","",Eingaben!$M$21) | L80: =IF(Eingaben!$B$21="","",'Steuer & AfA'!L80) | M80: =IF(Eingaben!$B$21="","",E80+L80-I80-K80) | N80: =IF(Eingaben!$B$21="","",M80/12) | O80: =IF(Eingaben!$B$21="","",Eingaben!$AF$21) | P80: =IF(Eingaben!$B$21="","",Eingaben!$AE$21)
A81: 8 | B81: =IF(Eingaben!$B$21="","",Eingaben!$B$21) | C81: 7 | D81: =IF(Eingaben!$B$21="","",J80) | E81: =IF(Eingaben!$B$21="","",Eingaben!$AC$21*12*(1+Eingaben!$K$21)^(7-1)) | F81: =IF(Eingaben!$B$21="","",E81/12) | G81: =IF(Eingaben!$B$21="","",I81-H81) | H81: =IF(Eingaben!$B$21="","",D81-J81) | I81: =IF(Eingaben!$B$21="","",P81*12) | J81: =IF(Eingaben!$B$21="","",IF(O81=0,MAX(0,D81-P81*12),MAX(0,D81*(1+O81)^12-P81*((1+O81)^12-1)/O81))) | K81: =IF(Eingaben!$B$21="","",Eingaben!$M$21) | L81: =IF(Eingaben!$B$21="","",'Steuer & AfA'!L81) | M81: =IF(Eingaben!$B$21="","",E81+L81-I81-K81) | N81: =IF(Eingaben!$B$21="","",M81/12) | O81: =IF(Eingaben!$B$21="","",Eingaben!$AF$21) | P81: =IF(Eingaben!$B$21="","",Eingaben!$AE$21)
A82: 8 | B82: =IF(Eingaben!$B$21="","",Eingaben!$B$21) | C82: 8 | D82: =IF(Eingaben!$B$21="","",J81) | E82: =IF(Eingaben!$B$21="","",Eingaben!$AC$21*12*(1+Eingaben!$K$21)^(8-1)) | F82: =IF(Eingaben!$B$21="","",E82/12) | G82: =IF(Eingaben!$B$21="","",I82-H82) | H82: =IF(Eingaben!$B$21="","",D82-J82) | I82: =IF(Eingaben!$B$21="","",P82*12) | J82: =IF(Eingaben!$B$21="","",IF(O82=0,MAX(0,D82-P82*12),MAX(0,D82*(1+O82)^12-P82*((1+O82)^12-1)/O82))) | K82: =IF(Eingaben!$B$21="","",Eingaben!$M$21) | L82: =IF(Eingaben!$B$21="","",'Steuer & AfA'!L82) | M82: =IF(Eingaben!$B$21="","",E82+L82-I82-K82) | N82: =IF(Eingaben!$B$21="","",M82/12) | O82: =IF(Eingaben!$B$21="","",Eingaben!$AF$21) | P82: =IF(Eingaben!$B$21="","",Eingaben!$AE$21)
A83: 8 | B83: =IF(Eingaben!$B$21="","",Eingaben!$B$21) | C83: 9 | D83: =IF(Eingaben!$B$21="","",J82) | E83: =IF(Eingaben!$B$21="","",Eingaben!$AC$21*12*(1+Eingaben!$K$21)^(9-1)) | F83: =IF(Eingaben!$B$21="","",E83/12) | G83: =IF(Eingaben!$B$21="","",I83-H83) | H83: =IF(Eingaben!$B$21="","",D83-J83) | I83: =IF(Eingaben!$B$21="","",P83*12) | J83: =IF(Eingaben!$B$21="","",IF(O83=0,MAX(0,D83-P83*12),MAX(0,D83*(1+O83)^12-P83*((1+O83)^12-1)/O83))) | K83: =IF(Eingaben!$B$21="","",Eingaben!$M$21) | L83: =IF(Eingaben!$B$21="","",'Steuer & AfA'!L83) | M83: =IF(Eingaben!$B$21="","",E83+L83-I83-K83) | N83: =IF(Eingaben!$B$21="","",M83/12) | O83: =IF(Eingaben!$B$21="","",Eingaben!$AF$21) | P83: =IF(Eingaben!$B$21="","",Eingaben!$AE$21)
A84: 8 | B84: =IF(Eingaben!$B$21="","",Eingaben!$B$21) | C84: 10 | D84: =IF(Eingaben!$B$21="","",J83) | E84: =IF(Eingaben!$B$21="","",Eingaben!$AC$21*12*(1+Eingaben!$K$21)^(10-1)) | F84: =IF(Eingaben!$B$21="","",E84/12) | G84: =IF(Eingaben!$B$21="","",I84-H84) | H84: =IF(Eingaben!$B$21="","",D84-J84) | I84: =IF(Eingaben!$B$21="","",P84*12) | J84: =IF(Eingaben!$B$21="","",IF(O84=0,MAX(0,D84-P84*12),MAX(0,D84*(1+O84)^12-P84*((1+O84)^12-1)/O84))) | K84: =IF(Eingaben!$B$21="","",Eingaben!$M$21) | L84: =IF(Eingaben!$B$21="","",'Steuer & AfA'!L84) | M84: =IF(Eingaben!$B$21="","",E84+L84-I84-K84) | N84: =IF(Eingaben!$B$21="","",M84/12) | O84: =IF(Eingaben!$B$21="","",Eingaben!$AF$21) | P84: =IF(Eingaben!$B$21="","",Eingaben!$AE$21)
A85: 9 | B85: =IF(Eingaben!$B$22="","",Eingaben!$B$22) | C85: 1 | D85: =IF(Eingaben!$B$22="","",Eingaben!$AB$22) | E85: =IF(Eingaben!$B$22="","",Eingaben!$AC$22*12*(1+Eingaben!$K$22)^(1-1)) | F85: =IF(Eingaben!$B$22="","",E85/12) | G85: =IF(Eingaben!$B$22="","",I85-H85) | H85: =IF(Eingaben!$B$22="","",D85-J85) | I85: =IF(Eingaben!$B$22="","",P85*12) | J85: =IF(Eingaben!$B$22="","",IF(O85=0,MAX(0,D85-P85*12),MAX(0,D85*(1+O85)^12-P85*((1+O85)^12-1)/O85))) | K85: =IF(Eingaben!$B$22="","",Eingaben!$M$22) | L85: =IF(Eingaben!$B$22="","",'Steuer & AfA'!L85) | M85: =IF(Eingaben!$B$22="","",E85+L85-I85-K85) | N85: =IF(Eingaben!$B$22="","",M85/12) | O85: =IF(Eingaben!$B$22="","",Eingaben!$AF$22) | P85: =IF(Eingaben!$B$22="","",Eingaben!$AE$22)
A86: 9 | B86: =IF(Eingaben!$B$22="","",Eingaben!$B$22) | C86: 2 | D86: =IF(Eingaben!$B$22="","",J85) | E86: =IF(Eingaben!$B$22="","",Eingaben!$AC$22*12*(1+Eingaben!$K$22)^(2-1)) | F86: =IF(Eingaben!$B$22="","",E86/12) | G86: =IF(Eingaben!$B$22="","",I86-H86) | H86: =IF(Eingaben!$B$22="","",D86-J86) | I86: =IF(Eingaben!$B$22="","",P86*12) | J86: =IF(Eingaben!$B$22="","",IF(O86=0,MAX(0,D86-P86*12),MAX(0,D86*(1+O86)^12-P86*((1+O86)^12-1)/O86))) | K86: =IF(Eingaben!$B$22="","",Eingaben!$M$22) | L86: =IF(Eingaben!$B$22="","",'Steuer & AfA'!L86) | M86: =IF(Eingaben!$B$22="","",E86+L86-I86-K86) | N86: =IF(Eingaben!$B$22="","",M86/12) | O86: =IF(Eingaben!$B$22="","",Eingaben!$AF$22) | P86: =IF(Eingaben!$B$22="","",Eingaben!$AE$22)
A87: 9 | B87: =IF(Eingaben!$B$22="","",Eingaben!$B$22) | C87: 3 | D87: =IF(Eingaben!$B$22="","",J86) | E87: =IF(Eingaben!$B$22="","",Eingaben!$AC$22*12*(1+Eingaben!$K$22)^(3-1)) | F87: =IF(Eingaben!$B$22="","",E87/12) | G87: =IF(Eingaben!$B$22="","",I87-H87) | H87: =IF(Eingaben!$B$22="","",D87-J87) | I87: =IF(Eingaben!$B$22="","",P87*12) | J87: =IF(Eingaben!$B$22="","",IF(O87=0,MAX(0,D87-P87*12),MAX(0,D87*(1+O87)^12-P87*((1+O87)^12-1)/O87))) | K87: =IF(Eingaben!$B$22="","",Eingaben!$M$22) | L87: =IF(Eingaben!$B$22="","",'Steuer & AfA'!L87) | M87: =IF(Eingaben!$B$22="","",E87+L87-I87-K87) | N87: =IF(Eingaben!$B$22="","",M87/12) | O87: =IF(Eingaben!$B$22="","",Eingaben!$AF$22) | P87: =IF(Eingaben!$B$22="","",Eingaben!$AE$22)
A88: 9 | B88: =IF(Eingaben!$B$22="","",Eingaben!$B$22) | C88: 4 | D88: =IF(Eingaben!$B$22="","",J87) | E88: =IF(Eingaben!$B$22="","",Eingaben!$AC$22*12*(1+Eingaben!$K$22)^(4-1)) | F88: =IF(Eingaben!$B$22="","",E88/12) | G88: =IF(Eingaben!$B$22="","",I88-H88) | H88: =IF(Eingaben!$B$22="","",D88-J88) | I88: =IF(Eingaben!$B$22="","",P88*12) | J88: =IF(Eingaben!$B$22="","",IF(O88=0,MAX(0,D88-P88*12),MAX(0,D88*(1+O88)^12-P88*((1+O88)^12-1)/O88))) | K88: =IF(Eingaben!$B$22="","",Eingaben!$M$22) | L88: =IF(Eingaben!$B$22="","",'Steuer & AfA'!L88) | M88: =IF(Eingaben!$B$22="","",E88+L88-I88-K88) | N88: =IF(Eingaben!$B$22="","",M88/12) | O88: =IF(Eingaben!$B$22="","",Eingaben!$AF$22) | P88: =IF(Eingaben!$B$22="","",Eingaben!$AE$22)
A89: 9 | B89: =IF(Eingaben!$B$22="","",Eingaben!$B$22) | C89: 5 | D89: =IF(Eingaben!$B$22="","",J88) | E89: =IF(Eingaben!$B$22="","",Eingaben!$AC$22*12*(1+Eingaben!$K$22)^(5-1)) | F89: =IF(Eingaben!$B$22="","",E89/12) | G89: =IF(Eingaben!$B$22="","",I89-H89) | H89: =IF(Eingaben!$B$22="","",D89-J89) | I89: =IF(Eingaben!$B$22="","",P89*12) | J89: =IF(Eingaben!$B$22="","",IF(O89=0,MAX(0,D89-P89*12),MAX(0,D89*(1+O89)^12-P89*((1+O89)^12-1)/O89))) | K89: =IF(Eingaben!$B$22="","",Eingaben!$M$22) | L89: =IF(Eingaben!$B$22="","",'Steuer & AfA'!L89) | M89: =IF(Eingaben!$B$22="","",E89+L89-I89-K89) | N89: =IF(Eingaben!$B$22="","",M89/12) | O89: =IF(Eingaben!$B$22="","",Eingaben!$AF$22) | P89: =IF(Eingaben!$B$22="","",Eingaben!$AE$22)
A90: 9 | B90: =IF(Eingaben!$B$22="","",Eingaben!$B$22) | C90: 6 | D90: =IF(Eingaben!$B$22="","",J89) | E90: =IF(Eingaben!$B$22="","",Eingaben!$AC$22*12*(1+Eingaben!$K$22)^(6-1)) | F90: =IF(Eingaben!$B$22="","",E90/12) | G90: =IF(Eingaben!$B$22="","",I90-H90) | H90: =IF(Eingaben!$B$22="","",D90-J90) | I90: =IF(Eingaben!$B$22="","",P90*12) | J90: =IF(Eingaben!$B$22="","",IF(O90=0,MAX(0,D90-P90*12),MAX(0,D90*(1+O90)^12-P90*((1+O90)^12-1)/O90))) | K90: =IF(Eingaben!$B$22="","",Eingaben!$M$22) | L90: =IF(Eingaben!$B$22="","",'Steuer & AfA'!L90) | M90: =IF(Eingaben!$B$22="","",E90+L90-I90-K90) | N90: =IF(Eingaben!$B$22="","",M90/12) | O90: =IF(Eingaben!$B$22="","",Eingaben!$AF$22) | P90: =IF(Eingaben!$B$22="","",Eingaben!$AE$22)
A91: 9 | B91: =IF(Eingaben!$B$22="","",Eingaben!$B$22) | C91: 7 | D91: =IF(Eingaben!$B$22="","",J90) | E91: =IF(Eingaben!$B$22="","",Eingaben!$AC$22*12*(1+Eingaben!$K$22)^(7-1)) | F91: =IF(Eingaben!$B$22="","",E91/12) | G91: =IF(Eingaben!$B$22="","",I91-H91) | H91: =IF(Eingaben!$B$22="","",D91-J91) | I91: =IF(Eingaben!$B$22="","",P91*12) | J91: =IF(Eingaben!$B$22="","",IF(O91=0,MAX(0,D91-P91*12),MAX(0,D91*(1+O91)^12-P91*((1+O91)^12-1)/O91))) | K91: =IF(Eingaben!$B$22="","",Eingaben!$M$22) | L91: =IF(Eingaben!$B$22="","",'Steuer & AfA'!L91) | M91: =IF(Eingaben!$B$22="","",E91+L91-I91-K91) | N91: =IF(Eingaben!$B$22="","",M91/12) | O91: =IF(Eingaben!$B$22="","",Eingaben!$AF$22) | P91: =IF(Eingaben!$B$22="","",Eingaben!$AE$22)
A92: 9 | B92: =IF(Eingaben!$B$22="","",Eingaben!$B$22) | C92: 8 | D92: =IF(Eingaben!$B$22="","",J91) | E92: =IF(Eingaben!$B$22="","",Eingaben!$AC$22*12*(1+Eingaben!$K$22)^(8-1)) | F92: =IF(Eingaben!$B$22="","",E92/12) | G92: =IF(Eingaben!$B$22="","",I92-H92) | H92: =IF(Eingaben!$B$22="","",D92-J92) | I92: =IF(Eingaben!$B$22="","",P92*12) | J92: =IF(Eingaben!$B$22="","",IF(O92=0,MAX(0,D92-P92*12),MAX(0,D92*(1+O92)^12-P92*((1+O92)^12-1)/O92))) | K92: =IF(Eingaben!$B$22="","",Eingaben!$M$22) | L92: =IF(Eingaben!$B$22="","",'Steuer & AfA'!L92) | M92: =IF(Eingaben!$B$22="","",E92+L92-I92-K92) | N92: =IF(Eingaben!$B$22="","",M92/12) | O92: =IF(Eingaben!$B$22="","",Eingaben!$AF$22) | P92: =IF(Eingaben!$B$22="","",Eingaben!$AE$22)
A93: 9 | B93: =IF(Eingaben!$B$22="","",Eingaben!$B$22) | C93: 9 | D93: =IF(Eingaben!$B$22="","",J92) | E93: =IF(Eingaben!$B$22="","",Eingaben!$AC$22*12*(1+Eingaben!$K$22)^(9-1)) | F93: =IF(Eingaben!$B$22="","",E93/12) | G93: =IF(Eingaben!$B$22="","",I93-H93) | H93: =IF(Eingaben!$B$22="","",D93-J93) | I93: =IF(Eingaben!$B$22="","",P93*12) | J93: =IF(Eingaben!$B$22="","",IF(O93=0,MAX(0,D93-P93*12),MAX(0,D93*(1+O93)^12-P93*((1+O93)^12-1)/O93))) | K93: =IF(Eingaben!$B$22="","",Eingaben!$M$22) | L93: =IF(Eingaben!$B$22="","",'Steuer & AfA'!L93) | M93: =IF(Eingaben!$B$22="","",E93+L93-I93-K93) | N93: =IF(Eingaben!$B$22="","",M93/12) | O93: =IF(Eingaben!$B$22="","",Eingaben!$AF$22) | P93: =IF(Eingaben!$B$22="","",Eingaben!$AE$22)
A94: 9 | B94: =IF(Eingaben!$B$22="","",Eingaben!$B$22) | C94: 10 | D94: =IF(Eingaben!$B$22="","",J93) | E94: =IF(Eingaben!$B$22="","",Eingaben!$AC$22*12*(1+Eingaben!$K$22)^(10-1)) | F94: =IF(Eingaben!$B$22="","",E94/12) | G94: =IF(Eingaben!$B$22="","",I94-H94) | H94: =IF(Eingaben!$B$22="","",D94-J94) | I94: =IF(Eingaben!$B$22="","",P94*12) | J94: =IF(Eingaben!$B$22="","",IF(O94=0,MAX(0,D94-P94*12),MAX(0,D94*(1+O94)^12-P94*((1+O94)^12-1)/O94))) | K94: =IF(Eingaben!$B$22="","",Eingaben!$M$22) | L94: =IF(Eingaben!$B$22="","",'Steuer & AfA'!L94) | M94: =IF(Eingaben!$B$22="","",E94+L94-I94-K94) | N94: =IF(Eingaben!$B$22="","",M94/12) | O94: =IF(Eingaben!$B$22="","",Eingaben!$AF$22) | P94: =IF(Eingaben!$B$22="","",Eingaben!$AE$22)
A95: 10 | B95: =IF(Eingaben!$B$23="","",Eingaben!$B$23) | C95: 1 | D95: =IF(Eingaben!$B$23="","",Eingaben!$AB$23) | E95: =IF(Eingaben!$B$23="","",Eingaben!$AC$23*12*(1+Eingaben!$K$23)^(1-1)) | F95: =IF(Eingaben!$B$23="","",E95/12) | G95: =IF(Eingaben!$B$23="","",I95-H95) | H95: =IF(Eingaben!$B$23="","",D95-J95) | I95: =IF(Eingaben!$B$23="","",P95*12) | J95: =IF(Eingaben!$B$23="","",IF(O95=0,MAX(0,D95-P95*12),MAX(0,D95*(1+O95)^12-P95*((1+O95)^12-1)/O95))) | K95: =IF(Eingaben!$B$23="","",Eingaben!$M$23) | L95: =IF(Eingaben!$B$23="","",'Steuer & AfA'!L95) | M95: =IF(Eingaben!$B$23="","",E95+L95-I95-K95) | N95: =IF(Eingaben!$B$23="","",M95/12) | O95: =IF(Eingaben!$B$23="","",Eingaben!$AF$23) | P95: =IF(Eingaben!$B$23="","",Eingaben!$AE$23)
A96: 10 | B96: =IF(Eingaben!$B$23="","",Eingaben!$B$23) | C96: 2 | D96: =IF(Eingaben!$B$23="","",J95) | E96: =IF(Eingaben!$B$23="","",Eingaben!$AC$23*12*(1+Eingaben!$K$23)^(2-1)) | F96: =IF(Eingaben!$B$23="","",E96/12) | G96: =IF(Eingaben!$B$23="","",I96-H96) | H96: =IF(Eingaben!$B$23="","",D96-J96) | I96: =IF(Eingaben!$B$23="","",P96*12) | J96: =IF(Eingaben!$B$23="","",IF(O96=0,MAX(0,D96-P96*12),MAX(0,D96*(1+O96)^12-P96*((1+O96)^12-1)/O96))) | K96: =IF(Eingaben!$B$23="","",Eingaben!$M$23) | L96: =IF(Eingaben!$B$23="","",'Steuer & AfA'!L96) | M96: =IF(Eingaben!$B$23="","",E96+L96-I96-K96) | N96: =IF(Eingaben!$B$23="","",M96/12) | O96: =IF(Eingaben!$B$23="","",Eingaben!$AF$23) | P96: =IF(Eingaben!$B$23="","",Eingaben!$AE$23)
A97: 10 | B97: =IF(Eingaben!$B$23="","",Eingaben!$B$23) | C97: 3 | D97: =IF(Eingaben!$B$23="","",J96) | E97: =IF(Eingaben!$B$23="","",Eingaben!$AC$23*12*(1+Eingaben!$K$23)^(3-1)) | F97: =IF(Eingaben!$B$23="","",E97/12) | G97: =IF(Eingaben!$B$23="","",I97-H97) | H97: =IF(Eingaben!$B$23="","",D97-J97) | I97: =IF(Eingaben!$B$23="","",P97*12) | J97: =IF(Eingaben!$B$23="","",IF(O97=0,MAX(0,D97-P97*12),MAX(0,D97*(1+O97)^12-P97*((1+O97)^12-1)/O97))) | K97: =IF(Eingaben!$B$23="","",Eingaben!$M$23) | L97: =IF(Eingaben!$B$23="","",'Steuer & AfA'!L97) | M97: =IF(Eingaben!$B$23="","",E97+L97-I97-K97) | N97: =IF(Eingaben!$B$23="","",M97/12) | O97: =IF(Eingaben!$B$23="","",Eingaben!$AF$23) | P97: =IF(Eingaben!$B$23="","",Eingaben!$AE$23)
A98: 10 | B98: =IF(Eingaben!$B$23="","",Eingaben!$B$23) | C98: 4 | D98: =IF(Eingaben!$B$23="","",J97) | E98: =IF(Eingaben!$B$23="","",Eingaben!$AC$23*12*(1+Eingaben!$K$23)^(4-1)) | F98: =IF(Eingaben!$B$23="","",E98/12) | G98: =IF(Eingaben!$B$23="","",I98-H98) | H98: =IF(Eingaben!$B$23="","",D98-J98) | I98: =IF(Eingaben!$B$23="","",P98*12) | J98: =IF(Eingaben!$B$23="","",IF(O98=0,MAX(0,D98-P98*12),MAX(0,D98*(1+O98)^12-P98*((1+O98)^12-1)/O98))) | K98: =IF(Eingaben!$B$23="","",Eingaben!$M$23) | L98: =IF(Eingaben!$B$23="","",'Steuer & AfA'!L98) | M98: =IF(Eingaben!$B$23="","",E98+L98-I98-K98) | N98: =IF(Eingaben!$B$23="","",M98/12) | O98: =IF(Eingaben!$B$23="","",Eingaben!$AF$23) | P98: =IF(Eingaben!$B$23="","",Eingaben!$AE$23)
A99: 10 | B99: =IF(Eingaben!$B$23="","",Eingaben!$B$23) | C99: 5 | D99: =IF(Eingaben!$B$23="","",J98) | E99: =IF(Eingaben!$B$23="","",Eingaben!$AC$23*12*(1+Eingaben!$K$23)^(5-1)) | F99: =IF(Eingaben!$B$23="","",E99/12) | G99: =IF(Eingaben!$B$23="","",I99-H99) | H99: =IF(Eingaben!$B$23="","",D99-J99) | I99: =IF(Eingaben!$B$23="","",P99*12) | J99: =IF(Eingaben!$B$23="","",IF(O99=0,MAX(0,D99-P99*12),MAX(0,D99*(1+O99)^12-P99*((1+O99)^12-1)/O99))) | K99: =IF(Eingaben!$B$23="","",Eingaben!$M$23) | L99: =IF(Eingaben!$B$23="","",'Steuer & AfA'!L99) | M99: =IF(Eingaben!$B$23="","",E99+L99-I99-K99) | N99: =IF(Eingaben!$B$23="","",M99/12) | O99: =IF(Eingaben!$B$23="","",Eingaben!$AF$23) | P99: =IF(Eingaben!$B$23="","",Eingaben!$AE$23)
A100: 10 | B100: =IF(Eingaben!$B$23="","",Eingaben!$B$23) | C100: 6 | D100: =IF(Eingaben!$B$23="","",J99) | E100: =IF(Eingaben!$B$23="","",Eingaben!$AC$23*12*(1+Eingaben!$K$23)^(6-1)) | F100: =IF(Eingaben!$B$23="","",E100/12) | G100: =IF(Eingaben!$B$23="","",I100-H100) | H100: =IF(Eingaben!$B$23="","",D100-J100) | I100: =IF(Eingaben!$B$23="","",P100*12) | J100: =IF(Eingaben!$B$23="","",IF(O100=0,MAX(0,D100-P100*12),MAX(0,D100*(1+O100)^12-P100*((1+O100)^12-1)/O100))) | K100: =IF(Eingaben!$B$23="","",Eingaben!$M$23) | L100: =IF(Eingaben!$B$23="","",'Steuer & AfA'!L100) | M100: =IF(Eingaben!$B$23="","",E100+L100-I100-K100) | N100: =IF(Eingaben!$B$23="","",M100/12) | O100: =IF(Eingaben!$B$23="","",Eingaben!$AF$23) | P100: =IF(Eingaben!$B$23="","",Eingaben!$AE$23)
A101: 10 | B101: =IF(Eingaben!$B$23="","",Eingaben!$B$23) | C101: 7 | D101: =IF(Eingaben!$B$23="","",J100) | E101: =IF(Eingaben!$B$23="","",Eingaben!$AC$23*12*(1+Eingaben!$K$23)^(7-1)) | F101: =IF(Eingaben!$B$23="","",E101/12) | G101: =IF(Eingaben!$B$23="","",I101-H101) | H101: =IF(Eingaben!$B$23="","",D101-J101) | I101: =IF(Eingaben!$B$23="","",P101*12) | J101: =IF(Eingaben!$B$23="","",IF(O101=0,MAX(0,D101-P101*12),MAX(0,D101*(1+O101)^12-P101*((1+O101)^12-1)/O101))) | K101: =IF(Eingaben!$B$23="","",Eingaben!$M$23) | L101: =IF(Eingaben!$B$23="","",'Steuer & AfA'!L101) | M101: =IF(Eingaben!$B$23="","",E101+L101-I101-K101) | N101: =IF(Eingaben!$B$23="","",M101/12) | O101: =IF(Eingaben!$B$23="","",Eingaben!$AF$23) | P101: =IF(Eingaben!$B$23="","",Eingaben!$AE$23)
...

Sheet Steuer & AfA
A1: 🧾 Steuer & AfA – 10-Jahres-Verlauf je Immobilie
A2: AfA-Schedule und Steuervergleich (ohne/mit Immobilie) je Immobilie und Jahr. Isolierte Betrachtung je Objekt gegen das Haushaltseinkommen (vereinfachte Modellrechnung).
A4: Nr. | B4: Immobilie | C4: Jahr | D4: Restbuchwert Jahresanfang (€) | E4: Basis-AfA (€) | F4: Sonder-AfA (€) | G4: AfA gesamt (€) | H4: Restbuchwert Jahresende (€) | I4: Steuerliches Ergebnis (€) | J4: Steuer ohne Immobilie (€) | K4: Steuer mit Immobilie (€) | L4: Steuerwirkung (€) | N4: ZvE eff. ohne | O4: Basissteuer ohne | P4: ZvE eff. mit | Q4: Basissteuer mit
A5: 1 | B5: =IF(Eingaben!$B$14="","",Cashflow!B5) -> Musterwohnung Berlin | C5: 1 | D5: =IF(Eingaben!$B$14="","",Eingaben!$AD$14) -> 198400 | E5: =IF(Eingaben!$B$14="","",MIN(D5,MAX(0,IF(Eingaben!$S$14="Ja",D5*Eingaben!$T$14,Eingaben!$AD$14*Eingaben!$Q$14)))) -> 3968 | F5: =IF(Eingaben!$B$14="","",MIN(MAX(0,IF(AND(Eingaben!$U$14="Ja",1<=Eingaben!$W$14),Eingaben!$AD$14*Eingaben!$V$14,0)),MAX(0,D5-E5))) -> 0 | G5: =IF(Eingaben!$B$14="","",E5+F5) -> 3968 | H5: =IF(Eingaben!$B$14="","",D5-G5) -> 194432 | I5: =IF(Eingaben!$B$14="","",Cashflow!E5-Cashflow!G5-G5) -> -5095.2186 | J5: =IF(Eingaben!$B$14="","",IF(Eingaben!$D$6="Ja",2*MAX(0,O5),MAX(0,O5))) -> 0 | K5: =IF(Eingaben!$B$14="","",IF(Eingaben!$D$6="Ja",2*MAX(0,Q5),MAX(0,Q5))) -> 0 | L5: =IF(Eingaben!$B$14="","",IF(Eingaben!$D$5>0,J5-K5,-I5*Eingaben!$D$9)) -> 2038.0874 | N5: =IF(Eingaben!$B$14="","",IF(Eingaben!$D$6="Ja",Eingaben!$F$6/2,Eingaben!$F$6)) -> 0 | O5: =IF(Eingaben!$B$14="","",IF(N5<=12348,0,IF(N5<=17799,(914.51*((N5-12348)/10000)+1400)*((N5-12348)/10000),IF(N5<=69878,(181.19*((N5-17799)/10000)+2397)*((N5-17799)/10000)+1025.38,IF(N5<=277825,0.42*N5-10637.32,0.45*N5-18971.07))))) -> 0 | P5: =IF(Eingaben!$B$14="","",IF(Eingaben!$D$6="Ja",MAX(0,Eingaben!$F$6+I5)/2,MAX(0,Eingaben!$F$6+I5))) -> 0 | Q5: =IF(Eingaben!$B$14="","",IF(P5<=12348,0,IF(P5<=17799,(914.51*((P5-12348)/10000)+1400)*((P5-12348)/10000),IF(P5<=69878,(181.19*((P5-17799)/10000)+2397)*((P5-17799)/10000)+1025.38,IF(P5<=277825,0.42*P5-10637.32,0.45*P5-18971.07))))) -> 0
A6: 1 | B6: =IF(Eingaben!$B$14="","",Cashflow!B6) -> Musterwohnung Berlin | C6: 2 | D6: =IF(Eingaben!$B$14="","",H5) -> 194432 | E6: =IF(Eingaben!$B$14="","",MIN(D6,MAX(0,IF(Eingaben!$S$14="Ja",D6*Eingaben!$T$14,Eingaben!$AD$14*Eingaben!$Q$14)))) -> 3968 | F6: =IF(Eingaben!$B$14="","",MIN(MAX(0,IF(AND(Eingaben!$U$14="Ja",2<=Eingaben!$W$14),Eingaben!$AD$14*Eingaben!$V$14,0)),MAX(0,D6-E6))) -> 0 | G6: =IF(Eingaben!$B$14="","",E6+F6) -> 3968 | H6: =IF(Eingaben!$B$14="","",D6-G6) -> 190464 | I6: =IF(Eingaben!$B$14="","",Cashflow!E6-Cashflow!G6-G6) -> -4802.1522 | J6: =IF(Eingaben!$B$14="","",IF(Eingaben!$D$6="Ja",2*MAX(0,O6),MAX(0,O6))) -> 0 | K6: =IF(Eingaben!$B$14="","",IF(Eingaben!$D$6="Ja",2*MAX(0,Q6),MAX(0,Q6))) -> 0 | L6: =IF(Eingaben!$B$14="","",IF(Eingaben!$D$5>0,J6-K6,-I6*Eingaben!$D$9)) -> 1920.8609 | N6: =IF(Eingaben!$B$14="","",IF(Eingaben!$D$6="Ja",Eingaben!$F$6/2,Eingaben!$F$6)) -> 0 | O6: =IF(Eingaben!$B$14="","",IF(N6<=12348,0,IF(N6<=17799,(914.51*((N6-12348)/10000)+1400)*((N6-12348)/10000),IF(N6<=69878,(181.19*((N6-17799)/10000)+2397)*((N6-17799)/10000)+1025.38,IF(N6<=277825,0.42*N6-10637.32,0.45*N6-18971.07))))) -> 0 | P6: =IF(Eingaben!$B$14="","",IF(Eingaben!$D$6="Ja",MAX(0,Eingaben!$F$6+I6)/2,MAX(0,Eingaben!$F$6+I6))) -> 0 | Q6: =IF(Eingaben!$B$14="","",IF(P6<=12348,0,IF(P6<=17799,(914.51*((P6-12348)/10000)+1400)*((P6-12348)/10000),IF(P6<=69878,(181.19*((P6-17799)/10000)+2397)*((P6-17799)/10000)+1025.38,IF(P6<=277825,0.42*P6-10637.32,0.45*P6-18971.07))))) -> 0
A7: 1 | B7: =IF(Eingaben!$B$14="","",Cashflow!B7) -> Musterwohnung Berlin | C7: 3 | D7: =IF(Eingaben!$B$14="","",H6) -> 190464 | E7: =IF(Eingaben!$B$14="","",MIN(D7,MAX(0,IF(Eingaben!$S$14="Ja",D7*Eingaben!$T$14,Eingaben!$AD$14*Eingaben!$Q$14)))) -> 3968 | F7: =IF(Eingaben!$B$14="","",MIN(MAX(0,IF(AND(Eingaben!$U$14="Ja",3<=Eingaben!$W$14),Eingaben!$AD$14*Eingaben!$V$14,0)),MAX(0,D7-E7))) -> 0 | G7: =IF(Eingaben!$B$14="","",E7+F7) -> 3968 | H7: =IF(Eingaben!$B$14="","",D7-G7) -> 186496 | I7: =IF(Eingaben!$B$14="","",Cashflow!E7-Cashflow!G7-G7) -> -4500.7542 | J7: =IF(Eingaben!$B$14="","",IF(Eingaben!$D$6="Ja",2*MAX(0,O7),MAX(0,O7))) -> 0 | K7: =IF(Eingaben!$B$14="","",IF(Eingaben!$D$6="Ja",2*MAX(0,Q7),MAX(0,Q7))) -> 0 | L7: =IF(Eingaben!$B$14="","",IF(Eingaben!$D$5>0,J7-K7,-I7*Eingaben!$D$9)) -> 1800.3017 | N7: =IF(Eingaben!$B$14="","",IF(Eingaben!$D$6="Ja",Eingaben!$F$6/2,Eingaben!$F$6)) -> 0 | O7: =IF(Eingaben!$B$14="","",IF(N7<=12348,0,IF(N7<=17799,(914.51*((N7-12348)/10000)+1400)*((N7-12348)/10000),IF(N7<=69878,(181.19*((N7-17799)/10000)+2397)*((N7-17799)/10000)+1025.38,IF(N7<=277825,0.42*N7-10637.32,0.45*N7-18971.07))))) -> 0 | P7: =IF(Eingaben!$B$14="","",IF(Eingaben!$D$6="Ja",MAX(0,Eingaben!$F$6+I7)/2,MAX(0,Eingaben!$F$6+I7))) -> 0 | Q7: =IF(Eingaben!$B$14="","",IF(P7<=12348,0,IF(P7<=17799,(914.51*((P7-12348)/10000)+1400)*((P7-12348)/10000),IF(P7<=69878,(181.19*((P7-17799)/10000)+2397)*((P7-17799)/10000)+1025.38,IF(P7<=277825,0.42*P7-10637.32,0.45*P7-18971.07))))) -> 0
A8: 1 | B8: =IF(Eingaben!$B$14="","",Cashflow!B8) -> Musterwohnung Berlin | C8: 4 | D8: =IF(Eingaben!$B$14="","",H7) -> 186496 | E8: =IF(Eingaben!$B$14="","",MIN(D8,MAX(0,IF(Eingaben!$S$14="Ja",D8*Eingaben!$T$14,Eingaben!$AD$14*Eingaben!$Q$14)))) -> 3968 | F8: =IF(Eingaben!$B$14="","",MIN(MAX(0,IF(AND(Eingaben!$U$14="Ja",4<=Eingaben!$W$14),Eingaben!$AD$14*Eingaben!$V$14,0)),MAX(0,D8-E8))) -> 0 | G8: =IF(Eingaben!$B$14="","",E8+F8) -> 3968 | H8: =IF(Eingaben!$B$14="","",D8-G8) -> 182528 | I8: =IF(Eingaben!$B$14="","",Cashflow!E8-Cashflow!G8-G8) -> -4190.7523 | J8: =IF(Eingaben!$B$14="","",IF(Eingaben!$D$6="Ja",2*MAX(0,O8),MAX(0,O8))) -> 0 | K8: =IF(Eingaben!$B$14="","",IF(Eingaben!$D$6="Ja",2*MAX(0,Q8),MAX(0,Q8))) -> 0 | L8: =IF(Eingaben!$B$14="","",IF(Eingaben!$D$5>0,J8-K8,-I8*Eingaben!$D$9)) -> 1676.3009 | N8: =IF(Eingaben!$B$14="","",IF(Eingaben!$D$6="Ja",Eingaben!$F$6/2,Eingaben!$F$6)) -> 0 | O8: =IF(Eingaben!$B$14="","",IF(N8<=12348,0,IF(N8<=17799,(914.51*((N8-12348)/10000)+1400)*((N8-12348)/10000),IF(N8<=69878,(181.19*((N8-17799)/10000)+2397)*((N8-17799)/10000)+1025.38,IF(N8<=277825,0.42*N8-10637.32,0.45*N8-18971.07))))) -> 0 | P8: =IF(Eingaben!$B$14="","",IF(Eingaben!$D$6="Ja",MAX(0,Eingaben!$F$6+I8)/2,MAX(0,Eingaben!$F$6+I8))) -> 0 | Q8: =IF(Eingaben!$B$14="","",IF(P8<=12348,0,IF(P8<=17799,(914.51*((P8-12348)/10000)+1400)*((P8-12348)/10000),IF(P8<=69878,(181.19*((P8-17799)/10000)+2397)*((P8-17799)/10000)+1025.38,IF(P8<=277825,0.42*P8-10637.32,0.45*P8-18971.07))))) -> 0
A9: 1 | B9: =IF(Eingaben!$B$14="","",Cashflow!B9) -> Musterwohnung Berlin | C9: 5 | D9: =IF(Eingaben!$B$14="","",H8) -> 182528 | E9: =IF(Eingaben!$B$14="","",MIN(D9,MAX(0,IF(Eingaben!$S$14="Ja",D9*Eingaben!$T$14,Eingaben!$AD$14*Eingaben!$Q$14)))) -> 3968 | F9: =IF(Eingaben!$B$14="","",MIN(MAX(0,IF(AND(Eingaben!$U$14="Ja",5<=Eingaben!$W$14),Eingaben!$AD$14*Eingaben!$V$14,0)),MAX(0,D9-E9))) -> 0 | G9: =IF(Eingaben!$B$14="","",E9+F9) -> 3968 | H9: =IF(Eingaben!$B$14="","",D9-G9) -> 178560 | I9: =IF(Eingaben!$B$14="","",Cashflow!E9-Cashflow!G9-G9) -> -3871.8641 | J9: =IF(Eingaben!$B$14="","",IF(Eingaben!$D$6="Ja",2*MAX(0,O9),MAX(0,O9))) -> 0 | K9: =IF(Eingaben!$B$14="","",IF(Eingaben!$D$6="Ja",2*MAX(0,Q9),MAX(0,Q9))) -> 0 | L9: =IF(Eingaben!$B$14="","",IF(Eingaben!$D$5>0,J9-K9,-I9*Eingaben!$D$9)) -> 1548.7457 | N9: =IF(Eingaben!$B$14="","",IF(Eingaben!$D$6="Ja",Eingaben!$F$6/2,Eingaben!$F$6)) -> 0 | O9: =IF(Eingaben!$B$14="","",IF(N9<=12348,0,IF(N9<=17799,(914.51*((N9-12348)/10000)+1400)*((N9-12348)/10000),IF(N9<=69878,(181.19*((N9-17799)/10000)+2397)*((N9-17799)/10000)+1025.38,IF(N9<=277825,0.42*N9-10637.32,0.45*N9-18971.07))))) -> 0 | P9: =IF(Eingaben!$B$14="","",IF(Eingaben!$D$6="Ja",MAX(0,Eingaben!$F$6+I9)/2,MAX(0,Eingaben!$F$6+I9))) -> 0 | Q9: =IF(Eingaben!$B$14="","",IF(P9<=12348,0,IF(P9<=17799,(914.51*((P9-12348)/10000)+1400)*((P9-12348)/10000),IF(P9<=69878,(181.19*((P9-17799)/10000)+2397)*((P9-17799)/10000)+1025.38,IF(P9<=277825,0.42*P9-10637.32,0.45*P9-18971.07))))) -> 0
A10: 1 | B10: =IF(Eingaben!$B$14="","",Cashflow!B10) -> Musterwohnung Berlin | C10: 6 | D10: =IF(Eingaben!$B$14="","",H9) -> 178560 | E10: =IF(Eingaben!$B$14="","",MIN(D10,MAX(0,IF(Eingaben!$S$14="Ja",D10*Eingaben!$T$14,Eingaben!$AD$14*Eingaben!$Q$14)))) -> 3968 | F10: =IF(Eingaben!$B$14="","",MIN(MAX(0,IF(AND(Eingaben!$U$14="Ja",6<=Eingaben!$W$14),Eingaben!$AD$14*Eingaben!$V$14,0)),MAX(0,D10-E10))) -> 0 | G10: =IF(Eingaben!$B$14="","",E10+F10) -> 3968 | H10: =IF(Eingaben!$B$14="","",D10-G10) -> 174592 | I10: =IF(Eingaben!$B$14="","",Cashflow!E10-Cashflow!G10-G10) -> -3543.7969 | J10: =IF(Eingaben!$B$14="","",IF(Eingaben!$D$6="Ja",2*MAX(0,O10),MAX(0,O10))) -> 0 | K10: =IF(Eingaben!$B$14="","",IF(Eingaben!$D$6="Ja",2*MAX(0,Q10),MAX(0,Q10))) -> 0 | L10: =IF(Eingaben!$B$14="","",IF(Eingaben!$D$5>0,J10-K10,-I10*Eingaben!$D$9)) -> 1417.5188 | N10: =IF(Eingaben!$B$14="","",IF(Eingaben!$D$6="Ja",Eingaben!$F$6/2,Eingaben!$F$6)) -> 0 | O10: =IF(Eingaben!$B$14="","",IF(N10<=12348,0,IF(N10<=17799,(914.51*((N10-12348)/10000)+1400)*((N10-12348)/10000),IF(N10<=69878,(181.19*((N10-17799)/10000)+2397)*((N10-17799)/10000)+1025.38,IF(N10<=277825,0.42*N10-10637.32,0.45*N10-18971.07))))) -> 0 | P10: =IF(Eingaben!$B$14="","",IF(Eingaben!$D$6="Ja",MAX(0,Eingaben!$F$6+I10)/2,MAX(0,Eingaben!$F$6+I10))) -> 0 | Q10: =IF(Eingaben!$B$14="","",IF(P10<=12348,0,IF(P10<=17799,(914.51*((P10-12348)/10000)+1400)*((P10-12348)/10000),IF(P10<=69878,(181.19*((P10-17799)/10000)+2397)*((P10-17799)/10000)+1025.38,IF(P10<=277825,0.42*P10-10637.32,0.45*P10-18971.07))))) -> 0
A11: 1 | B11: =IF(Eingaben!$B$14="","",Cashflow!B11) -> Musterwohnung Berlin | C11: 7 | D11: =IF(Eingaben!$B$14="","",H10) -> 174592 | E11: =IF(Eingaben!$B$14="","",MIN(D11,MAX(0,IF(Eingaben!$S$14="Ja",D11*Eingaben!$T$14,Eingaben!$AD$14*Eingaben!$Q$14)))) -> 3968 | F11: =IF(Eingaben!$B$14="","",MIN(MAX(0,IF(AND(Eingaben!$U$14="Ja",7<=Eingaben!$W$14),Eingaben!$AD$14*Eingaben!$V$14,0)),MAX(0,D11-E11))) -> 0 | G11: =IF(Eingaben!$B$14="","",E11+F11) -> 3968 | H11: =IF(Eingaben!$B$14="","",D11-G11) -> 170624 | I11: =IF(Eingaben!$B$14="","",Cashflow!E11-Cashflow!G11-G11) -> -3206.247 | J11: =IF(Eingaben!$B$14="","",IF(Eingaben!$D$6="Ja",2*MAX(0,O11),MAX(0,O11))) -> 0 | K11: =IF(Eingaben!$B$14="","",IF(Eingaben!$D$6="Ja",2*MAX(0,Q11),MAX(0,Q11))) -> 0 | L11: =IF(Eingaben!$B$14="","",IF(Eingaben!$D$5>0,J11-K11,-I11*Eingaben!$D$9)) -> 1282.4988 | N11: =IF(Eingaben!$B$14="","",IF(Eingaben!$D$6="Ja",Eingaben!$F$6/2,Eingaben!$F$6)) -> 0 | O11: =IF(Eingaben!$B$14="","",IF(N11<=12348,0,IF(N11<=17799,(914.51*((N11-12348)/10000)+1400)*((N11-12348)/10000),IF(N11<=69878,(181.19*((N11-17799)/10000)+2397)*((N11-17799)/10000)+1025.38,IF(N11<=277825,0.42*N11-10637.32,0.45*N11-18971.07))))) -> 0 | P11: =IF(Eingaben!$B$14="","",IF(Eingaben!$D$6="Ja",MAX(0,Eingaben!$F$6+I11)/2,MAX(0,Eingaben!$F$6+I11))) -> 0 | Q11: =IF(Eingaben!$B$14="","",IF(P11<=12348,0,IF(P11<=17799,(914.51*((P11-12348)/10000)+1400)*((P11-12348)/10000),IF(P11<=69878,(181.19*((P11-17799)/10000)+2397)*((P11-17799)/10000)+1025.38,IF(P11<=277825,0.42*P11-10637.32,0.45*P11-18971.07))))) -> 0
A12: 1 | B12: =IF(Eingaben!$B$14="","",Cashflow!B12) -> Musterwohnung Berlin | C12: 8 | D12: =IF(Eingaben!$B$14="","",H11) -> 170624 | E12: =IF(Eingaben!$B$14="","",MIN(D12,MAX(0,IF(Eingaben!$S$14="Ja",D12*Eingaben!$T$14,Eingaben!$AD$14*Eingaben!$Q$14)))) -> 3968 | F12: =IF(Eingaben!$B$14="","",MIN(MAX(0,IF(AND(Eingaben!$U$14="Ja",8<=Eingaben!$W$14),Eingaben!$AD$14*Eingaben!$V$14,0)),MAX(0,D12-E12))) -> 0 | G12: =IF(Eingaben!$B$14="","",E12+F12) -> 3968 | H12: =IF(Eingaben!$B$14="","",D12-G12) -> 166656 | I12: =IF(Eingaben!$B$14="","",Cashflow!E12-Cashflow!G12-G12) -> -2858.8999 | J12: =IF(Eingaben!$B$14="","",IF(Eingaben!$D$6="Ja",2*MAX(0,O12),MAX(0,O12))) -> 0 | K12: =IF(Eingaben!$B$14="","",IF(Eingaben!$D$6="Ja",2*MAX(0,Q12),MAX(0,Q12))) -> 0 | L12: =IF(Eingaben!$B$14="","",IF(Eingaben!$D$5>0,J12-K12,-I12*Eingaben!$D$9)) -> 1143.5599 | N12: =IF(Eingaben!$B$14="","",IF(Eingaben!$D$6="Ja",Eingaben!$F$6/2,Eingaben!$F$6)) -> 0 | O12: =IF(Eingaben!$B$14="","",IF(N12<=12348,0,IF(N12<=17799,(914.51*((N12-12348)/10000)+1400)*((N12-12348)/10000),IF(N12<=69878,(181.19*((N12-17799)/10000)+2397)*((N12-17799)/10000)+1025.38,IF(N12<=277825,0.42*N12-10637.32,0.45*N12-18971.07))))) -> 0 | P12: =IF(Eingaben!$B$14="","",IF(Eingaben!$D$6="Ja",MAX(0,Eingaben!$F$6+I12)/2,MAX(0,Eingaben!$F$6+I12))) -> 0 | Q12: =IF(Eingaben!$B$14="","",IF(P12<=12348,0,IF(P12<=17799,(914.51*((P12-12348)/10000)+1400)*((P12-12348)/10000),IF(P12<=69878,(181.19*((P12-17799)/10000)+2397)*((P12-17799)/10000)+1025.38,IF(P12<=277825,0.42*P12-10637.32,0.45*P12-18971.07))))) -> 0
A13: 1 | B13: =IF(Eingaben!$B$14="","",Cashflow!B13) -> Musterwohnung Berlin | C13: 9 | D13: =IF(Eingaben!$B$14="","",H12) -> 166656 | E13: =IF(Eingaben!$B$14="","",MIN(D13,MAX(0,IF(Eingaben!$S$14="Ja",D13*Eingaben!$T$14,Eingaben!$AD$14*Eingaben!$Q$14)))) -> 3968 | F13: =IF(Eingaben!$B$14="","",MIN(MAX(0,IF(AND(Eingaben!$U$14="Ja",9<=Eingaben!$W$14),Eingaben!$AD$14*Eingaben!$V$14,0)),MAX(0,D13-E13))) -> 0 | G13: =IF(Eingaben!$B$14="","",E13+F13) -> 3968 | H13: =IF(Eingaben!$B$14="","",D13-G13) -> 162688 | I13: =IF(Eingaben!$B$14="","",Cashflow!E13-Cashflow!G13-G13) -> -2501.429 | J13: =IF(Eingaben!$B$14="","",IF(Eingaben!$D$6="Ja",2*MAX(0,O13),MAX(0,O13))) -> 0 | K13: =IF(Eingaben!$B$14="","",IF(Eingaben!$D$6="Ja",2*MAX(0,Q13),MAX(0,Q13))) -> 0 | L13: =IF(Eingaben!$B$14="","",IF(Eingaben!$D$5>0,J13-K13,-I13*Eingaben!$D$9)) -> 1000.5716 | N13: =IF(Eingaben!$B$14="","",IF(Eingaben!$D$6="Ja",Eingaben!$F$6/2,Eingaben!$F$6)) -> 0 | O13: =IF(Eingaben!$B$14="","",IF(N13<=12348,0,IF(N13<=17799,(914.51*((N13-12348)/10000)+1400)*((N13-12348)/10000),IF(N13<=69878,(181.19*((N13-17799)/10000)+2397)*((N13-17799)/10000)+1025.38,IF(N13<=277825,0.42*N13-10637.32,0.45*N13-18971.07))))) -> 0 | P13: =IF(Eingaben!$B$14="","",IF(Eingaben!$D$6="Ja",MAX(0,Eingaben!$F$6+I13)/2,MAX(0,Eingaben!$F$6+I13))) -> 0 | Q13: =IF(Eingaben!$B$14="","",IF(P13<=12348,0,IF(P13<=17799,(914.51*((P13-12348)/10000)+1400)*((P13-12348)/10000),IF(P13<=69878,(181.19*((P13-17799)/10000)+2397)*((P13-17799)/10000)+1025.38,IF(P13<=277825,0.42*P13-10637.32,0.45*P13-18971.07))))) -> 0
A14: 1 | B14: =IF(Eingaben!$B$14="","",Cashflow!B14) -> Musterwohnung Berlin | C14: 10 | D14: =IF(Eingaben!$B$14="","",H13) -> 162688 | E14: =IF(Eingaben!$B$14="","",MIN(D14,MAX(0,IF(Eingaben!$S$14="Ja",D14*Eingaben!$T$14,Eingaben!$AD$14*Eingaben!$Q$14)))) -> 3968 | F14: =IF(Eingaben!$B$14="","",MIN(MAX(0,IF(AND(Eingaben!$U$14="Ja",10<=Eingaben!$W$14),Eingaben!$AD$14*Eingaben!$V$14,0)),MAX(0,D14-E14))) -> 0 | G14: =IF(Eingaben!$B$14="","",E14+F14) -> 3968 | H14: =IF(Eingaben!$B$14="","",D14-G14) -> 158720 | I14: =IF(Eingaben!$B$14="","",Cashflow!E14-Cashflow!G14-G14) -> -2133.4959 | J14: =IF(Eingaben!$B$14="","",IF(Eingaben!$D$6="Ja",2*MAX(0,O14),MAX(0,O14))) -> 0 | K14: =IF(Eingaben!$B$14="","",IF(Eingaben!$D$6="Ja",2*MAX(0,Q14),MAX(0,Q14))) -> 0 | L14: =IF(Eingaben!$B$14="","",IF(Eingaben!$D$5>0,J14-K14,-I14*Eingaben!$D$9)) -> 853.39838 | N14: =IF(Eingaben!$B$14="","",IF(Eingaben!$D$6="Ja",Eingaben!$F$6/2,Eingaben!$F$6)) -> 0 | O14: =IF(Eingaben!$B$14="","",IF(N14<=12348,0,IF(N14<=17799,(914.51*((N14-12348)/10000)+1400)*((N14-12348)/10000),IF(N14<=69878,(181.19*((N14-17799)/10000)+2397)*((N14-17799)/10000)+1025.38,IF(N14<=277825,0.42*N14-10637.32,0.45*N14-18971.07))))) -> 0 | P14: =IF(Eingaben!$B$14="","",IF(Eingaben!$D$6="Ja",MAX(0,Eingaben!$F$6+I14)/2,MAX(0,Eingaben!$F$6+I14))) -> 0 | Q14: =IF(Eingaben!$B$14="","",IF(P14<=12348,0,IF(P14<=17799,(914.51*((P14-12348)/10000)+1400)*((P14-12348)/10000),IF(P14<=69878,(181.19*((P14-17799)/10000)+2397)*((P14-17799)/10000)+1025.38,IF(P14<=277825,0.42*P14-10637.32,0.45*P14-18971.07))))) -> 0
A15: 2 | B15: =IF(Eingaben!$B$15="","",Cashflow!B15) | C15: 1 | D15: =IF(Eingaben!$B$15="","",Eingaben!$AD$15) | E15: =IF(Eingaben!$B$15="","",MIN(D15,MAX(0,IF(Eingaben!$S$15="Ja",D15*Eingaben!$T$15,Eingaben!$AD$15*Eingaben!$Q$15)))) | F15: =IF(Eingaben!$B$15="","",MIN(MAX(0,IF(AND(Eingaben!$U$15="Ja",1<=Eingaben!$W$15),Eingaben!$AD$15*Eingaben!$V$15,0)),MAX(0,D15-E15))) | G15: =IF(Eingaben!$B$15="","",E15+F15) | H15: =IF(Eingaben!$B$15="","",D15-G15) | I15: =IF(Eingaben!$B$15="","",Cashflow!E15-Cashflow!G15-G15) | J15: =IF(Eingaben!$B$15="","",IF(Eingaben!$D$6="Ja",2*MAX(0,O15),MAX(0,O15))) | K15: =IF(Eingaben!$B$15="","",IF(Eingaben!$D$6="Ja",2*MAX(0,Q15),MAX(0,Q15))) | L15: =IF(Eingaben!$B$15="","",IF(Eingaben!$D$5>0,J15-K15,-I15*Eingaben!$D$9)) | N15: =IF(Eingaben!$B$15="","",IF(Eingaben!$D$6="Ja",Eingaben!$F$6/2,Eingaben!$F$6)) | O15: =IF(Eingaben!$B$15="","",IF(N15<=12348,0,IF(N15<=17799,(914.51*((N15-12348)/10000)+1400)*((N15-12348)/10000),IF(N15<=69878,(181.19*((N15-17799)/10000)+2397)*((N15-17799)/10000)+1025.38,IF(N15<=277825,0.42*N15-10637.32,0.45*N15-18971.07))))) | P15: =IF(Eingaben!$B$15="","",IF(Eingaben!$D$6="Ja",MAX(0,Eingaben!$F$6+I15)/2,MAX(0,Eingaben!$F$6+I15))) | Q15: =IF(Eingaben!$B$15="","",IF(P15<=12348,0,IF(P15<=17799,(914.51*((P15-12348)/10000)+1400)*((P15-12348)/10000),IF(P15<=69878,(181.19*((P15-17799)/10000)+2397)*((P15-17799)/10000)+1025.38,IF(P15<=277825,0.42*P15-10637.32,0.45*P15-18971.07)))))
A16: 2 | B16: =IF(Eingaben!$B$15="","",Cashflow!B16) | C16: 2 | D16: =IF(Eingaben!$B$15="","",H15) | E16: =IF(Eingaben!$B$15="","",MIN(D16,MAX(0,IF(Eingaben!$S$15="Ja",D16*Eingaben!$T$15,Eingaben!$AD$15*Eingaben!$Q$15)))) | F16: =IF(Eingaben!$B$15="","",MIN(MAX(0,IF(AND(Eingaben!$U$15="Ja",2<=Eingaben!$W$15),Eingaben!$AD$15*Eingaben!$V$15,0)),MAX(0,D16-E16))) | G16: =IF(Eingaben!$B$15="","",E16+F16) | H16: =IF(Eingaben!$B$15="","",D16-G16) | I16: =IF(Eingaben!$B$15="","",Cashflow!E16-Cashflow!G16-G16) | J16: =IF(Eingaben!$B$15="","",IF(Eingaben!$D$6="Ja",2*MAX(0,O16),MAX(0,O16))) | K16: =IF(Eingaben!$B$15="","",IF(Eingaben!$D$6="Ja",2*MAX(0,Q16),MAX(0,Q16))) | L16: =IF(Eingaben!$B$15="","",IF(Eingaben!$D$5>0,J16-K16,-I16*Eingaben!$D$9)) | N16: =IF(Eingaben!$B$15="","",IF(Eingaben!$D$6="Ja",Eingaben!$F$6/2,Eingaben!$F$6)) | O16: =IF(Eingaben!$B$15="","",IF(N16<=12348,0,IF(N16<=17799,(914.51*((N16-12348)/10000)+1400)*((N16-12348)/10000),IF(N16<=69878,(181.19*((N16-17799)/10000)+2397)*((N16-17799)/10000)+1025.38,IF(N16<=277825,0.42*N16-10637.32,0.45*N16-18971.07))))) | P16: =IF(Eingaben!$B$15="","",IF(Eingaben!$D$6="Ja",MAX(0,Eingaben!$F$6+I16)/2,MAX(0,Eingaben!$F$6+I16))) | Q16: =IF(Eingaben!$B$15="","",IF(P16<=12348,0,IF(P16<=17799,(914.51*((P16-12348)/10000)+1400)*((P16-12348)/10000),IF(P16<=69878,(181.19*((P16-17799)/10000)+2397)*((P16-17799)/10000)+1025.38,IF(P16<=277825,0.42*P16-10637.32,0.45*P16-18971.07)))))
A17: 2 | B17: =IF(Eingaben!$B$15="","",Cashflow!B17) | C17: 3 | D17: =IF(Eingaben!$B$15="","",H16) | E17: =IF(Eingaben!$B$15="","",MIN(D17,MAX(0,IF(Eingaben!$S$15="Ja",D17*Eingaben!$T$15,Eingaben!$AD$15*Eingaben!$Q$15)))) | F17: =IF(Eingaben!$B$15="","",MIN(MAX(0,IF(AND(Eingaben!$U$15="Ja",3<=Eingaben!$W$15),Eingaben!$AD$15*Eingaben!$V$15,0)),MAX(0,D17-E17))) | G17: =IF(Eingaben!$B$15="","",E17+F17) | H17: =IF(Eingaben!$B$15="","",D17-G17) | I17: =IF(Eingaben!$B$15="","",Cashflow!E17-Cashflow!G17-G17) | J17: =IF(Eingaben!$B$15="","",IF(Eingaben!$D$6="Ja",2*MAX(0,O17),MAX(0,O17))) | K17: =IF(Eingaben!$B$15="","",IF(Eingaben!$D$6="Ja",2*MAX(0,Q17),MAX(0,Q17))) | L17: =IF(Eingaben!$B$15="","",IF(Eingaben!$D$5>0,J17-K17,-I17*Eingaben!$D$9)) | N17: =IF(Eingaben!$B$15="","",IF(Eingaben!$D$6="Ja",Eingaben!$F$6/2,Eingaben!$F$6)) | O17: =IF(Eingaben!$B$15="","",IF(N17<=12348,0,IF(N17<=17799,(914.51*((N17-12348)/10000)+1400)*((N17-12348)/10000),IF(N17<=69878,(181.19*((N17-17799)/10000)+2397)*((N17-17799)/10000)+1025.38,IF(N17<=277825,0.42*N17-10637.32,0.45*N17-18971.07))))) | P17: =IF(Eingaben!$B$15="","",IF(Eingaben!$D$6="Ja",MAX(0,Eingaben!$F$6+I17)/2,MAX(0,Eingaben!$F$6+I17))) | Q17: =IF(Eingaben!$B$15="","",IF(P17<=12348,0,IF(P17<=17799,(914.51*((P17-12348)/10000)+1400)*((P17-12348)/10000),IF(P17<=69878,(181.19*((P17-17799)/10000)+2397)*((P17-17799)/10000)+1025.38,IF(P17<=277825,0.42*P17-10637.32,0.45*P17-18971.07)))))
A18: 2 | B18: =IF(Eingaben!$B$15="","",Cashflow!B18) | C18: 4 | D18: =IF(Eingaben!$B$15="","",H17) | E18: =IF(Eingaben!$B$15="","",MIN(D18,MAX(0,IF(Eingaben!$S$15="Ja",D18*Eingaben!$T$15,Eingaben!$AD$15*Eingaben!$Q$15)))) | F18: =IF(Eingaben!$B$15="","",MIN(MAX(0,IF(AND(Eingaben!$U$15="Ja",4<=Eingaben!$W$15),Eingaben!$AD$15*Eingaben!$V$15,0)),MAX(0,D18-E18))) | G18: =IF(Eingaben!$B$15="","",E18+F18) | H18: =IF(Eingaben!$B$15="","",D18-G18) | I18: =IF(Eingaben!$B$15="","",Cashflow!E18-Cashflow!G18-G18) | J18: =IF(Eingaben!$B$15="","",IF(Eingaben!$D$6="Ja",2*MAX(0,O18),MAX(0,O18))) | K18: =IF(Eingaben!$B$15="","",IF(Eingaben!$D$6="Ja",2*MAX(0,Q18),MAX(0,Q18))) | L18: =IF(Eingaben!$B$15="","",IF(Eingaben!$D$5>0,J18-K18,-I18*Eingaben!$D$9)) | N18: =IF(Eingaben!$B$15="","",IF(Eingaben!$D$6="Ja",Eingaben!$F$6/2,Eingaben!$F$6)) | O18: =IF(Eingaben!$B$15="","",IF(N18<=12348,0,IF(N18<=17799,(914.51*((N18-12348)/10000)+1400)*((N18-12348)/10000),IF(N18<=69878,(181.19*((N18-17799)/10000)+2397)*((N18-17799)/10000)+1025.38,IF(N18<=277825,0.42*N18-10637.32,0.45*N18-18971.07))))) | P18: =IF(Eingaben!$B$15="","",IF(Eingaben!$D$6="Ja",MAX(0,Eingaben!$F$6+I18)/2,MAX(0,Eingaben!$F$6+I18))) | Q18: =IF(Eingaben!$B$15="","",IF(P18<=12348,0,IF(P18<=17799,(914.51*((P18-12348)/10000)+1400)*((P18-12348)/10000),IF(P18<=69878,(181.19*((P18-17799)/10000)+2397)*((P18-17799)/10000)+1025.38,IF(P18<=277825,0.42*P18-10637.32,0.45*P18-18971.07)))))
A19: 2 | B19: =IF(Eingaben!$B$15="","",Cashflow!B19) | C19: 5 | D19: =IF(Eingaben!$B$15="","",H18) | E19: =IF(Eingaben!$B$15="","",MIN(D19,MAX(0,IF(Eingaben!$S$15="Ja",D19*Eingaben!$T$15,Eingaben!$AD$15*Eingaben!$Q$15)))) | F19: =IF(Eingaben!$B$15="","",MIN(MAX(0,IF(AND(Eingaben!$U$15="Ja",5<=Eingaben!$W$15),Eingaben!$AD$15*Eingaben!$V$15,0)),MAX(0,D19-E19))) | G19: =IF(Eingaben!$B$15="","",E19+F19) | H19: =IF(Eingaben!$B$15="","",D19-G19) | I19: =IF(Eingaben!$B$15="","",Cashflow!E19-Cashflow!G19-G19) | J19: =IF(Eingaben!$B$15="","",IF(Eingaben!$D$6="Ja",2*MAX(0,O19),MAX(0,O19))) | K19: =IF(Eingaben!$B$15="","",IF(Eingaben!$D$6="Ja",2*MAX(0,Q19),MAX(0,Q19))) | L19: =IF(Eingaben!$B$15="","",IF(Eingaben!$D$5>0,J19-K19,-I19*Eingaben!$D$9)) | N19: =IF(Eingaben!$B$15="","",IF(Eingaben!$D$6="Ja",Eingaben!$F$6/2,Eingaben!$F$6)) | O19: =IF(Eingaben!$B$15="","",IF(N19<=12348,0,IF(N19<=17799,(914.51*((N19-12348)/10000)+1400)*((N19-12348)/10000),IF(N19<=69878,(181.19*((N19-17799)/10000)+2397)*((N19-17799)/10000)+1025.38,IF(N19<=277825,0.42*N19-10637.32,0.45*N19-18971.07))))) | P19: =IF(Eingaben!$B$15="","",IF(Eingaben!$D$6="Ja",MAX(0,Eingaben!$F$6+I19)/2,MAX(0,Eingaben!$F$6+I19))) | Q19: =IF(Eingaben!$B$15="","",IF(P19<=12348,0,IF(P19<=17799,(914.51*((P19-12348)/10000)+1400)*((P19-12348)/10000),IF(P19<=69878,(181.19*((P19-17799)/10000)+2397)*((P19-17799)/10000)+1025.38,IF(P19<=277825,0.42*P19-10637.32,0.45*P19-18971.07)))))
A20: 2 | B20: =IF(Eingaben!$B$15="","",Cashflow!B20) | C20: 6 | D20: =IF(Eingaben!$B$15="","",H19) | E20: =IF(Eingaben!$B$15="","",MIN(D20,MAX(0,IF(Eingaben!$S$15="Ja",D20*Eingaben!$T$15,Eingaben!$AD$15*Eingaben!$Q$15)))) | F20: =IF(Eingaben!$B$15="","",MIN(MAX(0,IF(AND(Eingaben!$U$15="Ja",6<=Eingaben!$W$15),Eingaben!$AD$15*Eingaben!$V$15,0)),MAX(0,D20-E20))) | G20: =IF(Eingaben!$B$15="","",E20+F20) | H20: =IF(Eingaben!$B$15="","",D20-G20) | I20: =IF(Eingaben!$B$15="","",Cashflow!E20-Cashflow!G20-G20) | J20: =IF(Eingaben!$B$15="","",IF(Eingaben!$D$6="Ja",2*MAX(0,O20),MAX(0,O20))) | K20: =IF(Eingaben!$B$15="","",IF(Eingaben!$D$6="Ja",2*MAX(0,Q20),MAX(0,Q20))) | L20: =IF(Eingaben!$B$15="","",IF(Eingaben!$D$5>0,J20-K20,-I20*Eingaben!$D$9)) | N20: =IF(Eingaben!$B$15="","",IF(Eingaben!$D$6="Ja",Eingaben!$F$6/2,Eingaben!$F$6)) | O20: =IF(Eingaben!$B$15="","",IF(N20<=12348,0,IF(N20<=17799,(914.51*((N20-12348)/10000)+1400)*((N20-12348)/10000),IF(N20<=69878,(181.19*((N20-17799)/10000)+2397)*((N20-17799)/10000)+1025.38,IF(N20<=277825,0.42*N20-10637.32,0.45*N20-18971.07))))) | P20: =IF(Eingaben!$B$15="","",IF(Eingaben!$D$6="Ja",MAX(0,Eingaben!$F$6+I20)/2,MAX(0,Eingaben!$F$6+I20))) | Q20: =IF(Eingaben!$B$15="","",IF(P20<=12348,0,IF(P20<=17799,(914.51*((P20-12348)/10000)+1400)*((P20-12348)/10000),IF(P20<=69878,(181.19*((P20-17799)/10000)+2397)*((P20-17799)/10000)+1025.38,IF(P20<=277825,0.42*P20-10637.32,0.45*P20-18971.07)))))
A21: 2 | B21: =IF(Eingaben!$B$15="","",Cashflow!B21) | C21: 7 | D21: =IF(Eingaben!$B$15="","",H20) | E21: =IF(Eingaben!$B$15="","",MIN(D21,MAX(0,IF(Eingaben!$S$15="Ja",D21*Eingaben!$T$15,Eingaben!$AD$15*Eingaben!$Q$15)))) | F21: =IF(Eingaben!$B$15="","",MIN(MAX(0,IF(AND(Eingaben!$U$15="Ja",7<=Eingaben!$W$15),Eingaben!$AD$15*Eingaben!$V$15,0)),MAX(0,D21-E21))) | G21: =IF(Eingaben!$B$15="","",E21+F21) | H21: =IF(Eingaben!$B$15="","",D21-G21) | I21: =IF(Eingaben!$B$15="","",Cashflow!E21-Cashflow!G21-G21) | J21: =IF(Eingaben!$B$15="","",IF(Eingaben!$D$6="Ja",2*MAX(0,O21),MAX(0,O21))) | K21: =IF(Eingaben!$B$15="","",IF(Eingaben!$D$6="Ja",2*MAX(0,Q21),MAX(0,Q21))) | L21: =IF(Eingaben!$B$15="","",IF(Eingaben!$D$5>0,J21-K21,-I21*Eingaben!$D$9)) | N21: =IF(Eingaben!$B$15="","",IF(Eingaben!$D$6="Ja",Eingaben!$F$6/2,Eingaben!$F$6)) | O21: =IF(Eingaben!$B$15="","",IF(N21<=12348,0,IF(N21<=17799,(914.51*((N21-12348)/10000)+1400)*((N21-12348)/10000),IF(N21<=69878,(181.19*((N21-17799)/10000)+2397)*((N21-17799)/10000)+1025.38,IF(N21<=277825,0.42*N21-10637.32,0.45*N21-18971.07))))) | P21: =IF(Eingaben!$B$15="","",IF(Eingaben!$D$6="Ja",MAX(0,Eingaben!$F$6+I21)/2,MAX(0,Eingaben!$F$6+I21))) | Q21: =IF(Eingaben!$B$15="","",IF(P21<=12348,0,IF(P21<=17799,(914.51*((P21-12348)/10000)+1400)*((P21-12348)/10000),IF(P21<=69878,(181.19*((P21-17799)/10000)+2397)*((P21-17799)/10000)+1025.38,IF(P21<=277825,0.42*P21-10637.32,0.45*P21-18971.07)))))
A22: 2 | B22: =IF(Eingaben!$B$15="","",Cashflow!B22) | C22: 8 | D22: =IF(Eingaben!$B$15="","",H21) | E22: =IF(Eingaben!$B$15="","",MIN(D22,MAX(0,IF(Eingaben!$S$15="Ja",D22*Eingaben!$T$15,Eingaben!$AD$15*Eingaben!$Q$15)))) | F22: =IF(Eingaben!$B$15="","",MIN(MAX(0,IF(AND(Eingaben!$U$15="Ja",8<=Eingaben!$W$15),Eingaben!$AD$15*Eingaben!$V$15,0)),MAX(0,D22-E22))) | G22: =IF(Eingaben!$B$15="","",E22+F22) | H22: =IF(Eingaben!$B$15="","",D22-G22) | I22: =IF(Eingaben!$B$15="","",Cashflow!E22-Cashflow!G22-G22) | J22: =IF(Eingaben!$B$15="","",IF(Eingaben!$D$6="Ja",2*MAX(0,O22),MAX(0,O22))) | K22: =IF(Eingaben!$B$15="","",IF(Eingaben!$D$6="Ja",2*MAX(0,Q22),MAX(0,Q22))) | L22: =IF(Eingaben!$B$15="","",IF(Eingaben!$D$5>0,J22-K22,-I22*Eingaben!$D$9)) | N22: =IF(Eingaben!$B$15="","",IF(Eingaben!$D$6="Ja",Eingaben!$F$6/2,Eingaben!$F$6)) | O22: =IF(Eingaben!$B$15="","",IF(N22<=12348,0,IF(N22<=17799,(914.51*((N22-12348)/10000)+1400)*((N22-12348)/10000),IF(N22<=69878,(181.19*((N22-17799)/10000)+2397)*((N22-17799)/10000)+1025.38,IF(N22<=277825,0.42*N22-10637.32,0.45*N22-18971.07))))) | P22: =IF(Eingaben!$B$15="","",IF(Eingaben!$D$6="Ja",MAX(0,Eingaben!$F$6+I22)/2,MAX(0,Eingaben!$F$6+I22))) | Q22: =IF(Eingaben!$B$15="","",IF(P22<=12348,0,IF(P22<=17799,(914.51*((P22-12348)/10000)+1400)*((P22-12348)/10000),IF(P22<=69878,(181.19*((P22-17799)/10000)+2397)*((P22-17799)/10000)+1025.38,IF(P22<=277825,0.42*P22-10637.32,0.45*P22-18971.07)))))
A23: 2 | B23: =IF(Eingaben!$B$15="","",Cashflow!B23) | C23: 9 | D23: =IF(Eingaben!$B$15="","",H22) | E23: =IF(Eingaben!$B$15="","",MIN(D23,MAX(0,IF(Eingaben!$S$15="Ja",D23*Eingaben!$T$15,Eingaben!$AD$15*Eingaben!$Q$15)))) | F23: =IF(Eingaben!$B$15="","",MIN(MAX(0,IF(AND(Eingaben!$U$15="Ja",9<=Eingaben!$W$15),Eingaben!$AD$15*Eingaben!$V$15,0)),MAX(0,D23-E23))) | G23: =IF(Eingaben!$B$15="","",E23+F23) | H23: =IF(Eingaben!$B$15="","",D23-G23) | I23: =IF(Eingaben!$B$15="","",Cashflow!E23-Cashflow!G23-G23) | J23: =IF(Eingaben!$B$15="","",IF(Eingaben!$D$6="Ja",2*MAX(0,O23),MAX(0,O23))) | K23: =IF(Eingaben!$B$15="","",IF(Eingaben!$D$6="Ja",2*MAX(0,Q23),MAX(0,Q23))) | L23: =IF(Eingaben!$B$15="","",IF(Eingaben!$D$5>0,J23-K23,-I23*Eingaben!$D$9)) | N23: =IF(Eingaben!$B$15="","",IF(Eingaben!$D$6="Ja",Eingaben!$F$6/2,Eingaben!$F$6)) | O23: =IF(Eingaben!$B$15="","",IF(N23<=12348,0,IF(N23<=17799,(914.51*((N23-12348)/10000)+1400)*((N23-12348)/10000),IF(N23<=69878,(181.19*((N23-17799)/10000)+2397)*((N23-17799)/10000)+1025.38,IF(N23<=277825,0.42*N23-10637.32,0.45*N23-18971.07))))) | P23: =IF(Eingaben!$B$15="","",IF(Eingaben!$D$6="Ja",MAX(0,Eingaben!$F$6+I23)/2,MAX(0,Eingaben!$F$6+I23))) | Q23: =IF(Eingaben!$B$15="","",IF(P23<=12348,0,IF(P23<=17799,(914.51*((P23-12348)/10000)+1400)*((P23-12348)/10000),IF(P23<=69878,(181.19*((P23-17799)/10000)+2397)*((P23-17799)/10000)+1025.38,IF(P23<=277825,0.42*P23-10637.32,0.45*P23-18971.07)))))
A24: 2 | B24: =IF(Eingaben!$B$15="","",Cashflow!B24) | C24: 10 | D24: =IF(Eingaben!$B$15="","",H23) | E24: =IF(Eingaben!$B$15="","",MIN(D24,MAX(0,IF(Eingaben!$S$15="Ja",D24*Eingaben!$T$15,Eingaben!$AD$15*Eingaben!$Q$15)))) | F24: =IF(Eingaben!$B$15="","",MIN(MAX(0,IF(AND(Eingaben!$U$15="Ja",10<=Eingaben!$W$15),Eingaben!$AD$15*Eingaben!$V$15,0)),MAX(0,D24-E24))) | G24: =IF(Eingaben!$B$15="","",E24+F24) | H24: =IF(Eingaben!$B$15="","",D24-G24) | I24: =IF(Eingaben!$B$15="","",Cashflow!E24-Cashflow!G24-G24) | J24: =IF(Eingaben!$B$15="","",IF(Eingaben!$D$6="Ja",2*MAX(0,O24),MAX(0,O24))) | K24: =IF(Eingaben!$B$15="","",IF(Eingaben!$D$6="Ja",2*MAX(0,Q24),MAX(0,Q24))) | L24: =IF(Eingaben!$B$15="","",IF(Eingaben!$D$5>0,J24-K24,-I24*Eingaben!$D$9)) | N24: =IF(Eingaben!$B$15="","",IF(Eingaben!$D$6="Ja",Eingaben!$F$6/2,Eingaben!$F$6)) | O24: =IF(Eingaben!$B$15="","",IF(N24<=12348,0,IF(N24<=17799,(914.51*((N24-12348)/10000)+1400)*((N24-12348)/10000),IF(N24<=69878,(181.19*((N24-17799)/10000)+2397)*((N24-17799)/10000)+1025.38,IF(N24<=277825,0.42*N24-10637.32,0.45*N24-18971.07))))) | P24: =IF(Eingaben!$B$15="","",IF(Eingaben!$D$6="Ja",MAX(0,Eingaben!$F$6+I24)/2,MAX(0,Eingaben!$F$6+I24))) | Q24: =IF(Eingaben!$B$15="","",IF(P24<=12348,0,IF(P24<=17799,(914.51*((P24-12348)/10000)+1400)*((P24-12348)/10000),IF(P24<=69878,(181.19*((P24-17799)/10000)+2397)*((P24-17799)/10000)+1025.38,IF(P24<=277825,0.42*P24-10637.32,0.45*P24-18971.07)))))
A25: 3 | B25: =IF(Eingaben!$B$16="","",Cashflow!B25) | C25: 1 | D25: =IF(Eingaben!$B$16="","",Eingaben!$AD$16) | E25: =IF(Eingaben!$B$16="","",MIN(D25,MAX(0,IF(Eingaben!$S$16="Ja",D25*Eingaben!$T$16,Eingaben!$AD$16*Eingaben!$Q$16)))) | F25: =IF(Eingaben!$B$16="","",MIN(MAX(0,IF(AND(Eingaben!$U$16="Ja",1<=Eingaben!$W$16),Eingaben!$AD$16*Eingaben!$V$16,0)),MAX(0,D25-E25))) | G25: =IF(Eingaben!$B$16="","",E25+F25) | H25: =IF(Eingaben!$B$16="","",D25-G25) | I25: =IF(Eingaben!$B$16="","",Cashflow!E25-Cashflow!G25-G25) | J25: =IF(Eingaben!$B$16="","",IF(Eingaben!$D$6="Ja",2*MAX(0,O25),MAX(0,O25))) | K25: =IF(Eingaben!$B$16="","",IF(Eingaben!$D$6="Ja",2*MAX(0,Q25),MAX(0,Q25))) | L25: =IF(Eingaben!$B$16="","",IF(Eingaben!$D$5>0,J25-K25,-I25*Eingaben!$D$9)) | N25: =IF(Eingaben!$B$16="","",IF(Eingaben!$D$6="Ja",Eingaben!$F$6/2,Eingaben!$F$6)) | O25: =IF(Eingaben!$B$16="","",IF(N25<=12348,0,IF(N25<=17799,(914.51*((N25-12348)/10000)+1400)*((N25-12348)/10000),IF(N25<=69878,(181.19*((N25-17799)/10000)+2397)*((N25-17799)/10000)+1025.38,IF(N25<=277825,0.42*N25-10637.32,0.45*N25-18971.07))))) | P25: =IF(Eingaben!$B$16="","",IF(Eingaben!$D$6="Ja",MAX(0,Eingaben!$F$6+I25)/2,MAX(0,Eingaben!$F$6+I25))) | Q25: =IF(Eingaben!$B$16="","",IF(P25<=12348,0,IF(P25<=17799,(914.51*((P25-12348)/10000)+1400)*((P25-12348)/10000),IF(P25<=69878,(181.19*((P25-17799)/10000)+2397)*((P25-17799)/10000)+1025.38,IF(P25<=277825,0.42*P25-10637.32,0.45*P25-18971.07)))))
A26: 3 | B26: =IF(Eingaben!$B$16="","",Cashflow!B26) | C26: 2 | D26: =IF(Eingaben!$B$16="","",H25) | E26: =IF(Eingaben!$B$16="","",MIN(D26,MAX(0,IF(Eingaben!$S$16="Ja",D26*Eingaben!$T$16,Eingaben!$AD$16*Eingaben!$Q$16)))) | F26: =IF(Eingaben!$B$16="","",MIN(MAX(0,IF(AND(Eingaben!$U$16="Ja",2<=Eingaben!$W$16),Eingaben!$AD$16*Eingaben!$V$16,0)),MAX(0,D26-E26))) | G26: =IF(Eingaben!$B$16="","",E26+F26) | H26: =IF(Eingaben!$B$16="","",D26-G26) | I26: =IF(Eingaben!$B$16="","",Cashflow!E26-Cashflow!G26-G26) | J26: =IF(Eingaben!$B$16="","",IF(Eingaben!$D$6="Ja",2*MAX(0,O26),MAX(0,O26))) | K26: =IF(Eingaben!$B$16="","",IF(Eingaben!$D$6="Ja",2*MAX(0,Q26),MAX(0,Q26))) | L26: =IF(Eingaben!$B$16="","",IF(Eingaben!$D$5>0,J26-K26,-I26*Eingaben!$D$9)) | N26: =IF(Eingaben!$B$16="","",IF(Eingaben!$D$6="Ja",Eingaben!$F$6/2,Eingaben!$F$6)) | O26: =IF(Eingaben!$B$16="","",IF(N26<=12348,0,IF(N26<=17799,(914.51*((N26-12348)/10000)+1400)*((N26-12348)/10000),IF(N26<=69878,(181.19*((N26-17799)/10000)+2397)*((N26-17799)/10000)+1025.38,IF(N26<=277825,0.42*N26-10637.32,0.45*N26-18971.07))))) | P26: =IF(Eingaben!$B$16="","",IF(Eingaben!$D$6="Ja",MAX(0,Eingaben!$F$6+I26)/2,MAX(0,Eingaben!$F$6+I26))) | Q26: =IF(Eingaben!$B$16="","",IF(P26<=12348,0,IF(P26<=17799,(914.51*((P26-12348)/10000)+1400)*((P26-12348)/10000),IF(P26<=69878,(181.19*((P26-17799)/10000)+2397)*((P26-17799)/10000)+1025.38,IF(P26<=277825,0.42*P26-10637.32,0.45*P26-18971.07)))))
A27: 3 | B27: =IF(Eingaben!$B$16="","",Cashflow!B27) | C27: 3 | D27: =IF(Eingaben!$B$16="","",H26) | E27: =IF(Eingaben!$B$16="","",MIN(D27,MAX(0,IF(Eingaben!$S$16="Ja",D27*Eingaben!$T$16,Eingaben!$AD$16*Eingaben!$Q$16)))) | F27: =IF(Eingaben!$B$16="","",MIN(MAX(0,IF(AND(Eingaben!$U$16="Ja",3<=Eingaben!$W$16),Eingaben!$AD$16*Eingaben!$V$16,0)),MAX(0,D27-E27))) | G27: =IF(Eingaben!$B$16="","",E27+F27) | H27: =IF(Eingaben!$B$16="","",D27-G27) | I27: =IF(Eingaben!$B$16="","",Cashflow!E27-Cashflow!G27-G27) | J27: =IF(Eingaben!$B$16="","",IF(Eingaben!$D$6="Ja",2*MAX(0,O27),MAX(0,O27))) | K27: =IF(Eingaben!$B$16="","",IF(Eingaben!$D$6="Ja",2*MAX(0,Q27),MAX(0,Q27))) | L27: =IF(Eingaben!$B$16="","",IF(Eingaben!$D$5>0,J27-K27,-I27*Eingaben!$D$9)) | N27: =IF(Eingaben!$B$16="","",IF(Eingaben!$D$6="Ja",Eingaben!$F$6/2,Eingaben!$F$6)) | O27: =IF(Eingaben!$B$16="","",IF(N27<=12348,0,IF(N27<=17799,(914.51*((N27-12348)/10000)+1400)*((N27-12348)/10000),IF(N27<=69878,(181.19*((N27-17799)/10000)+2397)*((N27-17799)/10000)+1025.38,IF(N27<=277825,0.42*N27-10637.32,0.45*N27-18971.07))))) | P27: =IF(Eingaben!$B$16="","",IF(Eingaben!$D$6="Ja",MAX(0,Eingaben!$F$6+I27)/2,MAX(0,Eingaben!$F$6+I27))) | Q27: =IF(Eingaben!$B$16="","",IF(P27<=12348,0,IF(P27<=17799,(914.51*((P27-12348)/10000)+1400)*((P27-12348)/10000),IF(P27<=69878,(181.19*((P27-17799)/10000)+2397)*((P27-17799)/10000)+1025.38,IF(P27<=277825,0.42*P27-10637.32,0.45*P27-18971.07)))))
A28: 3 | B28: =IF(Eingaben!$B$16="","",Cashflow!B28) | C28: 4 | D28: =IF(Eingaben!$B$16="","",H27) | E28: =IF(Eingaben!$B$16="","",MIN(D28,MAX(0,IF(Eingaben!$S$16="Ja",D28*Eingaben!$T$16,Eingaben!$AD$16*Eingaben!$Q$16)))) | F28: =IF(Eingaben!$B$16="","",MIN(MAX(0,IF(AND(Eingaben!$U$16="Ja",4<=Eingaben!$W$16),Eingaben!$AD$16*Eingaben!$V$16,0)),MAX(0,D28-E28))) | G28: =IF(Eingaben!$B$16="","",E28+F28) | H28: =IF(Eingaben!$B$16="","",D28-G28) | I28: =IF(Eingaben!$B$16="","",Cashflow!E28-Cashflow!G28-G28) | J28: =IF(Eingaben!$B$16="","",IF(Eingaben!$D$6="Ja",2*MAX(0,O28),MAX(0,O28))) | K28: =IF(Eingaben!$B$16="","",IF(Eingaben!$D$6="Ja",2*MAX(0,Q28),MAX(0,Q28))) | L28: =IF(Eingaben!$B$16="","",IF(Eingaben!$D$5>0,J28-K28,-I28*Eingaben!$D$9)) | N28: =IF(Eingaben!$B$16="","",IF(Eingaben!$D$6="Ja",Eingaben!$F$6/2,Eingaben!$F$6)) | O28: =IF(Eingaben!$B$16="","",IF(N28<=12348,0,IF(N28<=17799,(914.51*((N28-12348)/10000)+1400)*((N28-12348)/10000),IF(N28<=69878,(181.19*((N28-17799)/10000)+2397)*((N28-17799)/10000)+1025.38,IF(N28<=277825,0.42*N28-10637.32,0.45*N28-18971.07))))) | P28: =IF(Eingaben!$B$16="","",IF(Eingaben!$D$6="Ja",MAX(0,Eingaben!$F$6+I28)/2,MAX(0,Eingaben!$F$6+I28))) | Q28: =IF(Eingaben!$B$16="","",IF(P28<=12348,0,IF(P28<=17799,(914.51*((P28-12348)/10000)+1400)*((P28-12348)/10000),IF(P28<=69878,(181.19*((P28-17799)/10000)+2397)*((P28-17799)/10000)+1025.38,IF(P28<=277825,0.42*P28-10637.32,0.45*P28-18971.07)))))
A29: 3 | B29: =IF(Eingaben!$B$16="","",Cashflow!B29) | C29: 5 | D29: =IF(Eingaben!$B$16="","",H28) | E29: =IF(Eingaben!$B$16="","",MIN(D29,MAX(0,IF(Eingaben!$S$16="Ja",D29*Eingaben!$T$16,Eingaben!$AD$16*Eingaben!$Q$16)))) | F29: =IF(Eingaben!$B$16="","",MIN(MAX(0,IF(AND(Eingaben!$U$16="Ja",5<=Eingaben!$W$16),Eingaben!$AD$16*Eingaben!$V$16,0)),MAX(0,D29-E29))) | G29: =IF(Eingaben!$B$16="","",E29+F29) | H29: =IF(Eingaben!$B$16="","",D29-G29) | I29: =IF(Eingaben!$B$16="","",Cashflow!E29-Cashflow!G29-G29) | J29: =IF(Eingaben!$B$16="","",IF(Eingaben!$D$6="Ja",2*MAX(0,O29),MAX(0,O29))) | K29: =IF(Eingaben!$B$16="","",IF(Eingaben!$D$6="Ja",2*MAX(0,Q29),MAX(0,Q29))) | L29: =IF(Eingaben!$B$16="","",IF(Eingaben!$D$5>0,J29-K29,-I29*Eingaben!$D$9)) | N29: =IF(Eingaben!$B$16="","",IF(Eingaben!$D$6="Ja",Eingaben!$F$6/2,Eingaben!$F$6)) | O29: =IF(Eingaben!$B$16="","",IF(N29<=12348,0,IF(N29<=17799,(914.51*((N29-12348)/10000)+1400)*((N29-12348)/10000),IF(N29<=69878,(181.19*((N29-17799)/10000)+2397)*((N29-17799)/10000)+1025.38,IF(N29<=277825,0.42*N29-10637.32,0.45*N29-18971.07))))) | P29: =IF(Eingaben!$B$16="","",IF(Eingaben!$D$6="Ja",MAX(0,Eingaben!$F$6+I29)/2,MAX(0,Eingaben!$F$6+I29))) | Q29: =IF(Eingaben!$B$16="","",IF(P29<=12348,0,IF(P29<=17799,(914.51*((P29-12348)/10000)+1400)*((P29-12348)/10000),IF(P29<=69878,(181.19*((P29-17799)/10000)+2397)*((P29-17799)/10000)+1025.38,IF(P29<=277825,0.42*P29-10637.32,0.45*P29-18971.07)))))
A30: 3 | B30: =IF(Eingaben!$B$16="","",Cashflow!B30) | C30: 6 | D30: =IF(Eingaben!$B$16="","",H29) | E30: =IF(Eingaben!$B$16="","",MIN(D30,MAX(0,IF(Eingaben!$S$16="Ja",D30*Eingaben!$T$16,Eingaben!$AD$16*Eingaben!$Q$16)))) | F30: =IF(Eingaben!$B$16="","",MIN(MAX(0,IF(AND(Eingaben!$U$16="Ja",6<=Eingaben!$W$16),Eingaben!$AD$16*Eingaben!$V$16,0)),MAX(0,D30-E30))) | G30: =IF(Eingaben!$B$16="","",E30+F30) | H30: =IF(Eingaben!$B$16="","",D30-G30) | I30: =IF(Eingaben!$B$16="","",Cashflow!E30-Cashflow!G30-G30) | J30: =IF(Eingaben!$B$16="","",IF(Eingaben!$D$6="Ja",2*MAX(0,O30),MAX(0,O30))) | K30: =IF(Eingaben!$B$16="","",IF(Eingaben!$D$6="Ja",2*MAX(0,Q30),MAX(0,Q30))) | L30: =IF(Eingaben!$B$16="","",IF(Eingaben!$D$5>0,J30-K30,-I30*Eingaben!$D$9)) | N30: =IF(Eingaben!$B$16="","",IF(Eingaben!$D$6="Ja",Eingaben!$F$6/2,Eingaben!$F$6)) | O30: =IF(Eingaben!$B$16="","",IF(N30<=12348,0,IF(N30<=17799,(914.51*((N30-12348)/10000)+1400)*((N30-12348)/10000),IF(N30<=69878,(181.19*((N30-17799)/10000)+2397)*((N30-17799)/10000)+1025.38,IF(N30<=277825,0.42*N30-10637.32,0.45*N30-18971.07))))) | P30: =IF(Eingaben!$B$16="","",IF(Eingaben!$D$6="Ja",MAX(0,Eingaben!$F$6+I30)/2,MAX(0,Eingaben!$F$6+I30))) | Q30: =IF(Eingaben!$B$16="","",IF(P30<=12348,0,IF(P30<=17799,(914.51*((P30-12348)/10000)+1400)*((P30-12348)/10000),IF(P30<=69878,(181.19*((P30-17799)/10000)+2397)*((P30-17799)/10000)+1025.38,IF(P30<=277825,0.42*P30-10637.32,0.45*P30-18971.07)))))
A31: 3 | B31: =IF(Eingaben!$B$16="","",Cashflow!B31) | C31: 7 | D31: =IF(Eingaben!$B$16="","",H30) | E31: =IF(Eingaben!$B$16="","",MIN(D31,MAX(0,IF(Eingaben!$S$16="Ja",D31*Eingaben!$T$16,Eingaben!$AD$16*Eingaben!$Q$16)))) | F31: =IF(Eingaben!$B$16="","",MIN(MAX(0,IF(AND(Eingaben!$U$16="Ja",7<=Eingaben!$W$16),Eingaben!$AD$16*Eingaben!$V$16,0)),MAX(0,D31-E31))) | G31: =IF(Eingaben!$B$16="","",E31+F31) | H31: =IF(Eingaben!$B$16="","",D31-G31) | I31: =IF(Eingaben!$B$16="","",Cashflow!E31-Cashflow!G31-G31) | J31: =IF(Eingaben!$B$16="","",IF(Eingaben!$D$6="Ja",2*MAX(0,O31),MAX(0,O31))) | K31: =IF(Eingaben!$B$16="","",IF(Eingaben!$D$6="Ja",2*MAX(0,Q31),MAX(0,Q31))) | L31: =IF(Eingaben!$B$16="","",IF(Eingaben!$D$5>0,J31-K31,-I31*Eingaben!$D$9)) | N31: =IF(Eingaben!$B$16="","",IF(Eingaben!$D$6="Ja",Eingaben!$F$6/2,Eingaben!$F$6)) | O31: =IF(Eingaben!$B$16="","",IF(N31<=12348,0,IF(N31<=17799,(914.51*((N31-12348)/10000)+1400)*((N31-12348)/10000),IF(N31<=69878,(181.19*((N31-17799)/10000)+2397)*((N31-17799)/10000)+1025.38,IF(N31<=277825,0.42*N31-10637.32,0.45*N31-18971.07))))) | P31: =IF(Eingaben!$B$16="","",IF(Eingaben!$D$6="Ja",MAX(0,Eingaben!$F$6+I31)/2,MAX(0,Eingaben!$F$6+I31))) | Q31: =IF(Eingaben!$B$16="","",IF(P31<=12348,0,IF(P31<=17799,(914.51*((P31-12348)/10000)+1400)*((P31-12348)/10000),IF(P31<=69878,(181.19*((P31-17799)/10000)+2397)*((P31-17799)/10000)+1025.38,IF(P31<=277825,0.42*P31-10637.32,0.45*P31-18971.07)))))
A32: 3 | B32: =IF(Eingaben!$B$16="","",Cashflow!B32) | C32: 8 | D32: =IF(Eingaben!$B$16="","",H31) | E32: =IF(Eingaben!$B$16="","",MIN(D32,MAX(0,IF(Eingaben!$S$16="Ja",D32*Eingaben!$T$16,Eingaben!$AD$16*Eingaben!$Q$16)))) | F32: =IF(Eingaben!$B$16="","",MIN(MAX(0,IF(AND(Eingaben!$U$16="Ja",8<=Eingaben!$W$16),Eingaben!$AD$16*Eingaben!$V$16,0)),MAX(0,D32-E32))) | G32: =IF(Eingaben!$B$16="","",E32+F32) | H32: =IF(Eingaben!$B$16="","",D32-G32) | I32: =IF(Eingaben!$B$16="","",Cashflow!E32-Cashflow!G32-G32) | J32: =IF(Eingaben!$B$16="","",IF(Eingaben!$D$6="Ja",2*MAX(0,O32),MAX(0,O32))) | K32: =IF(Eingaben!$B$16="","",IF(Eingaben!$D$6="Ja",2*MAX(0,Q32),MAX(0,Q32))) | L32: =IF(Eingaben!$B$16="","",IF(Eingaben!$D$5>0,J32-K32,-I32*Eingaben!$D$9)) | N32: =IF(Eingaben!$B$16="","",IF(Eingaben!$D$6="Ja",Eingaben!$F$6/2,Eingaben!$F$6)) | O32: =IF(Eingaben!$B$16="","",IF(N32<=12348,0,IF(N32<=17799,(914.51*((N32-12348)/10000)+1400)*((N32-12348)/10000),IF(N32<=69878,(181.19*((N32-17799)/10000)+2397)*((N32-17799)/10000)+1025.38,IF(N32<=277825,0.42*N32-10637.32,0.45*N32-18971.07))))) | P32: =IF(Eingaben!$B$16="","",IF(Eingaben!$D$6="Ja",MAX(0,Eingaben!$F$6+I32)/2,MAX(0,Eingaben!$F$6+I32))) | Q32: =IF(Eingaben!$B$16="","",IF(P32<=12348,0,IF(P32<=17799,(914.51*((P32-12348)/10000)+1400)*((P32-12348)/10000),IF(P32<=69878,(181.19*((P32-17799)/10000)+2397)*((P32-17799)/10000)+1025.38,IF(P32<=277825,0.42*P32-10637.32,0.45*P32-18971.07)))))
A33: 3 | B33: =IF(Eingaben!$B$16="","",Cashflow!B33) | C33: 9 | D33: =IF(Eingaben!$B$16="","",H32) | E33: =IF(Eingaben!$B$16="","",MIN(D33,MAX(0,IF(Eingaben!$S$16="Ja",D33*Eingaben!$T$16,Eingaben!$AD$16*Eingaben!$Q$16)))) | F33: =IF(Eingaben!$B$16="","",MIN(MAX(0,IF(AND(Eingaben!$U$16="Ja",9<=Eingaben!$W$16),Eingaben!$AD$16*Eingaben!$V$16,0)),MAX(0,D33-E33))) | G33: =IF(Eingaben!$B$16="","",E33+F33) | H33: =IF(Eingaben!$B$16="","",D33-G33) | I33: =IF(Eingaben!$B$16="","",Cashflow!E33-Cashflow!G33-G33) | J33: =IF(Eingaben!$B$16="","",IF(Eingaben!$D$6="Ja",2*MAX(0,O33),MAX(0,O33))) | K33: =IF(Eingaben!$B$16="","",IF(Eingaben!$D$6="Ja",2*MAX(0,Q33),MAX(0,Q33))) | L33: =IF(Eingaben!$B$16="","",IF(Eingaben!$D$5>0,J33-K33,-I33*Eingaben!$D$9)) | N33: =IF(Eingaben!$B$16="","",IF(Eingaben!$D$6="Ja",Eingaben!$F$6/2,Eingaben!$F$6)) | O33: =IF(Eingaben!$B$16="","",IF(N33<=12348,0,IF(N33<=17799,(914.51*((N33-12348)/10000)+1400)*((N33-12348)/10000),IF(N33<=69878,(181.19*((N33-17799)/10000)+2397)*((N33-17799)/10000)+1025.38,IF(N33<=277825,0.42*N33-10637.32,0.45*N33-18971.07))))) | P33: =IF(Eingaben!$B$16="","",IF(Eingaben!$D$6="Ja",MAX(0,Eingaben!$F$6+I33)/2,MAX(0,Eingaben!$F$6+I33))) | Q33: =IF(Eingaben!$B$16="","",IF(P33<=12348,0,IF(P33<=17799,(914.51*((P33-12348)/10000)+1400)*((P33-12348)/10000),IF(P33<=69878,(181.19*((P33-17799)/10000)+2397)*((P33-17799)/10000)+1025.38,IF(P33<=277825,0.42*P33-10637.32,0.45*P33-18971.07)))))
A34: 3 | B34: =IF(Eingaben!$B$16="","",Cashflow!B34) | C34: 10 | D34: =IF(Eingaben!$B$16="","",H33) | E34: =IF(Eingaben!$B$16="","",MIN(D34,MAX(0,IF(Eingaben!$S$16="Ja",D34*Eingaben!$T$16,Eingaben!$AD$16*Eingaben!$Q$16)))) | F34: =IF(Eingaben!$B$16="","",MIN(MAX(0,IF(AND(Eingaben!$U$16="Ja",10<=Eingaben!$W$16),Eingaben!$AD$16*Eingaben!$V$16,0)),MAX(0,D34-E34))) | G34: =IF(Eingaben!$B$16="","",E34+F34) | H34: =IF(Eingaben!$B$16="","",D34-G34) | I34: =IF(Eingaben!$B$16="","",Cashflow!E34-Cashflow!G34-G34) | J34: =IF(Eingaben!$B$16="","",IF(Eingaben!$D$6="Ja",2*MAX(0,O34),MAX(0,O34))) | K34: =IF(Eingaben!$B$16="","",IF(Eingaben!$D$6="Ja",2*MAX(0,Q34),MAX(0,Q34))) | L34: =IF(Eingaben!$B$16="","",IF(Eingaben!$D$5>0,J34-K34,-I34*Eingaben!$D$9)) | N34: =IF(Eingaben!$B$16="","",IF(Eingaben!$D$6="Ja",Eingaben!$F$6/2,Eingaben!$F$6)) | O34: =IF(Eingaben!$B$16="","",IF(N34<=12348,0,IF(N34<=17799,(914.51*((N34-12348)/10000)+1400)*((N34-12348)/10000),IF(N34<=69878,(181.19*((N34-17799)/10000)+2397)*((N34-17799)/10000)+1025.38,IF(N34<=277825,0.42*N34-10637.32,0.45*N34-18971.07))))) | P34: =IF(Eingaben!$B$16="","",IF(Eingaben!$D$6="Ja",MAX(0,Eingaben!$F$6+I34)/2,MAX(0,Eingaben!$F$6+I34))) | Q34: =IF(Eingaben!$B$16="","",IF(P34<=12348,0,IF(P34<=17799,(914.51*((P34-12348)/10000)+1400)*((P34-12348)/10000),IF(P34<=69878,(181.19*((P34-17799)/10000)+2397)*((P34-17799)/10000)+1025.38,IF(P34<=277825,0.42*P34-10637.32,0.45*P34-18971.07)))))
A35: 4 | B35: =IF(Eingaben!$B$17="","",Cashflow!B35) | C35: 1 | D35: =IF(Eingaben!$B$17="","",Eingaben!$AD$17) | E35: =IF(Eingaben!$B$17="","",MIN(D35,MAX(0,IF(Eingaben!$S$17="Ja",D35*Eingaben!$T$17,Eingaben!$AD$17*Eingaben!$Q$17)))) | F35: =IF(Eingaben!$B$17="","",MIN(MAX(0,IF(AND(Eingaben!$U$17="Ja",1<=Eingaben!$W$17),Eingaben!$AD$17*Eingaben!$V$17,0)),MAX(0,D35-E35))) | G35: =IF(Eingaben!$B$17="","",E35+F35) | H35: =IF(Eingaben!$B$17="","",D35-G35) | I35: =IF(Eingaben!$B$17="","",Cashflow!E35-Cashflow!G35-G35) | J35: =IF(Eingaben!$B$17="","",IF(Eingaben!$D$6="Ja",2*MAX(0,O35),MAX(0,O35))) | K35: =IF(Eingaben!$B$17="","",IF(Eingaben!$D$6="Ja",2*MAX(0,Q35),MAX(0,Q35))) | L35: =IF(Eingaben!$B$17="","",IF(Eingaben!$D$5>0,J35-K35,-I35*Eingaben!$D$9)) | N35: =IF(Eingaben!$B$17="","",IF(Eingaben!$D$6="Ja",Eingaben!$F$6/2,Eingaben!$F$6)) | O35: =IF(Eingaben!$B$17="","",IF(N35<=12348,0,IF(N35<=17799,(914.51*((N35-12348)/10000)+1400)*((N35-12348)/10000),IF(N35<=69878,(181.19*((N35-17799)/10000)+2397)*((N35-17799)/10000)+1025.38,IF(N35<=277825,0.42*N35-10637.32,0.45*N35-18971.07))))) | P35: =IF(Eingaben!$B$17="","",IF(Eingaben!$D$6="Ja",MAX(0,Eingaben!$F$6+I35)/2,MAX(0,Eingaben!$F$6+I35))) | Q35: =IF(Eingaben!$B$17="","",IF(P35<=12348,0,IF(P35<=17799,(914.51*((P35-12348)/10000)+1400)*((P35-12348)/10000),IF(P35<=69878,(181.19*((P35-17799)/10000)+2397)*((P35-17799)/10000)+1025.38,IF(P35<=277825,0.42*P35-10637.32,0.45*P35-18971.07)))))
A36: 4 | B36: =IF(Eingaben!$B$17="","",Cashflow!B36) | C36: 2 | D36: =IF(Eingaben!$B$17="","",H35) | E36: =IF(Eingaben!$B$17="","",MIN(D36,MAX(0,IF(Eingaben!$S$17="Ja",D36*Eingaben!$T$17,Eingaben!$AD$17*Eingaben!$Q$17)))) | F36: =IF(Eingaben!$B$17="","",MIN(MAX(0,IF(AND(Eingaben!$U$17="Ja",2<=Eingaben!$W$17),Eingaben!$AD$17*Eingaben!$V$17,0)),MAX(0,D36-E36))) | G36: =IF(Eingaben!$B$17="","",E36+F36) | H36: =IF(Eingaben!$B$17="","",D36-G36) | I36: =IF(Eingaben!$B$17="","",Cashflow!E36-Cashflow!G36-G36) | J36: =IF(Eingaben!$B$17="","",IF(Eingaben!$D$6="Ja",2*MAX(0,O36),MAX(0,O36))) | K36: =IF(Eingaben!$B$17="","",IF(Eingaben!$D$6="Ja",2*MAX(0,Q36),MAX(0,Q36))) | L36: =IF(Eingaben!$B$17="","",IF(Eingaben!$D$5>0,J36-K36,-I36*Eingaben!$D$9)) | N36: =IF(Eingaben!$B$17="","",IF(Eingaben!$D$6="Ja",Eingaben!$F$6/2,Eingaben!$F$6)) | O36: =IF(Eingaben!$B$17="","",IF(N36<=12348,0,IF(N36<=17799,(914.51*((N36-12348)/10000)+1400)*((N36-12348)/10000),IF(N36<=69878,(181.19*((N36-17799)/10000)+2397)*((N36-17799)/10000)+1025.38,IF(N36<=277825,0.42*N36-10637.32,0.45*N36-18971.07))))) | P36: =IF(Eingaben!$B$17="","",IF(Eingaben!$D$6="Ja",MAX(0,Eingaben!$F$6+I36)/2,MAX(0,Eingaben!$F$6+I36))) | Q36: =IF(Eingaben!$B$17="","",IF(P36<=12348,0,IF(P36<=17799,(914.51*((P36-12348)/10000)+1400)*((P36-12348)/10000),IF(P36<=69878,(181.19*((P36-17799)/10000)+2397)*((P36-17799)/10000)+1025.38,IF(P36<=277825,0.42*P36-10637.32,0.45*P36-18971.07)))))
A37: 4 | B37: =IF(Eingaben!$B$17="","",Cashflow!B37) | C37: 3 | D37: =IF(Eingaben!$B$17="","",H36) | E37: =IF(Eingaben!$B$17="","",MIN(D37,MAX(0,IF(Eingaben!$S$17="Ja",D37*Eingaben!$T$17,Eingaben!$AD$17*Eingaben!$Q$17)))) | F37: =IF(Eingaben!$B$17="","",MIN(MAX(0,IF(AND(Eingaben!$U$17="Ja",3<=Eingaben!$W$17),Eingaben!$AD$17*Eingaben!$V$17,0)),MAX(0,D37-E37))) | G37: =IF(Eingaben!$B$17="","",E37+F37) | H37: =IF(Eingaben!$B$17="","",D37-G37) | I37: =IF(Eingaben!$B$17="","",Cashflow!E37-Cashflow!G37-G37) | J37: =IF(Eingaben!$B$17="","",IF(Eingaben!$D$6="Ja",2*MAX(0,O37),MAX(0,O37))) | K37: =IF(Eingaben!$B$17="","",IF(Eingaben!$D$6="Ja",2*MAX(0,Q37),MAX(0,Q37))) | L37: =IF(Eingaben!$B$17="","",IF(Eingaben!$D$5>0,J37-K37,-I37*Eingaben!$D$9)) | N37: =IF(Eingaben!$B$17="","",IF(Eingaben!$D$6="Ja",Eingaben!$F$6/2,Eingaben!$F$6)) | O37: =IF(Eingaben!$B$17="","",IF(N37<=12348,0,IF(N37<=17799,(914.51*((N37-12348)/10000)+1400)*((N37-12348)/10000),IF(N37<=69878,(181.19*((N37-17799)/10000)+2397)*((N37-17799)/10000)+1025.38,IF(N37<=277825,0.42*N37-10637.32,0.45*N37-18971.07))))) | P37: =IF(Eingaben!$B$17="","",IF(Eingaben!$D$6="Ja",MAX(0,Eingaben!$F$6+I37)/2,MAX(0,Eingaben!$F$6+I37))) | Q37: =IF(Eingaben!$B$17="","",IF(P37<=12348,0,IF(P37<=17799,(914.51*((P37-12348)/10000)+1400)*((P37-12348)/10000),IF(P37<=69878,(181.19*((P37-17799)/10000)+2397)*((P37-17799)/10000)+1025.38,IF(P37<=277825,0.42*P37-10637.32,0.45*P37-18971.07)))))
A38: 4 | B38: =IF(Eingaben!$B$17="","",Cashflow!B38) | C38: 4 | D38: =IF(Eingaben!$B$17="","",H37) | E38: =IF(Eingaben!$B$17="","",MIN(D38,MAX(0,IF(Eingaben!$S$17="Ja",D38*Eingaben!$T$17,Eingaben!$AD$17*Eingaben!$Q$17)))) | F38: =IF(Eingaben!$B$17="","",MIN(MAX(0,IF(AND(Eingaben!$U$17="Ja",4<=Eingaben!$W$17),Eingaben!$AD$17*Eingaben!$V$17,0)),MAX(0,D38-E38))) | G38: =IF(Eingaben!$B$17="","",E38+F38) | H38: =IF(Eingaben!$B$17="","",D38-G38) | I38: =IF(Eingaben!$B$17="","",Cashflow!E38-Cashflow!G38-G38) | J38: =IF(Eingaben!$B$17="","",IF(Eingaben!$D$6="Ja",2*MAX(0,O38),MAX(0,O38))) | K38: =IF(Eingaben!$B$17="","",IF(Eingaben!$D$6="Ja",2*MAX(0,Q38),MAX(0,Q38))) | L38: =IF(Eingaben!$B$17="","",IF(Eingaben!$D$5>0,J38-K38,-I38*Eingaben!$D$9)) | N38: =IF(Eingaben!$B$17="","",IF(Eingaben!$D$6="Ja",Eingaben!$F$6/2,Eingaben!$F$6)) | O38: =IF(Eingaben!$B$17="","",IF(N38<=12348,0,IF(N38<=17799,(914.51*((N38-12348)/10000)+1400)*((N38-12348)/10000),IF(N38<=69878,(181.19*((N38-17799)/10000)+2397)*((N38-17799)/10000)+1025.38,IF(N38<=277825,0.42*N38-10637.32,0.45*N38-18971.07))))) | P38: =IF(Eingaben!$B$17="","",IF(Eingaben!$D$6="Ja",MAX(0,Eingaben!$F$6+I38)/2,MAX(0,Eingaben!$F$6+I38))) | Q38: =IF(Eingaben!$B$17="","",IF(P38<=12348,0,IF(P38<=17799,(914.51*((P38-12348)/10000)+1400)*((P38-12348)/10000),IF(P38<=69878,(181.19*((P38-17799)/10000)+2397)*((P38-17799)/10000)+1025.38,IF(P38<=277825,0.42*P38-10637.32,0.45*P38-18971.07)))))
A39: 4 | B39: =IF(Eingaben!$B$17="","",Cashflow!B39) | C39: 5 | D39: =IF(Eingaben!$B$17="","",H38) | E39: =IF(Eingaben!$B$17="","",MIN(D39,MAX(0,IF(Eingaben!$S$17="Ja",D39*Eingaben!$T$17,Eingaben!$AD$17*Eingaben!$Q$17)))) | F39: =IF(Eingaben!$B$17="","",MIN(MAX(0,IF(AND(Eingaben!$U$17="Ja",5<=Eingaben!$W$17),Eingaben!$AD$17*Eingaben!$V$17,0)),MAX(0,D39-E39))) | G39: =IF(Eingaben!$B$17="","",E39+F39) | H39: =IF(Eingaben!$B$17="","",D39-G39) | I39: =IF(Eingaben!$B$17="","",Cashflow!E39-Cashflow!G39-G39) | J39: =IF(Eingaben!$B$17="","",IF(Eingaben!$D$6="Ja",2*MAX(0,O39),MAX(0,O39))) | K39: =IF(Eingaben!$B$17="","",IF(Eingaben!$D$6="Ja",2*MAX(0,Q39),MAX(0,Q39))) | L39: =IF(Eingaben!$B$17="","",IF(Eingaben!$D$5>0,J39-K39,-I39*Eingaben!$D$9)) | N39: =IF(Eingaben!$B$17="","",IF(Eingaben!$D$6="Ja",Eingaben!$F$6/2,Eingaben!$F$6)) | O39: =IF(Eingaben!$B$17="","",IF(N39<=12348,0,IF(N39<=17799,(914.51*((N39-12348)/10000)+1400)*((N39-12348)/10000),IF(N39<=69878,(181.19*((N39-17799)/10000)+2397)*((N39-17799)/10000)+1025.38,IF(N39<=277825,0.42*N39-10637.32,0.45*N39-18971.07))))) | P39: =IF(Eingaben!$B$17="","",IF(Eingaben!$D$6="Ja",MAX(0,Eingaben!$F$6+I39)/2,MAX(0,Eingaben!$F$6+I39))) | Q39: =IF(Eingaben!$B$17="","",IF(P39<=12348,0,IF(P39<=17799,(914.51*((P39-12348)/10000)+1400)*((P39-12348)/10000),IF(P39<=69878,(181.19*((P39-17799)/10000)+2397)*((P39-17799)/10000)+1025.38,IF(P39<=277825,0.42*P39-10637.32,0.45*P39-18971.07)))))
A40: 4 | B40: =IF(Eingaben!$B$17="","",Cashflow!B40) | C40: 6 | D40: =IF(Eingaben!$B$17="","",H39) | E40: =IF(Eingaben!$B$17="","",MIN(D40,MAX(0,IF(Eingaben!$S$17="Ja",D40*Eingaben!$T$17,Eingaben!$AD$17*Eingaben!$Q$17)))) | F40: =IF(Eingaben!$B$17="","",MIN(MAX(0,IF(AND(Eingaben!$U$17="Ja",6<=Eingaben!$W$17),Eingaben!$AD$17*Eingaben!$V$17,0)),MAX(0,D40-E40))) | G40: =IF(Eingaben!$B$17="","",E40+F40) | H40: =IF(Eingaben!$B$17="","",D40-G40) | I40: =IF(Eingaben!$B$17="","",Cashflow!E40-Cashflow!G40-G40) | J40: =IF(Eingaben!$B$17="","",IF(Eingaben!$D$6="Ja",2*MAX(0,O40),MAX(0,O40))) | K40: =IF(Eingaben!$B$17="","",IF(Eingaben!$D$6="Ja",2*MAX(0,Q40),MAX(0,Q40))) | L40: =IF(Eingaben!$B$17="","",IF(Eingaben!$D$5>0,J40-K40,-I40*Eingaben!$D$9)) | N40: =IF(Eingaben!$B$17="","",IF(Eingaben!$D$6="Ja",Eingaben!$F$6/2,Eingaben!$F$6)) | O40: =IF(Eingaben!$B$17="","",IF(N40<=12348,0,IF(N40<=17799,(914.51*((N40-12348)/10000)+1400)*((N40-12348)/10000),IF(N40<=69878,(181.19*((N40-17799)/10000)+2397)*((N40-17799)/10000)+1025.38,IF(N40<=277825,0.42*N40-10637.32,0.45*N40-18971.07))))) | P40: =IF(Eingaben!$B$17="","",IF(Eingaben!$D$6="Ja",MAX(0,Eingaben!$F$6+I40)/2,MAX(0,Eingaben!$F$6+I40))) | Q40: =IF(Eingaben!$B$17="","",IF(P40<=12348,0,IF(P40<=17799,(914.51*((P40-12348)/10000)+1400)*((P40-12348)/10000),IF(P40<=69878,(181.19*((P40-17799)/10000)+2397)*((P40-17799)/10000)+1025.38,IF(P40<=277825,0.42*P40-10637.32,0.45*P40-18971.07)))))
A41: 4 | B41: =IF(Eingaben!$B$17="","",Cashflow!B41) | C41: 7 | D41: =IF(Eingaben!$B$17="","",H40) | E41: =IF(Eingaben!$B$17="","",MIN(D41,MAX(0,IF(Eingaben!$S$17="Ja",D41*Eingaben!$T$17,Eingaben!$AD$17*Eingaben!$Q$17)))) | F41: =IF(Eingaben!$B$17="","",MIN(MAX(0,IF(AND(Eingaben!$U$17="Ja",7<=Eingaben!$W$17),Eingaben!$AD$17*Eingaben!$V$17,0)),MAX(0,D41-E41))) | G41: =IF(Eingaben!$B$17="","",E41+F41) | H41: =IF(Eingaben!$B$17="","",D41-G41) | I41: =IF(Eingaben!$B$17="","",Cashflow!E41-Cashflow!G41-G41) | J41: =IF(Eingaben!$B$17="","",IF(Eingaben!$D$6="Ja",2*MAX(0,O41),MAX(0,O41))) | K41: =IF(Eingaben!$B$17="","",IF(Eingaben!$D$6="Ja",2*MAX(0,Q41),MAX(0,Q41))) | L41: =IF(Eingaben!$B$17="","",IF(Eingaben!$D$5>0,J41-K41,-I41*Eingaben!$D$9)) | N41: =IF(Eingaben!$B$17="","",IF(Eingaben!$D$6="Ja",Eingaben!$F$6/2,Eingaben!$F$6)) | O41: =IF(Eingaben!$B$17="","",IF(N41<=12348,0,IF(N41<=17799,(914.51*((N41-12348)/10000)+1400)*((N41-12348)/10000),IF(N41<=69878,(181.19*((N41-17799)/10000)+2397)*((N41-17799)/10000)+1025.38,IF(N41<=277825,0.42*N41-10637.32,0.45*N41-18971.07))))) | P41: =IF(Eingaben!$B$17="","",IF(Eingaben!$D$6="Ja",MAX(0,Eingaben!$F$6+I41)/2,MAX(0,Eingaben!$F$6+I41))) | Q41: =IF(Eingaben!$B$17="","",IF(P41<=12348,0,IF(P41<=17799,(914.51*((P41-12348)/10000)+1400)*((P41-12348)/10000),IF(P41<=69878,(181.19*((P41-17799)/10000)+2397)*((P41-17799)/10000)+1025.38,IF(P41<=277825,0.42*P41-10637.32,0.45*P41-18971.07)))))
A42: 4 | B42: =IF(Eingaben!$B$17="","",Cashflow!B42) | C42: 8 | D42: =IF(Eingaben!$B$17="","",H41) | E42: =IF(Eingaben!$B$17="","",MIN(D42,MAX(0,IF(Eingaben!$S$17="Ja",D42*Eingaben!$T$17,Eingaben!$AD$17*Eingaben!$Q$17)))) | F42: =IF(Eingaben!$B$17="","",MIN(MAX(0,IF(AND(Eingaben!$U$17="Ja",8<=Eingaben!$W$17),Eingaben!$AD$17*Eingaben!$V$17,0)),MAX(0,D42-E42))) | G42: =IF(Eingaben!$B$17="","",E42+F42) | H42: =IF(Eingaben!$B$17="","",D42-G42) | I42: =IF(Eingaben!$B$17="","",Cashflow!E42-Cashflow!G42-G42) | J42: =IF(Eingaben!$B$17="","",IF(Eingaben!$D$6="Ja",2*MAX(0,O42),MAX(0,O42))) | K42: =IF(Eingaben!$B$17="","",IF(Eingaben!$D$6="Ja",2*MAX(0,Q42),MAX(0,Q42))) | L42: =IF(Eingaben!$B$17="","",IF(Eingaben!$D$5>0,J42-K42,-I42*Eingaben!$D$9)) | N42: =IF(Eingaben!$B$17="","",IF(Eingaben!$D$6="Ja",Eingaben!$F$6/2,Eingaben!$F$6)) | O42: =IF(Eingaben!$B$17="","",IF(N42<=12348,0,IF(N42<=17799,(914.51*((N42-12348)/10000)+1400)*((N42-12348)/10000),IF(N42<=69878,(181.19*((N42-17799)/10000)+2397)*((N42-17799)/10000)+1025.38,IF(N42<=277825,0.42*N42-10637.32,0.45*N42-18971.07))))) | P42: =IF(Eingaben!$B$17="","",IF(Eingaben!$D$6="Ja",MAX(0,Eingaben!$F$6+I42)/2,MAX(0,Eingaben!$F$6+I42))) | Q42: =IF(Eingaben!$B$17="","",IF(P42<=12348,0,IF(P42<=17799,(914.51*((P42-12348)/10000)+1400)*((P42-12348)/10000),IF(P42<=69878,(181.19*((P42-17799)/10000)+2397)*((P42-17799)/10000)+1025.38,IF(P42<=277825,0.42*P42-10637.32,0.45*P42-18971.07)))))
A43: 4 | B43: =IF(Eingaben!$B$17="","",Cashflow!B43) | C43: 9 | D43: =IF(Eingaben!$B$17="","",H42) | E43: =IF(Eingaben!$B$17="","",MIN(D43,MAX(0,IF(Eingaben!$S$17="Ja",D43*Eingaben!$T$17,Eingaben!$AD$17*Eingaben!$Q$17)))) | F43: =IF(Eingaben!$B$17="","",MIN(MAX(0,IF(AND(Eingaben!$U$17="Ja",9<=Eingaben!$W$17),Eingaben!$AD$17*Eingaben!$V$17,0)),MAX(0,D43-E43))) | G43: =IF(Eingaben!$B$17="","",E43+F43) | H43: =IF(Eingaben!$B$17="","",D43-G43) | I43: =IF(Eingaben!$B$17="","",Cashflow!E43-Cashflow!G43-G43) | J43: =IF(Eingaben!$B$17="","",IF(Eingaben!$D$6="Ja",2*MAX(0,O43),MAX(0,O43))) | K43: =IF(Eingaben!$B$17="","",IF(Eingaben!$D$6="Ja",2*MAX(0,Q43),MAX(0,Q43))) | L43: =IF(Eingaben!$B$17="","",IF(Eingaben!$D$5>0,J43-K43,-I43*Eingaben!$D$9)) | N43: =IF(Eingaben!$B$17="","",IF(Eingaben!$D$6="Ja",Eingaben!$F$6/2,Eingaben!$F$6)) | O43: =IF(Eingaben!$B$17="","",IF(N43<=12348,0,IF(N43<=17799,(914.51*((N43-12348)/10000)+1400)*((N43-12348)/10000),IF(N43<=69878,(181.19*((N43-17799)/10000)+2397)*((N43-17799)/10000)+1025.38,IF(N43<=277825,0.42*N43-10637.32,0.45*N43-18971.07))))) | P43: =IF(Eingaben!$B$17="","",IF(Eingaben!$D$6="Ja",MAX(0,Eingaben!$F$6+I43)/2,MAX(0,Eingaben!$F$6+I43))) | Q43: =IF(Eingaben!$B$17="","",IF(P43<=12348,0,IF(P43<=17799,(914.51*((P43-12348)/10000)+1400)*((P43-12348)/10000),IF(P43<=69878,(181.19*((P43-17799)/10000)+2397)*((P43-17799)/10000)+1025.38,IF(P43<=277825,0.42*P43-10637.32,0.45*P43-18971.07)))))
A44: 4 | B44: =IF(Eingaben!$B$17="","",Cashflow!B44) | C44: 10 | D44: =IF(Eingaben!$B$17="","",H43) | E44: =IF(Eingaben!$B$17="","",MIN(D44,MAX(0,IF(Eingaben!$S$17="Ja",D44*Eingaben!$T$17,Eingaben!$AD$17*Eingaben!$Q$17)))) | F44: =IF(Eingaben!$B$17="","",MIN(MAX(0,IF(AND(Eingaben!$U$17="Ja",10<=Eingaben!$W$17),Eingaben!$AD$17*Eingaben!$V$17,0)),MAX(0,D44-E44))) | G44: =IF(Eingaben!$B$17="","",E44+F44) | H44: =IF(Eingaben!$B$17="","",D44-G44) | I44: =IF(Eingaben!$B$17="","",Cashflow!E44-Cashflow!G44-G44) | J44: =IF(Eingaben!$B$17="","",IF(Eingaben!$D$6="Ja",2*MAX(0,O44),MAX(0,O44))) | K44: =IF(Eingaben!$B$17="","",IF(Eingaben!$D$6="Ja",2*MAX(0,Q44),MAX(0,Q44))) | L44: =IF(Eingaben!$B$17="","",IF(Eingaben!$D$5>0,J44-K44,-I44*Eingaben!$D$9)) | N44: =IF(Eingaben!$B$17="","",IF(Eingaben!$D$6="Ja",Eingaben!$F$6/2,Eingaben!$F$6)) | O44: =IF(Eingaben!$B$17="","",IF(N44<=12348,0,IF(N44<=17799,(914.51*((N44-12348)/10000)+1400)*((N44-12348)/10000),IF(N44<=69878,(181.19*((N44-17799)/10000)+2397)*((N44-17799)/10000)+1025.38,IF(N44<=277825,0.42*N44-10637.32,0.45*N44-18971.07))))) | P44: =IF(Eingaben!$B$17="","",IF(Eingaben!$D$6="Ja",MAX(0,Eingaben!$F$6+I44)/2,MAX(0,Eingaben!$F$6+I44))) | Q44: =IF(Eingaben!$B$17="","",IF(P44<=12348,0,IF(P44<=17799,(914.51*((P44-12348)/10000)+1400)*((P44-12348)/10000),IF(P44<=69878,(181.19*((P44-17799)/10000)+2397)*((P44-17799)/10000)+1025.38,IF(P44<=277825,0.42*P44-10637.32,0.45*P44-18971.07)))))
A45: 5 | B45: =IF(Eingaben!$B$18="","",Cashflow!B45) | C45: 1 | D45: =IF(Eingaben!$B$18="","",Eingaben!$AD$18) | E45: =IF(Eingaben!$B$18="","",MIN(D45,MAX(0,IF(Eingaben!$S$18="Ja",D45*Eingaben!$T$18,Eingaben!$AD$18*Eingaben!$Q$18)))) | F45: =IF(Eingaben!$B$18="","",MIN(MAX(0,IF(AND(Eingaben!$U$18="Ja",1<=Eingaben!$W$18),Eingaben!$AD$18*Eingaben!$V$18,0)),MAX(0,D45-E45))) | G45: =IF(Eingaben!$B$18="","",E45+F45) | H45: =IF(Eingaben!$B$18="","",D45-G45) | I45: =IF(Eingaben!$B$18="","",Cashflow!E45-Cashflow!G45-G45) | J45: =IF(Eingaben!$B$18="","",IF(Eingaben!$D$6="Ja",2*MAX(0,O45),MAX(0,O45))) | K45: =IF(Eingaben!$B$18="","",IF(Eingaben!$D$6="Ja",2*MAX(0,Q45),MAX(0,Q45))) | L45: =IF(Eingaben!$B$18="","",IF(Eingaben!$D$5>0,J45-K45,-I45*Eingaben!$D$9)) | N45: =IF(Eingaben!$B$18="","",IF(Eingaben!$D$6="Ja",Eingaben!$F$6/2,Eingaben!$F$6)) | O45: =IF(Eingaben!$B$18="","",IF(N45<=12348,0,IF(N45<=17799,(914.51*((N45-12348)/10000)+1400)*((N45-12348)/10000),IF(N45<=69878,(181.19*((N45-17799)/10000)+2397)*((N45-17799)/10000)+1025.38,IF(N45<=277825,0.42*N45-10637.32,0.45*N45-18971.07))))) | P45: =IF(Eingaben!$B$18="","",IF(Eingaben!$D$6="Ja",MAX(0,Eingaben!$F$6+I45)/2,MAX(0,Eingaben!$F$6+I45))) | Q45: =IF(Eingaben!$B$18="","",IF(P45<=12348,0,IF(P45<=17799,(914.51*((P45-12348)/10000)+1400)*((P45-12348)/10000),IF(P45<=69878,(181.19*((P45-17799)/10000)+2397)*((P45-17799)/10000)+1025.38,IF(P45<=277825,0.42*P45-10637.32,0.45*P45-18971.07)))))
A46: 5 | B46: =IF(Eingaben!$B$18="","",Cashflow!B46) | C46: 2 | D46: =IF(Eingaben!$B$18="","",H45) | E46: =IF(Eingaben!$B$18="","",MIN(D46,MAX(0,IF(Eingaben!$S$18="Ja",D46*Eingaben!$T$18,Eingaben!$AD$18*Eingaben!$Q$18)))) | F46: =IF(Eingaben!$B$18="","",MIN(MAX(0,IF(AND(Eingaben!$U$18="Ja",2<=Eingaben!$W$18),Eingaben!$AD$18*Eingaben!$V$18,0)),MAX(0,D46-E46))) | G46: =IF(Eingaben!$B$18="","",E46+F46) | H46: =IF(Eingaben!$B$18="","",D46-G46) | I46: =IF(Eingaben!$B$18="","",Cashflow!E46-Cashflow!G46-G46) | J46: =IF(Eingaben!$B$18="","",IF(Eingaben!$D$6="Ja",2*MAX(0,O46),MAX(0,O46))) | K46: =IF(Eingaben!$B$18="","",IF(Eingaben!$D$6="Ja",2*MAX(0,Q46),MAX(0,Q46))) | L46: =IF(Eingaben!$B$18="","",IF(Eingaben!$D$5>0,J46-K46,-I46*Eingaben!$D$9)) | N46: =IF(Eingaben!$B$18="","",IF(Eingaben!$D$6="Ja",Eingaben!$F$6/2,Eingaben!$F$6)) | O46: =IF(Eingaben!$B$18="","",IF(N46<=12348,0,IF(N46<=17799,(914.51*((N46-12348)/10000)+1400)*((N46-12348)/10000),IF(N46<=69878,(181.19*((N46-17799)/10000)+2397)*((N46-17799)/10000)+1025.38,IF(N46<=277825,0.42*N46-10637.32,0.45*N46-18971.07))))) | P46: =IF(Eingaben!$B$18="","",IF(Eingaben!$D$6="Ja",MAX(0,Eingaben!$F$6+I46)/2,MAX(0,Eingaben!$F$6+I46))) | Q46: =IF(Eingaben!$B$18="","",IF(P46<=12348,0,IF(P46<=17799,(914.51*((P46-12348)/10000)+1400)*((P46-12348)/10000),IF(P46<=69878,(181.19*((P46-17799)/10000)+2397)*((P46-17799)/10000)+1025.38,IF(P46<=277825,0.42*P46-10637.32,0.45*P46-18971.07)))))
A47: 5 | B47: =IF(Eingaben!$B$18="","",Cashflow!B47) | C47: 3 | D47: =IF(Eingaben!$B$18="","",H46) | E47: =IF(Eingaben!$B$18="","",MIN(D47,MAX(0,IF(Eingaben!$S$18="Ja",D47*Eingaben!$T$18,Eingaben!$AD$18*Eingaben!$Q$18)))) | F47: =IF(Eingaben!$B$18="","",MIN(MAX(0,IF(AND(Eingaben!$U$18="Ja",3<=Eingaben!$W$18),Eingaben!$AD$18*Eingaben!$V$18,0)),MAX(0,D47-E47))) | G47: =IF(Eingaben!$B$18="","",E47+F47) | H47: =IF(Eingaben!$B$18="","",D47-G47) | I47: =IF(Eingaben!$B$18="","",Cashflow!E47-Cashflow!G47-G47) | J47: =IF(Eingaben!$B$18="","",IF(Eingaben!$D$6="Ja",2*MAX(0,O47),MAX(0,O47))) | K47: =IF(Eingaben!$B$18="","",IF(Eingaben!$D$6="Ja",2*MAX(0,Q47),MAX(0,Q47))) | L47: =IF(Eingaben!$B$18="","",IF(Eingaben!$D$5>0,J47-K47,-I47*Eingaben!$D$9)) | N47: =IF(Eingaben!$B$18="","",IF(Eingaben!$D$6="Ja",Eingaben!$F$6/2,Eingaben!$F$6)) | O47: =IF(Eingaben!$B$18="","",IF(N47<=12348,0,IF(N47<=17799,(914.51*((N47-12348)/10000)+1400)*((N47-12348)/10000),IF(N47<=69878,(181.19*((N47-17799)/10000)+2397)*((N47-17799)/10000)+1025.38,IF(N47<=277825,0.42*N47-10637.32,0.45*N47-18971.07))))) | P47: =IF(Eingaben!$B$18="","",IF(Eingaben!$D$6="Ja",MAX(0,Eingaben!$F$6+I47)/2,MAX(0,Eingaben!$F$6+I47))) | Q47: =IF(Eingaben!$B$18="","",IF(P47<=12348,0,IF(P47<=17799,(914.51*((P47-12348)/10000)+1400)*((P47-12348)/10000),IF(P47<=69878,(181.19*((P47-17799)/10000)+2397)*((P47-17799)/10000)+1025.38,IF(P47<=277825,0.42*P47-10637.32,0.45*P47-18971.07)))))
A48: 5 | B48: =IF(Eingaben!$B$18="","",Cashflow!B48) | C48: 4 | D48: =IF(Eingaben!$B$18="","",H47) | E48: =IF(Eingaben!$B$18="","",MIN(D48,MAX(0,IF(Eingaben!$S$18="Ja",D48*Eingaben!$T$18,Eingaben!$AD$18*Eingaben!$Q$18)))) | F48: =IF(Eingaben!$B$18="","",MIN(MAX(0,IF(AND(Eingaben!$U$18="Ja",4<=Eingaben!$W$18),Eingaben!$AD$18*Eingaben!$V$18,0)),MAX(0,D48-E48))) | G48: =IF(Eingaben!$B$18="","",E48+F48) | H48: =IF(Eingaben!$B$18="","",D48-G48) | I48: =IF(Eingaben!$B$18="","",Cashflow!E48-Cashflow!G48-G48) | J48: =IF(Eingaben!$B$18="","",IF(Eingaben!$D$6="Ja",2*MAX(0,O48),MAX(0,O48))) | K48: =IF(Eingaben!$B$18="","",IF(Eingaben!$D$6="Ja",2*MAX(0,Q48),MAX(0,Q48))) | L48: =IF(Eingaben!$B$18="","",IF(Eingaben!$D$5>0,J48-K48,-I48*Eingaben!$D$9)) | N48: =IF(Eingaben!$B$18="","",IF(Eingaben!$D$6="Ja",Eingaben!$F$6/2,Eingaben!$F$6)) | O48: =IF(Eingaben!$B$18="","",IF(N48<=12348,0,IF(N48<=17799,(914.51*((N48-12348)/10000)+1400)*((N48-12348)/10000),IF(N48<=69878,(181.19*((N48-17799)/10000)+2397)*((N48-17799)/10000)+1025.38,IF(N48<=277825,0.42*N48-10637.32,0.45*N48-18971.07))))) | P48: =IF(Eingaben!$B$18="","",IF(Eingaben!$D$6="Ja",MAX(0,Eingaben!$F$6+I48)/2,MAX(0,Eingaben!$F$6+I48))) | Q48: =IF(Eingaben!$B$18="","",IF(P48<=12348,0,IF(P48<=17799,(914.51*((P48-12348)/10000)+1400)*((P48-12348)/10000),IF(P48<=69878,(181.19*((P48-17799)/10000)+2397)*((P48-17799)/10000)+1025.38,IF(P48<=277825,0.42*P48-10637.32,0.45*P48-18971.07)))))
A49: 5 | B49: =IF(Eingaben!$B$18="","",Cashflow!B49) | C49: 5 | D49: =IF(Eingaben!$B$18="","",H48) | E49: =IF(Eingaben!$B$18="","",MIN(D49,MAX(0,IF(Eingaben!$S$18="Ja",D49*Eingaben!$T$18,Eingaben!$AD$18*Eingaben!$Q$18)))) | F49: =IF(Eingaben!$B$18="","",MIN(MAX(0,IF(AND(Eingaben!$U$18="Ja",5<=Eingaben!$W$18),Eingaben!$AD$18*Eingaben!$V$18,0)),MAX(0,D49-E49))) | G49: =IF(Eingaben!$B$18="","",E49+F49) | H49: =IF(Eingaben!$B$18="","",D49-G49) | I49: =IF(Eingaben!$B$18="","",Cashflow!E49-Cashflow!G49-G49) | J49: =IF(Eingaben!$B$18="","",IF(Eingaben!$D$6="Ja",2*MAX(0,O49),MAX(0,O49))) | K49: =IF(Eingaben!$B$18="","",IF(Eingaben!$D$6="Ja",2*MAX(0,Q49),MAX(0,Q49))) | L49: =IF(Eingaben!$B$18="","",IF(Eingaben!$D$5>0,J49-K49,-I49*Eingaben!$D$9)) | N49: =IF(Eingaben!$B$18="","",IF(Eingaben!$D$6="Ja",Eingaben!$F$6/2,Eingaben!$F$6)) | O49: =IF(Eingaben!$B$18="","",IF(N49<=12348,0,IF(N49<=17799,(914.51*((N49-12348)/10000)+1400)*((N49-12348)/10000),IF(N49<=69878,(181.19*((N49-17799)/10000)+2397)*((N49-17799)/10000)+1025.38,IF(N49<=277825,0.42*N49-10637.32,0.45*N49-18971.07))))) | P49: =IF(Eingaben!$B$18="","",IF(Eingaben!$D$6="Ja",MAX(0,Eingaben!$F$6+I49)/2,MAX(0,Eingaben!$F$6+I49))) | Q49: =IF(Eingaben!$B$18="","",IF(P49<=12348,0,IF(P49<=17799,(914.51*((P49-12348)/10000)+1400)*((P49-12348)/10000),IF(P49<=69878,(181.19*((P49-17799)/10000)+2397)*((P49-17799)/10000)+1025.38,IF(P49<=277825,0.42*P49-10637.32,0.45*P49-18971.07)))))
A50: 5 | B50: =IF(Eingaben!$B$18="","",Cashflow!B50) | C50: 6 | D50: =IF(Eingaben!$B$18="","",H49) | E50: =IF(Eingaben!$B$18="","",MIN(D50,MAX(0,IF(Eingaben!$S$18="Ja",D50*Eingaben!$T$18,Eingaben!$AD$18*Eingaben!$Q$18)))) | F50: =IF(Eingaben!$B$18="","",MIN(MAX(0,IF(AND(Eingaben!$U$18="Ja",6<=Eingaben!$W$18),Eingaben!$AD$18*Eingaben!$V$18,0)),MAX(0,D50-E50))) | G50: =IF(Eingaben!$B$18="","",E50+F50) | H50: =IF(Eingaben!$B$18="","",D50-G50) | I50: =IF(Eingaben!$B$18="","",Cashflow!E50-Cashflow!G50-G50) | J50: =IF(Eingaben!$B$18="","",IF(Eingaben!$D$6="Ja",2*MAX(0,O50),MAX(0,O50))) | K50: =IF(Eingaben!$B$18="","",IF(Eingaben!$D$6="Ja",2*MAX(0,Q50),MAX(0,Q50))) | L50: =IF(Eingaben!$B$18="","",IF(Eingaben!$D$5>0,J50-K50,-I50*Eingaben!$D$9)) | N50: =IF(Eingaben!$B$18="","",IF(Eingaben!$D$6="Ja",Eingaben!$F$6/2,Eingaben!$F$6)) | O50: =IF(Eingaben!$B$18="","",IF(N50<=12348,0,IF(N50<=17799,(914.51*((N50-12348)/10000)+1400)*((N50-12348)/10000),IF(N50<=69878,(181.19*((N50-17799)/10000)+2397)*((N50-17799)/10000)+1025.38,IF(N50<=277825,0.42*N50-10637.32,0.45*N50-18971.07))))) | P50: =IF(Eingaben!$B$18="","",IF(Eingaben!$D$6="Ja",MAX(0,Eingaben!$F$6+I50)/2,MAX(0,Eingaben!$F$6+I50))) | Q50: =IF(Eingaben!$B$18="","",IF(P50<=12348,0,IF(P50<=17799,(914.51*((P50-12348)/10000)+1400)*((P50-12348)/10000),IF(P50<=69878,(181.19*((P50-17799)/10000)+2397)*((P50-17799)/10000)+1025.38,IF(P50<=277825,0.42*P50-10637.32,0.45*P50-18971.07)))))
A51: 5 | B51: =IF(Eingaben!$B$18="","",Cashflow!B51) | C51: 7 | D51: =IF(Eingaben!$B$18="","",H50) | E51: =IF(Eingaben!$B$18="","",MIN(D51,MAX(0,IF(Eingaben!$S$18="Ja",D51*Eingaben!$T$18,Eingaben!$AD$18*Eingaben!$Q$18)))) | F51: =IF(Eingaben!$B$18="","",MIN(MAX(0,IF(AND(Eingaben!$U$18="Ja",7<=Eingaben!$W$18),Eingaben!$AD$18*Eingaben!$V$18,0)),MAX(0,D51-E51))) | G51: =IF(Eingaben!$B$18="","",E51+F51) | H51: =IF(Eingaben!$B$18="","",D51-G51) | I51: =IF(Eingaben!$B$18="","",Cashflow!E51-Cashflow!G51-G51) | J51: =IF(Eingaben!$B$18="","",IF(Eingaben!$D$6="Ja",2*MAX(0,O51),MAX(0,O51))) | K51: =IF(Eingaben!$B$18="","",IF(Eingaben!$D$6="Ja",2*MAX(0,Q51),MAX(0,Q51))) | L51: =IF(Eingaben!$B$18="","",IF(Eingaben!$D$5>0,J51-K51,-I51*Eingaben!$D$9)) | N51: =IF(Eingaben!$B$18="","",IF(Eingaben!$D$6="Ja",Eingaben!$F$6/2,Eingaben!$F$6)) | O51: =IF(Eingaben!$B$18="","",IF(N51<=12348,0,IF(N51<=17799,(914.51*((N51-12348)/10000)+1400)*((N51-12348)/10000),IF(N51<=69878,(181.19*((N51-17799)/10000)+2397)*((N51-17799)/10000)+1025.38,IF(N51<=277825,0.42*N51-10637.32,0.45*N51-18971.07))))) | P51: =IF(Eingaben!$B$18="","",IF(Eingaben!$D$6="Ja",MAX(0,Eingaben!$F$6+I51)/2,MAX(0,Eingaben!$F$6+I51))) | Q51: =IF(Eingaben!$B$18="","",IF(P51<=12348,0,IF(P51<=17799,(914.51*((P51-12348)/10000)+1400)*((P51-12348)/10000),IF(P51<=69878,(181.19*((P51-17799)/10000)+2397)*((P51-17799)/10000)+1025.38,IF(P51<=277825,0.42*P51-10637.32,0.45*P51-18971.07)))))
A52: 5 | B52: =IF(Eingaben!$B$18="","",Cashflow!B52) | C52: 8 | D52: =IF(Eingaben!$B$18="","",H51) | E52: =IF(Eingaben!$B$18="","",MIN(D52,MAX(0,IF(Eingaben!$S$18="Ja",D52*Eingaben!$T$18,Eingaben!$AD$18*Eingaben!$Q$18)))) | F52: =IF(Eingaben!$B$18="","",MIN(MAX(0,IF(AND(Eingaben!$U$18="Ja",8<=Eingaben!$W$18),Eingaben!$AD$18*Eingaben!$V$18,0)),MAX(0,D52-E52))) | G52: =IF(Eingaben!$B$18="","",E52+F52) | H52: =IF(Eingaben!$B$18="","",D52-G52) | I52: =IF(Eingaben!$B$18="","",Cashflow!E52-Cashflow!G52-G52) | J52: =IF(Eingaben!$B$18="","",IF(Eingaben!$D$6="Ja",2*MAX(0,O52),MAX(0,O52))) | K52: =IF(Eingaben!$B$18="","",IF(Eingaben!$D$6="Ja",2*MAX(0,Q52),MAX(0,Q52))) | L52: =IF(Eingaben!$B$18="","",IF(Eingaben!$D$5>0,J52-K52,-I52*Eingaben!$D$9)) | N52: =IF(Eingaben!$B$18="","",IF(Eingaben!$D$6="Ja",Eingaben!$F$6/2,Eingaben!$F$6)) | O52: =IF(Eingaben!$B$18="","",IF(N52<=12348,0,IF(N52<=17799,(914.51*((N52-12348)/10000)+1400)*((N52-12348)/10000),IF(N52<=69878,(181.19*((N52-17799)/10000)+2397)*((N52-17799)/10000)+1025.38,IF(N52<=277825,0.42*N52-10637.32,0.45*N52-18971.07))))) | P52: =IF(Eingaben!$B$18="","",IF(Eingaben!$D$6="Ja",MAX(0,Eingaben!$F$6+I52)/2,MAX(0,Eingaben!$F$6+I52))) | Q52: =IF(Eingaben!$B$18="","",IF(P52<=12348,0,IF(P52<=17799,(914.51*((P52-12348)/10000)+1400)*((P52-12348)/10000),IF(P52<=69878,(181.19*((P52-17799)/10000)+2397)*((P52-17799)/10000)+1025.38,IF(P52<=277825,0.42*P52-10637.32,0.45*P52-18971.07)))))
A53: 5 | B53: =IF(Eingaben!$B$18="","",Cashflow!B53) | C53: 9 | D53: =IF(Eingaben!$B$18="","",H52) | E53: =IF(Eingaben!$B$18="","",MIN(D53,MAX(0,IF(Eingaben!$S$18="Ja",D53*Eingaben!$T$18,Eingaben!$AD$18*Eingaben!$Q$18)))) | F53: =IF(Eingaben!$B$18="","",MIN(MAX(0,IF(AND(Eingaben!$U$18="Ja",9<=Eingaben!$W$18),Eingaben!$AD$18*Eingaben!$V$18,0)),MAX(0,D53-E53))) | G53: =IF(Eingaben!$B$18="","",E53+F53) | H53: =IF(Eingaben!$B$18="","",D53-G53) | I53: =IF(Eingaben!$B$18="","",Cashflow!E53-Cashflow!G53-G53) | J53: =IF(Eingaben!$B$18="","",IF(Eingaben!$D$6="Ja",2*MAX(0,O53),MAX(0,O53))) | K53: =IF(Eingaben!$B$18="","",IF(Eingaben!$D$6="Ja",2*MAX(0,Q53),MAX(0,Q53))) | L53: =IF(Eingaben!$B$18="","",IF(Eingaben!$D$5>0,J53-K53,-I53*Eingaben!$D$9)) | N53: =IF(Eingaben!$B$18="","",IF(Eingaben!$D$6="Ja",Eingaben!$F$6/2,Eingaben!$F$6)) | O53: =IF(Eingaben!$B$18="","",IF(N53<=12348,0,IF(N53<=17799,(914.51*((N53-12348)/10000)+1400)*((N53-12348)/10000),IF(N53<=69878,(181.19*((N53-17799)/10000)+2397)*((N53-17799)/10000)+1025.38,IF(N53<=277825,0.42*N53-10637.32,0.45*N53-18971.07))))) | P53: =IF(Eingaben!$B$18="","",IF(Eingaben!$D$6="Ja",MAX(0,Eingaben!$F$6+I53)/2,MAX(0,Eingaben!$F$6+I53))) | Q53: =IF(Eingaben!$B$18="","",IF(P53<=12348,0,IF(P53<=17799,(914.51*((P53-12348)/10000)+1400)*((P53-12348)/10000),IF(P53<=69878,(181.19*((P53-17799)/10000)+2397)*((P53-17799)/10000)+1025.38,IF(P53<=277825,0.42*P53-10637.32,0.45*P53-18971.07)))))
A54: 5 | B54: =IF(Eingaben!$B$18="","",Cashflow!B54) | C54: 10 | D54: =IF(Eingaben!$B$18="","",H53) | E54: =IF(Eingaben!$B$18="","",MIN(D54,MAX(0,IF(Eingaben!$S$18="Ja",D54*Eingaben!$T$18,Eingaben!$AD$18*Eingaben!$Q$18)))) | F54: =IF(Eingaben!$B$18="","",MIN(MAX(0,IF(AND(Eingaben!$U$18="Ja",10<=Eingaben!$W$18),Eingaben!$AD$18*Eingaben!$V$18,0)),MAX(0,D54-E54))) | G54: =IF(Eingaben!$B$18="","",E54+F54) | H54: =IF(Eingaben!$B$18="","",D54-G54) | I54: =IF(Eingaben!$B$18="","",Cashflow!E54-Cashflow!G54-G54) | J54: =IF(Eingaben!$B$18="","",IF(Eingaben!$D$6="Ja",2*MAX(0,O54),MAX(0,O54))) | K54: =IF(Eingaben!$B$18="","",IF(Eingaben!$D$6="Ja",2*MAX(0,Q54),MAX(0,Q54))) | L54: =IF(Eingaben!$B$18="","",IF(Eingaben!$D$5>0,J54-K54,-I54*Eingaben!$D$9)) | N54: =IF(Eingaben!$B$18="","",IF(Eingaben!$D$6="Ja",Eingaben!$F$6/2,Eingaben!$F$6)) | O54: =IF(Eingaben!$B$18="","",IF(N54<=12348,0,IF(N54<=17799,(914.51*((N54-12348)/10000)+1400)*((N54-12348)/10000),IF(N54<=69878,(181.19*((N54-17799)/10000)+2397)*((N54-17799)/10000)+1025.38,IF(N54<=277825,0.42*N54-10637.32,0.45*N54-18971.07))))) | P54: =IF(Eingaben!$B$18="","",IF(Eingaben!$D$6="Ja",MAX(0,Eingaben!$F$6+I54)/2,MAX(0,Eingaben!$F$6+I54))) | Q54: =IF(Eingaben!$B$18="","",IF(P54<=12348,0,IF(P54<=17799,(914.51*((P54-12348)/10000)+1400)*((P54-12348)/10000),IF(P54<=69878,(181.19*((P54-17799)/10000)+2397)*((P54-17799)/10000)+1025.38,IF(P54<=277825,0.42*P54-10637.32,0.45*P54-18971.07)))))
A55: 6 | B55: =IF(Eingaben!$B$19="","",Cashflow!B55) | C55: 1 | D55: =IF(Eingaben!$B$19="","",Eingaben!$AD$19) | E55: =IF(Eingaben!$B$19="","",MIN(D55,MAX(0,IF(Eingaben!$S$19="Ja",D55*Eingaben!$T$19,Eingaben!$AD$19*Eingaben!$Q$19)))) | F55: =IF(Eingaben!$B$19="","",MIN(MAX(0,IF(AND(Eingaben!$U$19="Ja",1<=Eingaben!$W$19),Eingaben!$AD$19*Eingaben!$V$19,0)),MAX(0,D55-E55))) | G55: =IF(Eingaben!$B$19="","",E55+F55) | H55: =IF(Eingaben!$B$19="","",D55-G55) | I55: =IF(Eingaben!$B$19="","",Cashflow!E55-Cashflow!G55-G55) | J55: =IF(Eingaben!$B$19="","",IF(Eingaben!$D$6="Ja",2*MAX(0,O55),MAX(0,O55))) | K55: =IF(Eingaben!$B$19="","",IF(Eingaben!$D$6="Ja",2*MAX(0,Q55),MAX(0,Q55))) | L55: =IF(Eingaben!$B$19="","",IF(Eingaben!$D$5>0,J55-K55,-I55*Eingaben!$D$9)) | N55: =IF(Eingaben!$B$19="","",IF(Eingaben!$D$6="Ja",Eingaben!$F$6/2,Eingaben!$F$6)) | O55: =IF(Eingaben!$B$19="","",IF(N55<=12348,0,IF(N55<=17799,(914.51*((N55-12348)/10000)+1400)*((N55-12348)/10000),IF(N55<=69878,(181.19*((N55-17799)/10000)+2397)*((N55-17799)/10000)+1025.38,IF(N55<=277825,0.42*N55-10637.32,0.45*N55-18971.07))))) | P55: =IF(Eingaben!$B$19="","",IF(Eingaben!$D$6="Ja",MAX(0,Eingaben!$F$6+I55)/2,MAX(0,Eingaben!$F$6+I55))) | Q55: =IF(Eingaben!$B$19="","",IF(P55<=12348,0,IF(P55<=17799,(914.51*((P55-12348)/10000)+1400)*((P55-12348)/10000),IF(P55<=69878,(181.19*((P55-17799)/10000)+2397)*((P55-17799)/10000)+1025.38,IF(P55<=277825,0.42*P55-10637.32,0.45*P55-18971.07)))))
A56: 6 | B56: =IF(Eingaben!$B$19="","",Cashflow!B56) | C56: 2 | D56: =IF(Eingaben!$B$19="","",H55) | E56: =IF(Eingaben!$B$19="","",MIN(D56,MAX(0,IF(Eingaben!$S$19="Ja",D56*Eingaben!$T$19,Eingaben!$AD$19*Eingaben!$Q$19)))) | F56: =IF(Eingaben!$B$19="","",MIN(MAX(0,IF(AND(Eingaben!$U$19="Ja",2<=Eingaben!$W$19),Eingaben!$AD$19*Eingaben!$V$19,0)),MAX(0,D56-E56))) | G56: =IF(Eingaben!$B$19="","",E56+F56) | H56: =IF(Eingaben!$B$19="","",D56-G56) | I56: =IF(Eingaben!$B$19="","",Cashflow!E56-Cashflow!G56-G56) | J56: =IF(Eingaben!$B$19="","",IF(Eingaben!$D$6="Ja",2*MAX(0,O56),MAX(0,O56))) | K56: =IF(Eingaben!$B$19="","",IF(Eingaben!$D$6="Ja",2*MAX(0,Q56),MAX(0,Q56))) | L56: =IF(Eingaben!$B$19="","",IF(Eingaben!$D$5>0,J56-K56,-I56*Eingaben!$D$9)) | N56: =IF(Eingaben!$B$19="","",IF(Eingaben!$D$6="Ja",Eingaben!$F$6/2,Eingaben!$F$6)) | O56: =IF(Eingaben!$B$19="","",IF(N56<=12348,0,IF(N56<=17799,(914.51*((N56-12348)/10000)+1400)*((N56-12348)/10000),IF(N56<=69878,(181.19*((N56-17799)/10000)+2397)*((N56-17799)/10000)+1025.38,IF(N56<=277825,0.42*N56-10637.32,0.45*N56-18971.07))))) | P56: =IF(Eingaben!$B$19="","",IF(Eingaben!$D$6="Ja",MAX(0,Eingaben!$F$6+I56)/2,MAX(0,Eingaben!$F$6+I56))) | Q56: =IF(Eingaben!$B$19="","",IF(P56<=12348,0,IF(P56<=17799,(914.51*((P56-12348)/10000)+1400)*((P56-12348)/10000),IF(P56<=69878,(181.19*((P56-17799)/10000)+2397)*((P56-17799)/10000)+1025.38,IF(P56<=277825,0.42*P56-10637.32,0.45*P56-18971.07)))))
A57: 6 | B57: =IF(Eingaben!$B$19="","",Cashflow!B57) | C57: 3 | D57: =IF(Eingaben!$B$19="","",H56) | E57: =IF(Eingaben!$B$19="","",MIN(D57,MAX(0,IF(Eingaben!$S$19="Ja",D57*Eingaben!$T$19,Eingaben!$AD$19*Eingaben!$Q$19)))) | F57: =IF(Eingaben!$B$19="","",MIN(MAX(0,IF(AND(Eingaben!$U$19="Ja",3<=Eingaben!$W$19),Eingaben!$AD$19*Eingaben!$V$19,0)),MAX(0,D57-E57))) | G57: =IF(Eingaben!$B$19="","",E57+F57) | H57: =IF(Eingaben!$B$19="","",D57-G57) | I57: =IF(Eingaben!$B$19="","",Cashflow!E57-Cashflow!G57-G57) | J57: =IF(Eingaben!$B$19="","",IF(Eingaben!$D$6="Ja",2*MAX(0,O57),MAX(0,O57))) | K57: =IF(Eingaben!$B$19="","",IF(Eingaben!$D$6="Ja",2*MAX(0,Q57),MAX(0,Q57))) | L57: =IF(Eingaben!$B$19="","",IF(Eingaben!$D$5>0,J57-K57,-I57*Eingaben!$D$9)) | N57: =IF(Eingaben!$B$19="","",IF(Eingaben!$D$6="Ja",Eingaben!$F$6/2,Eingaben!$F$6)) | O57: =IF(Eingaben!$B$19="","",IF(N57<=12348,0,IF(N57<=17799,(914.51*((N57-12348)/10000)+1400)*((N57-12348)/10000),IF(N57<=69878,(181.19*((N57-17799)/10000)+2397)*((N57-17799)/10000)+1025.38,IF(N57<=277825,0.42*N57-10637.32,0.45*N57-18971.07))))) | P57: =IF(Eingaben!$B$19="","",IF(Eingaben!$D$6="Ja",MAX(0,Eingaben!$F$6+I57)/2,MAX(0,Eingaben!$F$6+I57))) | Q57: =IF(Eingaben!$B$19="","",IF(P57<=12348,0,IF(P57<=17799,(914.51*((P57-12348)/10000)+1400)*((P57-12348)/10000),IF(P57<=69878,(181.19*((P57-17799)/10000)+2397)*((P57-17799)/10000)+1025.38,IF(P57<=277825,0.42*P57-10637.32,0.45*P57-18971.07)))))
A58: 6 | B58: =IF(Eingaben!$B$19="","",Cashflow!B58) | C58: 4 | D58: =IF(Eingaben!$B$19="","",H57) | E58: =IF(Eingaben!$B$19="","",MIN(D58,MAX(0,IF(Eingaben!$S$19="Ja",D58*Eingaben!$T$19,Eingaben!$AD$19*Eingaben!$Q$19)))) | F58: =IF(Eingaben!$B$19="","",MIN(MAX(0,IF(AND(Eingaben!$U$19="Ja",4<=Eingaben!$W$19),Eingaben!$AD$19*Eingaben!$V$19,0)),MAX(0,D58-E58))) | G58: =IF(Eingaben!$B$19="","",E58+F58) | H58: =IF(Eingaben!$B$19="","",D58-G58) | I58: =IF(Eingaben!$B$19="","",Cashflow!E58-Cashflow!G58-G58) | J58: =IF(Eingaben!$B$19="","",IF(Eingaben!$D$6="Ja",2*MAX(0,O58),MAX(0,O58))) | K58: =IF(Eingaben!$B$19="","",IF(Eingaben!$D$6="Ja",2*MAX(0,Q58),MAX(0,Q58))) | L58: =IF(Eingaben!$B$19="","",IF(Eingaben!$D$5>0,J58-K58,-I58*Eingaben!$D$9)) | N58: =IF(Eingaben!$B$19="","",IF(Eingaben!$D$6="Ja",Eingaben!$F$6/2,Eingaben!$F$6)) | O58: =IF(Eingaben!$B$19="","",IF(N58<=12348,0,IF(N58<=17799,(914.51*((N58-12348)/10000)+1400)*((N58-12348)/10000),IF(N58<=69878,(181.19*((N58-17799)/10000)+2397)*((N58-17799)/10000)+1025.38,IF(N58<=277825,0.42*N58-10637.32,0.45*N58-18971.07))))) | P58: =IF(Eingaben!$B$19="","",IF(Eingaben!$D$6="Ja",MAX(0,Eingaben!$F$6+I58)/2,MAX(0,Eingaben!$F$6+I58))) | Q58: =IF(Eingaben!$B$19="","",IF(P58<=12348,0,IF(P58<=17799,(914.51*((P58-12348)/10000)+1400)*((P58-12348)/10000),IF(P58<=69878,(181.19*((P58-17799)/10000)+2397)*((P58-17799)/10000)+1025.38,IF(P58<=277825,0.42*P58-10637.32,0.45*P58-18971.07)))))
A59: 6 | B59: =IF(Eingaben!$B$19="","",Cashflow!B59) | C59: 5 | D59: =IF(Eingaben!$B$19="","",H58) | E59: =IF(Eingaben!$B$19="","",MIN(D59,MAX(0,IF(Eingaben!$S$19="Ja",D59*Eingaben!$T$19,Eingaben!$AD$19*Eingaben!$Q$19)))) | F59: =IF(Eingaben!$B$19="","",MIN(MAX(0,IF(AND(Eingaben!$U$19="Ja",5<=Eingaben!$W$19),Eingaben!$AD$19*Eingaben!$V$19,0)),MAX(0,D59-E59))) | G59: =IF(Eingaben!$B$19="","",E59+F59) | H59: =IF(Eingaben!$B$19="","",D59-G59) | I59: =IF(Eingaben!$B$19="","",Cashflow!E59-Cashflow!G59-G59) | J59: =IF(Eingaben!$B$19="","",IF(Eingaben!$D$6="Ja",2*MAX(0,O59),MAX(0,O59))) | K59: =IF(Eingaben!$B$19="","",IF(Eingaben!$D$6="Ja",2*MAX(0,Q59),MAX(0,Q59))) | L59: =IF(Eingaben!$B$19="","",IF(Eingaben!$D$5>0,J59-K59,-I59*Eingaben!$D$9)) | N59: =IF(Eingaben!$B$19="","",IF(Eingaben!$D$6="Ja",Eingaben!$F$6/2,Eingaben!$F$6)) | O59: =IF(Eingaben!$B$19="","",IF(N59<=12348,0,IF(N59<=17799,(914.51*((N59-12348)/10000)+1400)*((N59-12348)/10000),IF(N59<=69878,(181.19*((N59-17799)/10000)+2397)*((N59-17799)/10000)+1025.38,IF(N59<=277825,0.42*N59-10637.32,0.45*N59-18971.07))))) | P59: =IF(Eingaben!$B$19="","",IF(Eingaben!$D$6="Ja",MAX(0,Eingaben!$F$6+I59)/2,MAX(0,Eingaben!$F$6+I59))) | Q59: =IF(Eingaben!$B$19="","",IF(P59<=12348,0,IF(P59<=17799,(914.51*((P59-12348)/10000)+1400)*((P59-12348)/10000),IF(P59<=69878,(181.19*((P59-17799)/10000)+2397)*((P59-17799)/10000)+1025.38,IF(P59<=277825,0.42*P59-10637.32,0.45*P59-18971.07)))))
A60: 6 | B60: =IF(Eingaben!$B$19="","",Cashflow!B60) | C60: 6 | D60: =IF(Eingaben!$B$19="","",H59) | E60: =IF(Eingaben!$B$19="","",MIN(D60,MAX(0,IF(Eingaben!$S$19="Ja",D60*Eingaben!$T$19,Eingaben!$AD$19*Eingaben!$Q$19)))) | F60: =IF(Eingaben!$B$19="","",MIN(MAX(0,IF(AND(Eingaben!$U$19="Ja",6<=Eingaben!$W$19),Eingaben!$AD$19*Eingaben!$V$19,0)),MAX(0,D60-E60))) | G60: =IF(Eingaben!$B$19="","",E60+F60) | H60: =IF(Eingaben!$B$19="","",D60-G60) | I60: =IF(Eingaben!$B$19="","",Cashflow!E60-Cashflow!G60-G60) | J60: =IF(Eingaben!$B$19="","",IF(Eingaben!$D$6="Ja",2*MAX(0,O60),MAX(0,O60))) | K60: =IF(Eingaben!$B$19="","",IF(Eingaben!$D$6="Ja",2*MAX(0,Q60),MAX(0,Q60))) | L60: =IF(Eingaben!$B$19="","",IF(Eingaben!$D$5>0,J60-K60,-I60*Eingaben!$D$9)) | N60: =IF(Eingaben!$B$19="","",IF(Eingaben!$D$6="Ja",Eingaben!$F$6/2,Eingaben!$F$6)) | O60: =IF(Eingaben!$B$19="","",IF(N60<=12348,0,IF(N60<=17799,(914.51*((N60-12348)/10000)+1400)*((N60-12348)/10000),IF(N60<=69878,(181.19*((N60-17799)/10000)+2397)*((N60-17799)/10000)+1025.38,IF(N60<=277825,0.42*N60-10637.32,0.45*N60-18971.07))))) | P60: =IF(Eingaben!$B$19="","",IF(Eingaben!$D$6="Ja",MAX(0,Eingaben!$F$6+I60)/2,MAX(0,Eingaben!$F$6+I60))) | Q60: =IF(Eingaben!$B$19="","",IF(P60<=12348,0,IF(P60<=17799,(914.51*((P60-12348)/10000)+1400)*((P60-12348)/10000),IF(P60<=69878,(181.19*((P60-17799)/10000)+2397)*((P60-17799)/10000)+1025.38,IF(P60<=277825,0.42*P60-10637.32,0.45*P60-18971.07)))))
A61: 6 | B61: =IF(Eingaben!$B$19="","",Cashflow!B61) | C61: 7 | D61: =IF(Eingaben!$B$19="","",H60) | E61: =IF(Eingaben!$B$19="","",MIN(D61,MAX(0,IF(Eingaben!$S$19="Ja",D61*Eingaben!$T$19,Eingaben!$AD$19*Eingaben!$Q$19)))) | F61: =IF(Eingaben!$B$19="","",MIN(MAX(0,IF(AND(Eingaben!$U$19="Ja",7<=Eingaben!$W$19),Eingaben!$AD$19*Eingaben!$V$19,0)),MAX(0,D61-E61))) | G61: =IF(Eingaben!$B$19="","",E61+F61) | H61: =IF(Eingaben!$B$19="","",D61-G61) | I61: =IF(Eingaben!$B$19="","",Cashflow!E61-Cashflow!G61-G61) | J61: =IF(Eingaben!$B$19="","",IF(Eingaben!$D$6="Ja",2*MAX(0,O61),MAX(0,O61))) | K61: =IF(Eingaben!$B$19="","",IF(Eingaben!$D$6="Ja",2*MAX(0,Q61),MAX(0,Q61))) | L61: =IF(Eingaben!$B$19="","",IF(Eingaben!$D$5>0,J61-K61,-I61*Eingaben!$D$9)) | N61: =IF(Eingaben!$B$19="","",IF(Eingaben!$D$6="Ja",Eingaben!$F$6/2,Eingaben!$F$6)) | O61: =IF(Eingaben!$B$19="","",IF(N61<=12348,0,IF(N61<=17799,(914.51*((N61-12348)/10000)+1400)*((N61-12348)/10000),IF(N61<=69878,(181.19*((N61-17799)/10000)+2397)*((N61-17799)/10000)+1025.38,IF(N61<=277825,0.42*N61-10637.32,0.45*N61-18971.07))))) | P61: =IF(Eingaben!$B$19="","",IF(Eingaben!$D$6="Ja",MAX(0,Eingaben!$F$6+I61)/2,MAX(0,Eingaben!$F$6+I61))) | Q61: =IF(Eingaben!$B$19="","",IF(P61<=12348,0,IF(P61<=17799,(914.51*((P61-12348)/10000)+1400)*((P61-12348)/10000),IF(P61<=69878,(181.19*((P61-17799)/10000)+2397)*((P61-17799)/10000)+1025.38,IF(P61<=277825,0.42*P61-10637.32,0.45*P61-18971.07)))))
A62: 6 | B62: =IF(Eingaben!$B$19="","",Cashflow!B62) | C62: 8 | D62: =IF(Eingaben!$B$19="","",H61) | E62: =IF(Eingaben!$B$19="","",MIN(D62,MAX(0,IF(Eingaben!$S$19="Ja",D62*Eingaben!$T$19,Eingaben!$AD$19*Eingaben!$Q$19)))) | F62: =IF(Eingaben!$B$19="","",MIN(MAX(0,IF(AND(Eingaben!$U$19="Ja",8<=Eingaben!$W$19),Eingaben!$AD$19*Eingaben!$V$19,0)),MAX(0,D62-E62))) | G62: =IF(Eingaben!$B$19="","",E62+F62) | H62: =IF(Eingaben!$B$19="","",D62-G62) | I62: =IF(Eingaben!$B$19="","",Cashflow!E62-Cashflow!G62-G62) | J62: =IF(Eingaben!$B$19="","",IF(Eingaben!$D$6="Ja",2*MAX(0,O62),MAX(0,O62))) | K62: =IF(Eingaben!$B$19="","",IF(Eingaben!$D$6="Ja",2*MAX(0,Q62),MAX(0,Q62))) | L62: =IF(Eingaben!$B$19="","",IF(Eingaben!$D$5>0,J62-K62,-I62*Eingaben!$D$9)) | N62: =IF(Eingaben!$B$19="","",IF(Eingaben!$D$6="Ja",Eingaben!$F$6/2,Eingaben!$F$6)) | O62: =IF(Eingaben!$B$19="","",IF(N62<=12348,0,IF(N62<=17799,(914.51*((N62-12348)/10000)+1400)*((N62-12348)/10000),IF(N62<=69878,(181.19*((N62-17799)/10000)+2397)*((N62-17799)/10000)+1025.38,IF(N62<=277825,0.42*N62-10637.32,0.45*N62-18971.07))))) | P62: =IF(Eingaben!$B$19="","",IF(Eingaben!$D$6="Ja",MAX(0,Eingaben!$F$6+I62)/2,MAX(0,Eingaben!$F$6+I62))) | Q62: =IF(Eingaben!$B$19="","",IF(P62<=12348,0,IF(P62<=17799,(914.51*((P62-12348)/10000)+1400)*((P62-12348)/10000),IF(P62<=69878,(181.19*((P62-17799)/10000)+2397)*((P62-17799)/10000)+1025.38,IF(P62<=277825,0.42*P62-10637.32,0.45*P62-18971.07)))))
A63: 6 | B63: =IF(Eingaben!$B$19="","",Cashflow!B63) | C63: 9 | D63: =IF(Eingaben!$B$19="","",H62) | E63: =IF(Eingaben!$B$19="","",MIN(D63,MAX(0,IF(Eingaben!$S$19="Ja",D63*Eingaben!$T$19,Eingaben!$AD$19*Eingaben!$Q$19)))) | F63: =IF(Eingaben!$B$19="","",MIN(MAX(0,IF(AND(Eingaben!$U$19="Ja",9<=Eingaben!$W$19),Eingaben!$AD$19*Eingaben!$V$19,0)),MAX(0,D63-E63))) | G63: =IF(Eingaben!$B$19="","",E63+F63) | H63: =IF(Eingaben!$B$19="","",D63-G63) | I63: =IF(Eingaben!$B$19="","",Cashflow!E63-Cashflow!G63-G63) | J63: =IF(Eingaben!$B$19="","",IF(Eingaben!$D$6="Ja",2*MAX(0,O63),MAX(0,O63))) | K63: =IF(Eingaben!$B$19="","",IF(Eingaben!$D$6="Ja",2*MAX(0,Q63),MAX(0,Q63))) | L63: =IF(Eingaben!$B$19="","",IF(Eingaben!$D$5>0,J63-K63,-I63*Eingaben!$D$9)) | N63: =IF(Eingaben!$B$19="","",IF(Eingaben!$D$6="Ja",Eingaben!$F$6/2,Eingaben!$F$6)) | O63: =IF(Eingaben!$B$19="","",IF(N63<=12348,0,IF(N63<=17799,(914.51*((N63-12348)/10000)+1400)*((N63-12348)/10000),IF(N63<=69878,(181.19*((N63-17799)/10000)+2397)*((N63-17799)/10000)+1025.38,IF(N63<=277825,0.42*N63-10637.32,0.45*N63-18971.07))))) | P63: =IF(Eingaben!$B$19="","",IF(Eingaben!$D$6="Ja",MAX(0,Eingaben!$F$6+I63)/2,MAX(0,Eingaben!$F$6+I63))) | Q63: =IF(Eingaben!$B$19="","",IF(P63<=12348,0,IF(P63<=17799,(914.51*((P63-12348)/10000)+1400)*((P63-12348)/10000),IF(P63<=69878,(181.19*((P63-17799)/10000)+2397)*((P63-17799)/10000)+1025.38,IF(P63<=277825,0.42*P63-10637.32,0.45*P63-18971.07)))))
A64: 6 | B64: =IF(Eingaben!$B$19="","",Cashflow!B64) | C64: 10 | D64: =IF(Eingaben!$B$19="","",H63) | E64: =IF(Eingaben!$B$19="","",MIN(D64,MAX(0,IF(Eingaben!$S$19="Ja",D64*Eingaben!$T$19,Eingaben!$AD$19*Eingaben!$Q$19)))) | F64: =IF(Eingaben!$B$19="","",MIN(MAX(0,IF(AND(Eingaben!$U$19="Ja",10<=Eingaben!$W$19),Eingaben!$AD$19*Eingaben!$V$19,0)),MAX(0,D64-E64))) | G64: =IF(Eingaben!$B$19="","",E64+F64) | H64: =IF(Eingaben!$B$19="","",D64-G64) | I64: =IF(Eingaben!$B$19="","",Cashflow!E64-Cashflow!G64-G64) | J64: =IF(Eingaben!$B$19="","",IF(Eingaben!$D$6="Ja",2*MAX(0,O64),MAX(0,O64))) | K64: =IF(Eingaben!$B$19="","",IF(Eingaben!$D$6="Ja",2*MAX(0,Q64),MAX(0,Q64))) | L64: =IF(Eingaben!$B$19="","",IF(Eingaben!$D$5>0,J64-K64,-I64*Eingaben!$D$9)) | N64: =IF(Eingaben!$B$19="","",IF(Eingaben!$D$6="Ja",Eingaben!$F$6/2,Eingaben!$F$6)) | O64: =IF(Eingaben!$B$19="","",IF(N64<=12348,0,IF(N64<=17799,(914.51*((N64-12348)/10000)+1400)*((N64-12348)/10000),IF(N64<=69878,(181.19*((N64-17799)/10000)+2397)*((N64-17799)/10000)+1025.38,IF(N64<=277825,0.42*N64-10637.32,0.45*N64-18971.07))))) | P64: =IF(Eingaben!$B$19="","",IF(Eingaben!$D$6="Ja",MAX(0,Eingaben!$F$6+I64)/2,MAX(0,Eingaben!$F$6+I64))) | Q64: =IF(Eingaben!$B$19="","",IF(P64<=12348,0,IF(P64<=17799,(914.51*((P64-12348)/10000)+1400)*((P64-12348)/10000),IF(P64<=69878,(181.19*((P64-17799)/10000)+2397)*((P64-17799)/10000)+1025.38,IF(P64<=277825,0.42*P64-10637.32,0.45*P64-18971.07)))))
A65: 7 | B65: =IF(Eingaben!$B$20="","",Cashflow!B65) | C65: 1 | D65: =IF(Eingaben!$B$20="","",Eingaben!$AD$20) | E65: =IF(Eingaben!$B$20="","",MIN(D65,MAX(0,IF(Eingaben!$S$20="Ja",D65*Eingaben!$T$20,Eingaben!$AD$20*Eingaben!$Q$20)))) | F65: =IF(Eingaben!$B$20="","",MIN(MAX(0,IF(AND(Eingaben!$U$20="Ja",1<=Eingaben!$W$20),Eingaben!$AD$20*Eingaben!$V$20,0)),MAX(0,D65-E65))) | G65: =IF(Eingaben!$B$20="","",E65+F65) | H65: =IF(Eingaben!$B$20="","",D65-G65) | I65: =IF(Eingaben!$B$20="","",Cashflow!E65-Cashflow!G65-G65) | J65: =IF(Eingaben!$B$20="","",IF(Eingaben!$D$6="Ja",2*MAX(0,O65),MAX(0,O65))) | K65: =IF(Eingaben!$B$20="","",IF(Eingaben!$D$6="Ja",2*MAX(0,Q65),MAX(0,Q65))) | L65: =IF(Eingaben!$B$20="","",IF(Eingaben!$D$5>0,J65-K65,-I65*Eingaben!$D$9)) | N65: =IF(Eingaben!$B$20="","",IF(Eingaben!$D$6="Ja",Eingaben!$F$6/2,Eingaben!$F$6)) | O65: =IF(Eingaben!$B$20="","",IF(N65<=12348,0,IF(N65<=17799,(914.51*((N65-12348)/10000)+1400)*((N65-12348)/10000),IF(N65<=69878,(181.19*((N65-17799)/10000)+2397)*((N65-17799)/10000)+1025.38,IF(N65<=277825,0.42*N65-10637.32,0.45*N65-18971.07))))) | P65: =IF(Eingaben!$B$20="","",IF(Eingaben!$D$6="Ja",MAX(0,Eingaben!$F$6+I65)/2,MAX(0,Eingaben!$F$6+I65))) | Q65: =IF(Eingaben!$B$20="","",IF(P65<=12348,0,IF(P65<=17799,(914.51*((P65-12348)/10000)+1400)*((P65-12348)/10000),IF(P65<=69878,(181.19*((P65-17799)/10000)+2397)*((P65-17799)/10000)+1025.38,IF(P65<=277825,0.42*P65-10637.32,0.45*P65-18971.07)))))
A66: 7 | B66: =IF(Eingaben!$B$20="","",Cashflow!B66) | C66: 2 | D66: =IF(Eingaben!$B$20="","",H65) | E66: =IF(Eingaben!$B$20="","",MIN(D66,MAX(0,IF(Eingaben!$S$20="Ja",D66*Eingaben!$T$20,Eingaben!$AD$20*Eingaben!$Q$20)))) | F66: =IF(Eingaben!$B$20="","",MIN(MAX(0,IF(AND(Eingaben!$U$20="Ja",2<=Eingaben!$W$20),Eingaben!$AD$20*Eingaben!$V$20,0)),MAX(0,D66-E66))) | G66: =IF(Eingaben!$B$20="","",E66+F66) | H66: =IF(Eingaben!$B$20="","",D66-G66) | I66: =IF(Eingaben!$B$20="","",Cashflow!E66-Cashflow!G66-G66) | J66: =IF(Eingaben!$B$20="","",IF(Eingaben!$D$6="Ja",2*MAX(0,O66),MAX(0,O66))) | K66: =IF(Eingaben!$B$20="","",IF(Eingaben!$D$6="Ja",2*MAX(0,Q66),MAX(0,Q66))) | L66: =IF(Eingaben!$B$20="","",IF(Eingaben!$D$5>0,J66-K66,-I66*Eingaben!$D$9)) | N66: =IF(Eingaben!$B$20="","",IF(Eingaben!$D$6="Ja",Eingaben!$F$6/2,Eingaben!$F$6)) | O66: =IF(Eingaben!$B$20="","",IF(N66<=12348,0,IF(N66<=17799,(914.51*((N66-12348)/10000)+1400)*((N66-12348)/10000),IF(N66<=69878,(181.19*((N66-17799)/10000)+2397)*((N66-17799)/10000)+1025.38,IF(N66<=277825,0.42*N66-10637.32,0.45*N66-18971.07))))) | P66: =IF(Eingaben!$B$20="","",IF(Eingaben!$D$6="Ja",MAX(0,Eingaben!$F$6+I66)/2,MAX(0,Eingaben!$F$6+I66))) | Q66: =IF(Eingaben!$B$20="","",IF(P66<=12348,0,IF(P66<=17799,(914.51*((P66-12348)/10000)+1400)*((P66-12348)/10000),IF(P66<=69878,(181.19*((P66-17799)/10000)+2397)*((P66-17799)/10000)+1025.38,IF(P66<=277825,0.42*P66-10637.32,0.45*P66-18971.07)))))
A67: 7 | B67: =IF(Eingaben!$B$20="","",Cashflow!B67) | C67: 3 | D67: =IF(Eingaben!$B$20="","",H66) | E67: =IF(Eingaben!$B$20="","",MIN(D67,MAX(0,IF(Eingaben!$S$20="Ja",D67*Eingaben!$T$20,Eingaben!$AD$20*Eingaben!$Q$20)))) | F67: =IF(Eingaben!$B$20="","",MIN(MAX(0,IF(AND(Eingaben!$U$20="Ja",3<=Eingaben!$W$20),Eingaben!$AD$20*Eingaben!$V$20,0)),MAX(0,D67-E67))) | G67: =IF(Eingaben!$B$20="","",E67+F67) | H67: =IF(Eingaben!$B$20="","",D67-G67) | I67: =IF(Eingaben!$B$20="","",Cashflow!E67-Cashflow!G67-G67) | J67: =IF(Eingaben!$B$20="","",IF(Eingaben!$D$6="Ja",2*MAX(0,O67),MAX(0,O67))) | K67: =IF(Eingaben!$B$20="","",IF(Eingaben!$D$6="Ja",2*MAX(0,Q67),MAX(0,Q67))) | L67: =IF(Eingaben!$B$20="","",IF(Eingaben!$D$5>0,J67-K67,-I67*Eingaben!$D$9)) | N67: =IF(Eingaben!$B$20="","",IF(Eingaben!$D$6="Ja",Eingaben!$F$6/2,Eingaben!$F$6)) | O67: =IF(Eingaben!$B$20="","",IF(N67<=12348,0,IF(N67<=17799,(914.51*((N67-12348)/10000)+1400)*((N67-12348)/10000),IF(N67<=69878,(181.19*((N67-17799)/10000)+2397)*((N67-17799)/10000)+1025.38,IF(N67<=277825,0.42*N67-10637.32,0.45*N67-18971.07))))) | P67: =IF(Eingaben!$B$20="","",IF(Eingaben!$D$6="Ja",MAX(0,Eingaben!$F$6+I67)/2,MAX(0,Eingaben!$F$6+I67))) | Q67: =IF(Eingaben!$B$20="","",IF(P67<=12348,0,IF(P67<=17799,(914.51*((P67-12348)/10000)+1400)*((P67-12348)/10000),IF(P67<=69878,(181.19*((P67-17799)/10000)+2397)*((P67-17799)/10000)+1025.38,IF(P67<=277825,0.42*P67-10637.32,0.45*P67-18971.07)))))
A68: 7 | B68: =IF(Eingaben!$B$20="","",Cashflow!B68) | C68: 4 | D68: =IF(Eingaben!$B$20="","",H67) | E68: =IF(Eingaben!$B$20="","",MIN(D68,MAX(0,IF(Eingaben!$S$20="Ja",D68*Eingaben!$T$20,Eingaben!$AD$20*Eingaben!$Q$20)))) | F68: =IF(Eingaben!$B$20="","",MIN(MAX(0,IF(AND(Eingaben!$U$20="Ja",4<=Eingaben!$W$20),Eingaben!$AD$20*Eingaben!$V$20,0)),MAX(0,D68-E68))) | G68: =IF(Eingaben!$B$20="","",E68+F68) | H68: =IF(Eingaben!$B$20="","",D68-G68) | I68: =IF(Eingaben!$B$20="","",Cashflow!E68-Cashflow!G68-G68) | J68: =IF(Eingaben!$B$20="","",IF(Eingaben!$D$6="Ja",2*MAX(0,O68),MAX(0,O68))) | K68: =IF(Eingaben!$B$20="","",IF(Eingaben!$D$6="Ja",2*MAX(0,Q68),MAX(0,Q68))) | L68: =IF(Eingaben!$B$20="","",IF(Eingaben!$D$5>0,J68-K68,-I68*Eingaben!$D$9)) | N68: =IF(Eingaben!$B$20="","",IF(Eingaben!$D$6="Ja",Eingaben!$F$6/2,Eingaben!$F$6)) | O68: =IF(Eingaben!$B$20="","",IF(N68<=12348,0,IF(N68<=17799,(914.51*((N68-12348)/10000)+1400)*((N68-12348)/10000),IF(N68<=69878,(181.19*((N68-17799)/10000)+2397)*((N68-17799)/10000)+1025.38,IF(N68<=277825,0.42*N68-10637.32,0.45*N68-18971.07))))) | P68: =IF(Eingaben!$B$20="","",IF(Eingaben!$D$6="Ja",MAX(0,Eingaben!$F$6+I68)/2,MAX(0,Eingaben!$F$6+I68))) | Q68: =IF(Eingaben!$B$20="","",IF(P68<=12348,0,IF(P68<=17799,(914.51*((P68-12348)/10000)+1400)*((P68-12348)/10000),IF(P68<=69878,(181.19*((P68-17799)/10000)+2397)*((P68-17799)/10000)+1025.38,IF(P68<=277825,0.42*P68-10637.32,0.45*P68-18971.07)))))
A69: 7 | B69: =IF(Eingaben!$B$20="","",Cashflow!B69) | C69: 5 | D69: =IF(Eingaben!$B$20="","",H68) | E69: =IF(Eingaben!$B$20="","",MIN(D69,MAX(0,IF(Eingaben!$S$20="Ja",D69*Eingaben!$T$20,Eingaben!$AD$20*Eingaben!$Q$20)))) | F69: =IF(Eingaben!$B$20="","",MIN(MAX(0,IF(AND(Eingaben!$U$20="Ja",5<=Eingaben!$W$20),Eingaben!$AD$20*Eingaben!$V$20,0)),MAX(0,D69-E69))) | G69: =IF(Eingaben!$B$20="","",E69+F69) | H69: =IF(Eingaben!$B$20="","",D69-G69) | I69: =IF(Eingaben!$B$20="","",Cashflow!E69-Cashflow!G69-G69) | J69: =IF(Eingaben!$B$20="","",IF(Eingaben!$D$6="Ja",2*MAX(0,O69),MAX(0,O69))) | K69: =IF(Eingaben!$B$20="","",IF(Eingaben!$D$6="Ja",2*MAX(0,Q69),MAX(0,Q69))) | L69: =IF(Eingaben!$B$20="","",IF(Eingaben!$D$5>0,J69-K69,-I69*Eingaben!$D$9)) | N69: =IF(Eingaben!$B$20="","",IF(Eingaben!$D$6="Ja",Eingaben!$F$6/2,Eingaben!$F$6)) | O69: =IF(Eingaben!$B$20="","",IF(N69<=12348,0,IF(N69<=17799,(914.51*((N69-12348)/10000)+1400)*((N69-12348)/10000),IF(N69<=69878,(181.19*((N69-17799)/10000)+2397)*((N69-17799)/10000)+1025.38,IF(N69<=277825,0.42*N69-10637.32,0.45*N69-18971.07))))) | P69: =IF(Eingaben!$B$20="","",IF(Eingaben!$D$6="Ja",MAX(0,Eingaben!$F$6+I69)/2,MAX(0,Eingaben!$F$6+I69))) | Q69: =IF(Eingaben!$B$20="","",IF(P69<=12348,0,IF(P69<=17799,(914.51*((P69-12348)/10000)+1400)*((P69-12348)/10000),IF(P69<=69878,(181.19*((P69-17799)/10000)+2397)*((P69-17799)/10000)+1025.38,IF(P69<=277825,0.42*P69-10637.32,0.45*P69-18971.07)))))
A70: 7 | B70: =IF(Eingaben!$B$20="","",Cashflow!B70) | C70: 6 | D70: =IF(Eingaben!$B$20="","",H69) | E70: =IF(Eingaben!$B$20="","",MIN(D70,MAX(0,IF(Eingaben!$S$20="Ja",D70*Eingaben!$T$20,Eingaben!$AD$20*Eingaben!$Q$20)))) | F70: =IF(Eingaben!$B$20="","",MIN(MAX(0,IF(AND(Eingaben!$U$20="Ja",6<=Eingaben!$W$20),Eingaben!$AD$20*Eingaben!$V$20,0)),MAX(0,D70-E70))) | G70: =IF(Eingaben!$B$20="","",E70+F70) | H70: =IF(Eingaben!$B$20="","",D70-G70) | I70: =IF(Eingaben!$B$20="","",Cashflow!E70-Cashflow!G70-G70) | J70: =IF(Eingaben!$B$20="","",IF(Eingaben!$D$6="Ja",2*MAX(0,O70),MAX(0,O70))) | K70: =IF(Eingaben!$B$20="","",IF(Eingaben!$D$6="Ja",2*MAX(0,Q70),MAX(0,Q70))) | L70: =IF(Eingaben!$B$20="","",IF(Eingaben!$D$5>0,J70-K70,-I70*Eingaben!$D$9)) | N70: =IF(Eingaben!$B$20="","",IF(Eingaben!$D$6="Ja",Eingaben!$F$6/2,Eingaben!$F$6)) | O70: =IF(Eingaben!$B$20="","",IF(N70<=12348,0,IF(N70<=17799,(914.51*((N70-12348)/10000)+1400)*((N70-12348)/10000),IF(N70<=69878,(181.19*((N70-17799)/10000)+2397)*((N70-17799)/10000)+1025.38,IF(N70<=277825,0.42*N70-10637.32,0.45*N70-18971.07))))) | P70: =IF(Eingaben!$B$20="","",IF(Eingaben!$D$6="Ja",MAX(0,Eingaben!$F$6+I70)/2,MAX(0,Eingaben!$F$6+I70))) | Q70: =IF(Eingaben!$B$20="","",IF(P70<=12348,0,IF(P70<=17799,(914.51*((P70-12348)/10000)+1400)*((P70-12348)/10000),IF(P70<=69878,(181.19*((P70-17799)/10000)+2397)*((P70-17799)/10000)+1025.38,IF(P70<=277825,0.42*P70-10637.32,0.45*P70-18971.07)))))
A71: 7 | B71: =IF(Eingaben!$B$20="","",Cashflow!B71) | C71: 7 | D71: =IF(Eingaben!$B$20="","",H70) | E71: =IF(Eingaben!$B$20="","",MIN(D71,MAX(0,IF(Eingaben!$S$20="Ja",D71*Eingaben!$T$20,Eingaben!$AD$20*Eingaben!$Q$20)))) | F71: =IF(Eingaben!$B$20="","",MIN(MAX(0,IF(AND(Eingaben!$U$20="Ja",7<=Eingaben!$W$20),Eingaben!$AD$20*Eingaben!$V$20,0)),MAX(0,D71-E71))) | G71: =IF(Eingaben!$B$20="","",E71+F71) | H71: =IF(Eingaben!$B$20="","",D71-G71) | I71: =IF(Eingaben!$B$20="","",Cashflow!E71-Cashflow!G71-G71) | J71: =IF(Eingaben!$B$20="","",IF(Eingaben!$D$6="Ja",2*MAX(0,O71),MAX(0,O71))) | K71: =IF(Eingaben!$B$20="","",IF(Eingaben!$D$6="Ja",2*MAX(0,Q71),MAX(0,Q71))) | L71: =IF(Eingaben!$B$20="","",IF(Eingaben!$D$5>0,J71-K71,-I71*Eingaben!$D$9)) | N71: =IF(Eingaben!$B$20="","",IF(Eingaben!$D$6="Ja",Eingaben!$F$6/2,Eingaben!$F$6)) | O71: =IF(Eingaben!$B$20="","",IF(N71<=12348,0,IF(N71<=17799,(914.51*((N71-12348)/10000)+1400)*((N71-12348)/10000),IF(N71<=69878,(181.19*((N71-17799)/10000)+2397)*((N71-17799)/10000)+1025.38,IF(N71<=277825,0.42*N71-10637.32,0.45*N71-18971.07))))) | P71: =IF(Eingaben!$B$20="","",IF(Eingaben!$D$6="Ja",MAX(0,Eingaben!$F$6+I71)/2,MAX(0,Eingaben!$F$6+I71))) | Q71: =IF(Eingaben!$B$20="","",IF(P71<=12348,0,IF(P71<=17799,(914.51*((P71-12348)/10000)+1400)*((P71-12348)/10000),IF(P71<=69878,(181.19*((P71-17799)/10000)+2397)*((P71-17799)/10000)+1025.38,IF(P71<=277825,0.42*P71-10637.32,0.45*P71-18971.07)))))
A72: 7 | B72: =IF(Eingaben!$B$20="","",Cashflow!B72) | C72: 8 | D72: =IF(Eingaben!$B$20="","",H71) | E72: =IF(Eingaben!$B$20="","",MIN(D72,MAX(0,IF(Eingaben!$S$20="Ja",D72*Eingaben!$T$20,Eingaben!$AD$20*Eingaben!$Q$20)))) | F72: =IF(Eingaben!$B$20="","",MIN(MAX(0,IF(AND(Eingaben!$U$20="Ja",8<=Eingaben!$W$20),Eingaben!$AD$20*Eingaben!$V$20,0)),MAX(0,D72-E72))) | G72: =IF(Eingaben!$B$20="","",E72+F72) | H72: =IF(Eingaben!$B$20="","",D72-G72) | I72: =IF(Eingaben!$B$20="","",Cashflow!E72-Cashflow!G72-G72) | J72: =IF(Eingaben!$B$20="","",IF(Eingaben!$D$6="Ja",2*MAX(0,O72),MAX(0,O72))) | K72: =IF(Eingaben!$B$20="","",IF(Eingaben!$D$6="Ja",2*MAX(0,Q72),MAX(0,Q72))) | L72: =IF(Eingaben!$B$20="","",IF(Eingaben!$D$5>0,J72-K72,-I72*Eingaben!$D$9)) | N72: =IF(Eingaben!$B$20="","",IF(Eingaben!$D$6="Ja",Eingaben!$F$6/2,Eingaben!$F$6)) | O72: =IF(Eingaben!$B$20="","",IF(N72<=12348,0,IF(N72<=17799,(914.51*((N72-12348)/10000)+1400)*((N72-12348)/10000),IF(N72<=69878,(181.19*((N72-17799)/10000)+2397)*((N72-17799)/10000)+1025.38,IF(N72<=277825,0.42*N72-10637.32,0.45*N72-18971.07))))) | P72: =IF(Eingaben!$B$20="","",IF(Eingaben!$D$6="Ja",MAX(0,Eingaben!$F$6+I72)/2,MAX(0,Eingaben!$F$6+I72))) | Q72: =IF(Eingaben!$B$20="","",IF(P72<=12348,0,IF(P72<=17799,(914.51*((P72-12348)/10000)+1400)*((P72-12348)/10000),IF(P72<=69878,(181.19*((P72-17799)/10000)+2397)*((P72-17799)/10000)+1025.38,IF(P72<=277825,0.42*P72-10637.32,0.45*P72-18971.07)))))
A73: 7 | B73: =IF(Eingaben!$B$20="","",Cashflow!B73) | C73: 9 | D73: =IF(Eingaben!$B$20="","",H72) | E73: =IF(Eingaben!$B$20="","",MIN(D73,MAX(0,IF(Eingaben!$S$20="Ja",D73*Eingaben!$T$20,Eingaben!$AD$20*Eingaben!$Q$20)))) | F73: =IF(Eingaben!$B$20="","",MIN(MAX(0,IF(AND(Eingaben!$U$20="Ja",9<=Eingaben!$W$20),Eingaben!$AD$20*Eingaben!$V$20,0)),MAX(0,D73-E73))) | G73: =IF(Eingaben!$B$20="","",E73+F73) | H73: =IF(Eingaben!$B$20="","",D73-G73) | I73: =IF(Eingaben!$B$20="","",Cashflow!E73-Cashflow!G73-G73) | J73: =IF(Eingaben!$B$20="","",IF(Eingaben!$D$6="Ja",2*MAX(0,O73),MAX(0,O73))) | K73: =IF(Eingaben!$B$20="","",IF(Eingaben!$D$6="Ja",2*MAX(0,Q73),MAX(0,Q73))) | L73: =IF(Eingaben!$B$20="","",IF(Eingaben!$D$5>0,J73-K73,-I73*Eingaben!$D$9)) | N73: =IF(Eingaben!$B$20="","",IF(Eingaben!$D$6="Ja",Eingaben!$F$6/2,Eingaben!$F$6)) | O73: =IF(Eingaben!$B$20="","",IF(N73<=12348,0,IF(N73<=17799,(914.51*((N73-12348)/10000)+1400)*((N73-12348)/10000),IF(N73<=69878,(181.19*((N73-17799)/10000)+2397)*((N73-17799)/10000)+1025.38,IF(N73<=277825,0.42*N73-10637.32,0.45*N73-18971.07))))) | P73: =IF(Eingaben!$B$20="","",IF(Eingaben!$D$6="Ja",MAX(0,Eingaben!$F$6+I73)/2,MAX(0,Eingaben!$F$6+I73))) | Q73: =IF(Eingaben!$B$20="","",IF(P73<=12348,0,IF(P73<=17799,(914.51*((P73-12348)/10000)+1400)*((P73-12348)/10000),IF(P73<=69878,(181.19*((P73-17799)/10000)+2397)*((P73-17799)/10000)+1025.38,IF(P73<=277825,0.42*P73-10637.32,0.45*P73-18971.07)))))
A74: 7 | B74: =IF(Eingaben!$B$20="","",Cashflow!B74) | C74: 10 | D74: =IF(Eingaben!$B$20="","",H73) | E74: =IF(Eingaben!$B$20="","",MIN(D74,MAX(0,IF(Eingaben!$S$20="Ja",D74*Eingaben!$T$20,Eingaben!$AD$20*Eingaben!$Q$20)))) | F74: =IF(Eingaben!$B$20="","",MIN(MAX(0,IF(AND(Eingaben!$U$20="Ja",10<=Eingaben!$W$20),Eingaben!$AD$20*Eingaben!$V$20,0)),MAX(0,D74-E74))) | G74: =IF(Eingaben!$B$20="","",E74+F74) | H74: =IF(Eingaben!$B$20="","",D74-G74) | I74: =IF(Eingaben!$B$20="","",Cashflow!E74-Cashflow!G74-G74) | J74: =IF(Eingaben!$B$20="","",IF(Eingaben!$D$6="Ja",2*MAX(0,O74),MAX(0,O74))) | K74: =IF(Eingaben!$B$20="","",IF(Eingaben!$D$6="Ja",2*MAX(0,Q74),MAX(0,Q74))) | L74: =IF(Eingaben!$B$20="","",IF(Eingaben!$D$5>0,J74-K74,-I74*Eingaben!$D$9)) | N74: =IF(Eingaben!$B$20="","",IF(Eingaben!$D$6="Ja",Eingaben!$F$6/2,Eingaben!$F$6)) | O74: =IF(Eingaben!$B$20="","",IF(N74<=12348,0,IF(N74<=17799,(914.51*((N74-12348)/10000)+1400)*((N74-12348)/10000),IF(N74<=69878,(181.19*((N74-17799)/10000)+2397)*((N74-17799)/10000)+1025.38,IF(N74<=277825,0.42*N74-10637.32,0.45*N74-18971.07))))) | P74: =IF(Eingaben!$B$20="","",IF(Eingaben!$D$6="Ja",MAX(0,Eingaben!$F$6+I74)/2,MAX(0,Eingaben!$F$6+I74))) | Q74: =IF(Eingaben!$B$20="","",IF(P74<=12348,0,IF(P74<=17799,(914.51*((P74-12348)/10000)+1400)*((P74-12348)/10000),IF(P74<=69878,(181.19*((P74-17799)/10000)+2397)*((P74-17799)/10000)+1025.38,IF(P74<=277825,0.42*P74-10637.32,0.45*P74-18971.07)))))
A75: 8 | B75: =IF(Eingaben!$B$21="","",Cashflow!B75) | C75: 1 | D75: =IF(Eingaben!$B$21="","",Eingaben!$AD$21) | E75: =IF(Eingaben!$B$21="","",MIN(D75,MAX(0,IF(Eingaben!$S$21="Ja",D75*Eingaben!$T$21,Eingaben!$AD$21*Eingaben!$Q$21)))) | F75: =IF(Eingaben!$B$21="","",MIN(MAX(0,IF(AND(Eingaben!$U$21="Ja",1<=Eingaben!$W$21),Eingaben!$AD$21*Eingaben!$V$21,0)),MAX(0,D75-E75))) | G75: =IF(Eingaben!$B$21="","",E75+F75) | H75: =IF(Eingaben!$B$21="","",D75-G75) | I75: =IF(Eingaben!$B$21="","",Cashflow!E75-Cashflow!G75-G75) | J75: =IF(Eingaben!$B$21="","",IF(Eingaben!$D$6="Ja",2*MAX(0,O75),MAX(0,O75))) | K75: =IF(Eingaben!$B$21="","",IF(Eingaben!$D$6="Ja",2*MAX(0,Q75),MAX(0,Q75))) | L75: =IF(Eingaben!$B$21="","",IF(Eingaben!$D$5>0,J75-K75,-I75*Eingaben!$D$9)) | N75: =IF(Eingaben!$B$21="","",IF(Eingaben!$D$6="Ja",Eingaben!$F$6/2,Eingaben!$F$6)) | O75: =IF(Eingaben!$B$21="","",IF(N75<=12348,0,IF(N75<=17799,(914.51*((N75-12348)/10000)+1400)*((N75-12348)/10000),IF(N75<=69878,(181.19*((N75-17799)/10000)+2397)*((N75-17799)/10000)+1025.38,IF(N75<=277825,0.42*N75-10637.32,0.45*N75-18971.07))))) | P75: =IF(Eingaben!$B$21="","",IF(Eingaben!$D$6="Ja",MAX(0,Eingaben!$F$6+I75)/2,MAX(0,Eingaben!$F$6+I75))) | Q75: =IF(Eingaben!$B$21="","",IF(P75<=12348,0,IF(P75<=17799,(914.51*((P75-12348)/10000)+1400)*((P75-12348)/10000),IF(P75<=69878,(181.19*((P75-17799)/10000)+2397)*((P75-17799)/10000)+1025.38,IF(P75<=277825,0.42*P75-10637.32,0.45*P75-18971.07)))))
A76: 8 | B76: =IF(Eingaben!$B$21="","",Cashflow!B76) | C76: 2 | D76: =IF(Eingaben!$B$21="","",H75) | E76: =IF(Eingaben!$B$21="","",MIN(D76,MAX(0,IF(Eingaben!$S$21="Ja",D76*Eingaben!$T$21,Eingaben!$AD$21*Eingaben!$Q$21)))) | F76: =IF(Eingaben!$B$21="","",MIN(MAX(0,IF(AND(Eingaben!$U$21="Ja",2<=Eingaben!$W$21),Eingaben!$AD$21*Eingaben!$V$21,0)),MAX(0,D76-E76))) | G76: =IF(Eingaben!$B$21="","",E76+F76) | H76: =IF(Eingaben!$B$21="","",D76-G76) | I76: =IF(Eingaben!$B$21="","",Cashflow!E76-Cashflow!G76-G76) | J76: =IF(Eingaben!$B$21="","",IF(Eingaben!$D$6="Ja",2*MAX(0,O76),MAX(0,O76))) | K76: =IF(Eingaben!$B$21="","",IF(Eingaben!$D$6="Ja",2*MAX(0,Q76),MAX(0,Q76))) | L76: =IF(Eingaben!$B$21="","",IF(Eingaben!$D$5>0,J76-K76,-I76*Eingaben!$D$9)) | N76: =IF(Eingaben!$B$21="","",IF(Eingaben!$D$6="Ja",Eingaben!$F$6/2,Eingaben!$F$6)) | O76: =IF(Eingaben!$B$21="","",IF(N76<=12348,0,IF(N76<=17799,(914.51*((N76-12348)/10000)+1400)*((N76-12348)/10000),IF(N76<=69878,(181.19*((N76-17799)/10000)+2397)*((N76-17799)/10000)+1025.38,IF(N76<=277825,0.42*N76-10637.32,0.45*N76-18971.07))))) | P76: =IF(Eingaben!$B$21="","",IF(Eingaben!$D$6="Ja",MAX(0,Eingaben!$F$6+I76)/2,MAX(0,Eingaben!$F$6+I76))) | Q76: =IF(Eingaben!$B$21="","",IF(P76<=12348,0,IF(P76<=17799,(914.51*((P76-12348)/10000)+1400)*((P76-12348)/10000),IF(P76<=69878,(181.19*((P76-17799)/10000)+2397)*((P76-17799)/10000)+1025.38,IF(P76<=277825,0.42*P76-10637.32,0.45*P76-18971.07)))))
A77: 8 | B77: =IF(Eingaben!$B$21="","",Cashflow!B77) | C77: 3 | D77: =IF(Eingaben!$B$21="","",H76) | E77: =IF(Eingaben!$B$21="","",MIN(D77,MAX(0,IF(Eingaben!$S$21="Ja",D77*Eingaben!$T$21,Eingaben!$AD$21*Eingaben!$Q$21)))) | F77: =IF(Eingaben!$B$21="","",MIN(MAX(0,IF(AND(Eingaben!$U$21="Ja",3<=Eingaben!$W$21),Eingaben!$AD$21*Eingaben!$V$21,0)),MAX(0,D77-E77))) | G77: =IF(Eingaben!$B$21="","",E77+F77) | H77: =IF(Eingaben!$B$21="","",D77-G77) | I77: =IF(Eingaben!$B$21="","",Cashflow!E77-Cashflow!G77-G77) | J77: =IF(Eingaben!$B$21="","",IF(Eingaben!$D$6="Ja",2*MAX(0,O77),MAX(0,O77))) | K77: =IF(Eingaben!$B$21="","",IF(Eingaben!$D$6="Ja",2*MAX(0,Q77),MAX(0,Q77))) | L77: =IF(Eingaben!$B$21="","",IF(Eingaben!$D$5>0,J77-K77,-I77*Eingaben!$D$9)) | N77: =IF(Eingaben!$B$21="","",IF(Eingaben!$D$6="Ja",Eingaben!$F$6/2,Eingaben!$F$6)) | O77: =IF(Eingaben!$B$21="","",IF(N77<=12348,0,IF(N77<=17799,(914.51*((N77-12348)/10000)+1400)*((N77-12348)/10000),IF(N77<=69878,(181.19*((N77-17799)/10000)+2397)*((N77-17799)/10000)+1025.38,IF(N77<=277825,0.42*N77-10637.32,0.45*N77-18971.07))))) | P77: =IF(Eingaben!$B$21="","",IF(Eingaben!$D$6="Ja",MAX(0,Eingaben!$F$6+I77)/2,MAX(0,Eingaben!$F$6+I77))) | Q77: =IF(Eingaben!$B$21="","",IF(P77<=12348,0,IF(P77<=17799,(914.51*((P77-12348)/10000)+1400)*((P77-12348)/10000),IF(P77<=69878,(181.19*((P77-17799)/10000)+2397)*((P77-17799)/10000)+1025.38,IF(P77<=277825,0.42*P77-10637.32,0.45*P77-18971.07)))))
A78: 8 | B78: =IF(Eingaben!$B$21="","",Cashflow!B78) | C78: 4 | D78: =IF(Eingaben!$B$21="","",H77) | E78: =IF(Eingaben!$B$21="","",MIN(D78,MAX(0,IF(Eingaben!$S$21="Ja",D78*Eingaben!$T$21,Eingaben!$AD$21*Eingaben!$Q$21)))) | F78: =IF(Eingaben!$B$21="","",MIN(MAX(0,IF(AND(Eingaben!$U$21="Ja",4<=Eingaben!$W$21),Eingaben!$AD$21*Eingaben!$V$21,0)),MAX(0,D78-E78))) | G78: =IF(Eingaben!$B$21="","",E78+F78) | H78: =IF(Eingaben!$B$21="","",D78-G78) | I78: =IF(Eingaben!$B$21="","",Cashflow!E78-Cashflow!G78-G78) | J78: =IF(Eingaben!$B$21="","",IF(Eingaben!$D$6="Ja",2*MAX(0,O78),MAX(0,O78))) | K78: =IF(Eingaben!$B$21="","",IF(Eingaben!$D$6="Ja",2*MAX(0,Q78),MAX(0,Q78))) | L78: =IF(Eingaben!$B$21="","",IF(Eingaben!$D$5>0,J78-K78,-I78*Eingaben!$D$9)) | N78: =IF(Eingaben!$B$21="","",IF(Eingaben!$D$6="Ja",Eingaben!$F$6/2,Eingaben!$F$6)) | O78: =IF(Eingaben!$B$21="","",IF(N78<=12348,0,IF(N78<=17799,(914.51*((N78-12348)/10000)+1400)*((N78-12348)/10000),IF(N78<=69878,(181.19*((N78-17799)/10000)+2397)*((N78-17799)/10000)+1025.38,IF(N78<=277825,0.42*N78-10637.32,0.45*N78-18971.07))))) | P78: =IF(Eingaben!$B$21="","",IF(Eingaben!$D$6="Ja",MAX(0,Eingaben!$F$6+I78)/2,MAX(0,Eingaben!$F$6+I78))) | Q78: =IF(Eingaben!$B$21="","",IF(P78<=12348,0,IF(P78<=17799,(914.51*((P78-12348)/10000)+1400)*((P78-12348)/10000),IF(P78<=69878,(181.19*((P78-17799)/10000)+2397)*((P78-17799)/10000)+1025.38,IF(P78<=277825,0.42*P78-10637.32,0.45*P78-18971.07)))))
A79: 8 | B79: =IF(Eingaben!$B$21="","",Cashflow!B79) | C79: 5 | D79: =IF(Eingaben!$B$21="","",H78) | E79: =IF(Eingaben!$B$21="","",MIN(D79,MAX(0,IF(Eingaben!$S$21="Ja",D79*Eingaben!$T$21,Eingaben!$AD$21*Eingaben!$Q$21)))) | F79: =IF(Eingaben!$B$21="","",MIN(MAX(0,IF(AND(Eingaben!$U$21="Ja",5<=Eingaben!$W$21),Eingaben!$AD$21*Eingaben!$V$21,0)),MAX(0,D79-E79))) | G79: =IF(Eingaben!$B$21="","",E79+F79) | H79: =IF(Eingaben!$B$21="","",D79-G79) | I79: =IF(Eingaben!$B$21="","",Cashflow!E79-Cashflow!G79-G79) | J79: =IF(Eingaben!$B$21="","",IF(Eingaben!$D$6="Ja",2*MAX(0,O79),MAX(0,O79))) | K79: =IF(Eingaben!$B$21="","",IF(Eingaben!$D$6="Ja",2*MAX(0,Q79),MAX(0,Q79))) | L79: =IF(Eingaben!$B$21="","",IF(Eingaben!$D$5>0,J79-K79,-I79*Eingaben!$D$9)) | N79: =IF(Eingaben!$B$21="","",IF(Eingaben!$D$6="Ja",Eingaben!$F$6/2,Eingaben!$F$6)) | O79: =IF(Eingaben!$B$21="","",IF(N79<=12348,0,IF(N79<=17799,(914.51*((N79-12348)/10000)+1400)*((N79-12348)/10000),IF(N79<=69878,(181.19*((N79-17799)/10000)+2397)*((N79-17799)/10000)+1025.38,IF(N79<=277825,0.42*N79-10637.32,0.45*N79-18971.07))))) | P79: =IF(Eingaben!$B$21="","",IF(Eingaben!$D$6="Ja",MAX(0,Eingaben!$F$6+I79)/2,MAX(0,Eingaben!$F$6+I79))) | Q79: =IF(Eingaben!$B$21="","",IF(P79<=12348,0,IF(P79<=17799,(914.51*((P79-12348)/10000)+1400)*((P79-12348)/10000),IF(P79<=69878,(181.19*((P79-17799)/10000)+2397)*((P79-17799)/10000)+1025.38,IF(P79<=277825,0.42*P79-10637.32,0.45*P79-18971.07)))))
A80: 8 | B80: =IF(Eingaben!$B$21="","",Cashflow!B80) | C80: 6 | D80: =IF(Eingaben!$B$21="","",H79) | E80: =IF(Eingaben!$B$21="","",MIN(D80,MAX(0,IF(Eingaben!$S$21="Ja",D80*Eingaben!$T$21,Eingaben!$AD$21*Eingaben!$Q$21)))) | F80: =IF(Eingaben!$B$21="","",MIN(MAX(0,IF(AND(Eingaben!$U$21="Ja",6<=Eingaben!$W$21),Eingaben!$AD$21*Eingaben!$V$21,0)),MAX(0,D80-E80))) | G80: =IF(Eingaben!$B$21="","",E80+F80) | H80: =IF(Eingaben!$B$21="","",D80-G80) | I80: =IF(Eingaben!$B$21="","",Cashflow!E80-Cashflow!G80-G80) | J80: =IF(Eingaben!$B$21="","",IF(Eingaben!$D$6="Ja",2*MAX(0,O80),MAX(0,O80))) | K80: =IF(Eingaben!$B$21="","",IF(Eingaben!$D$6="Ja",2*MAX(0,Q80),MAX(0,Q80))) | L80: =IF(Eingaben!$B$21="","",IF(Eingaben!$D$5>0,J80-K80,-I80*Eingaben!$D$9)) | N80: =IF(Eingaben!$B$21="","",IF(Eingaben!$D$6="Ja",Eingaben!$F$6/2,Eingaben!$F$6)) | O80: =IF(Eingaben!$B$21="","",IF(N80<=12348,0,IF(N80<=17799,(914.51*((N80-12348)/10000)+1400)*((N80-12348)/10000),IF(N80<=69878,(181.19*((N80-17799)/10000)+2397)*((N80-17799)/10000)+1025.38,IF(N80<=277825,0.42*N80-10637.32,0.45*N80-18971.07))))) | P80: =IF(Eingaben!$B$21="","",IF(Eingaben!$D$6="Ja",MAX(0,Eingaben!$F$6+I80)/2,MAX(0,Eingaben!$F$6+I80))) | Q80: =IF(Eingaben!$B$21="","",IF(P80<=12348,0,IF(P80<=17799,(914.51*((P80-12348)/10000)+1400)*((P80-12348)/10000),IF(P80<=69878,(181.19*((P80-17799)/10000)+2397)*((P80-17799)/10000)+1025.38,IF(P80<=277825,0.42*P80-10637.32,0.45*P80-18971.07)))))
A81: 8 | B81: =IF(Eingaben!$B$21="","",Cashflow!B81) | C81: 7 | D81: =IF(Eingaben!$B$21="","",H80) | E81: =IF(Eingaben!$B$21="","",MIN(D81,MAX(0,IF(Eingaben!$S$21="Ja",D81*Eingaben!$T$21,Eingaben!$AD$21*Eingaben!$Q$21)))) | F81: =IF(Eingaben!$B$21="","",MIN(MAX(0,IF(AND(Eingaben!$U$21="Ja",7<=Eingaben!$W$21),Eingaben!$AD$21*Eingaben!$V$21,0)),MAX(0,D81-E81))) | G81: =IF(Eingaben!$B$21="","",E81+F81) | H81: =IF(Eingaben!$B$21="","",D81-G81) | I81: =IF(Eingaben!$B$21="","",Cashflow!E81-Cashflow!G81-G81) | J81: =IF(Eingaben!$B$21="","",IF(Eingaben!$D$6="Ja",2*MAX(0,O81),MAX(0,O81))) | K81: =IF(Eingaben!$B$21="","",IF(Eingaben!$D$6="Ja",2*MAX(0,Q81),MAX(0,Q81))) | L81: =IF(Eingaben!$B$21="","",IF(Eingaben!$D$5>0,J81-K81,-I81*Eingaben!$D$9)) | N81: =IF(Eingaben!$B$21="","",IF(Eingaben!$D$6="Ja",Eingaben!$F$6/2,Eingaben!$F$6)) | O81: =IF(Eingaben!$B$21="","",IF(N81<=12348,0,IF(N81<=17799,(914.51*((N81-12348)/10000)+1400)*((N81-12348)/10000),IF(N81<=69878,(181.19*((N81-17799)/10000)+2397)*((N81-17799)/10000)+1025.38,IF(N81<=277825,0.42*N81-10637.32,0.45*N81-18971.07))))) | P81: =IF(Eingaben!$B$21="","",IF(Eingaben!$D$6="Ja",MAX(0,Eingaben!$F$6+I81)/2,MAX(0,Eingaben!$F$6+I81))) | Q81: =IF(Eingaben!$B$21="","",IF(P81<=12348,0,IF(P81<=17799,(914.51*((P81-12348)/10000)+1400)*((P81-12348)/10000),IF(P81<=69878,(181.19*((P81-17799)/10000)+2397)*((P81-17799)/10000)+1025.38,IF(P81<=277825,0.42*P81-10637.32,0.45*P81-18971.07)))))
A82: 8 | B82: =IF(Eingaben!$B$21="","",Cashflow!B82) | C82: 8 | D82: =IF(Eingaben!$B$21="","",H81) | E82: =IF(Eingaben!$B$21="","",MIN(D82,MAX(0,IF(Eingaben!$S$21="Ja",D82*Eingaben!$T$21,Eingaben!$AD$21*Eingaben!$Q$21)))) | F82: =IF(Eingaben!$B$21="","",MIN(MAX(0,IF(AND(Eingaben!$U$21="Ja",8<=Eingaben!$W$21),Eingaben!$AD$21*Eingaben!$V$21,0)),MAX(0,D82-E82))) | G82: =IF(Eingaben!$B$21="","",E82+F82) | H82: =IF(Eingaben!$B$21="","",D82-G82) | I82: =IF(Eingaben!$B$21="","",Cashflow!E82-Cashflow!G82-G82) | J82: =IF(Eingaben!$B$21="","",IF(Eingaben!$D$6="Ja",2*MAX(0,O82),MAX(0,O82))) | K82: =IF(Eingaben!$B$21="","",IF(Eingaben!$D$6="Ja",2*MAX(0,Q82),MAX(0,Q82))) | L82: =IF(Eingaben!$B$21="","",IF(Eingaben!$D$5>0,J82-K82,-I82*Eingaben!$D$9)) | N82: =IF(Eingaben!$B$21="","",IF(Eingaben!$D$6="Ja",Eingaben!$F$6/2,Eingaben!$F$6)) | O82: =IF(Eingaben!$B$21="","",IF(N82<=12348,0,IF(N82<=17799,(914.51*((N82-12348)/10000)+1400)*((N82-12348)/10000),IF(N82<=69878,(181.19*((N82-17799)/10000)+2397)*((N82-17799)/10000)+1025.38,IF(N82<=277825,0.42*N82-10637.32,0.45*N82-18971.07))))) | P82: =IF(Eingaben!$B$21="","",IF(Eingaben!$D$6="Ja",MAX(0,Eingaben!$F$6+I82)/2,MAX(0,Eingaben!$F$6+I82))) | Q82: =IF(Eingaben!$B$21="","",IF(P82<=12348,0,IF(P82<=17799,(914.51*((P82-12348)/10000)+1400)*((P82-12348)/10000),IF(P82<=69878,(181.19*((P82-17799)/10000)+2397)*((P82-17799)/10000)+1025.38,IF(P82<=277825,0.42*P82-10637.32,0.45*P82-18971.07)))))
